Workbook

Sheet Annahmen
A1: TÆLLA · Read Layer · SOMNIO — Ertragsmodell (Stand 24.10.2026, CFO)
A2: Blau = änderbare Eingabe, gelb hinterlegt = Szenario-Treiber, schwarz = Formel. Monat 1 = 01/2027, 24 Monate. Alle Beträge in EUR netto, sofern nicht anders angegeben. Szenarien: B = vorsichtig, C = mittel, D = stark.
A4: Treiber | B4: vorsichtig | C4: mittel | D4: stark | E4: Einheit | F4: Quelle / Begründung
A6: ALLGEMEIN
A7: Wechselkurs EUR/USD | B7: 1.1193 | E7: USD je EUR | F7: EZB-Referenzkurs 23.10.2026, ecb.europa.eu
A8: MwSt App-Abo/Patenschaft (B2C) | B8: 0.19 | E8: Anteil | F8: Annahme Regelsatz – Steuerberater prüfen
A9: MwSt E-Book/Hörbuch (SOMNIO) | B9: 0.07 | E9: Anteil | F9: Annahme ermäßigter Satz elektronische Publikationen – Steuerberater prüfen
A10: Kalk. Stundensatz manuelle Prüfung | B10: 60 | E10: €/h | F10: Vorschlag CFO (Grundlage Schnitt-Aufschlag)
A12: KOSTENBASIS (aus Projektdokumenten, USD)
A13: Text EN+DE (DeepSeek, Stages 200–420) | B13: 0.09 | E13: $/1.000 Wörter | F13: TECHNIK.md Abschn. 2; PROJEKTSTAND 11.10.
A14: Basis-Audio Chatterbox (Modal L4) | B14: 0.94 | E14: $/Audio-h | F14: TECHNIK.md; PROJEKTSTAND 15.10. (2,48 $ / 2,65 h)
A15: Premium-Audio Gemini ab 01.01.2027 | B15: 1.62 | E15: $/Audio-h | F15: TECHNIK.md (0,81 $ × 2 ab 2027)
A16: Wortzeiten MMS_FA (Modal) | B16: =0.034/(13.4/60) -> 0.15223881 | E16: $/Audio-h | F16: PIPELINE.md Smoke Lauf 5: Stage 520 0,0340 $ für 13,4 Audio-min
A17: Hörspiel-VC Chatterbox | B17: 0.5 | E17: $/Werk | F17: TECHNIK.md; PROJEKTSTAND 14.10.
A18: Hörspiel Sprecherzuordnung 57b (DeepSeek Pro) | B18: 1 | E18: $/Werk | F18: PROJEKTSTAND 12.10. (~1 $/Roman)
A19: Hörspiel Trennungsmessung (Modal T4) | B19: 0.03 | E19: $/Werk | F19: PROJEKTSTAND 16.10.
A20: Text einsprachig (Import/Tagging 200+210) | B20: =(0.0031+0.0021)/1.339 -> 0.0038834951 | E20: $/1.000 Wörter | F20: PIPELINE.md Smoke Lauf 5 (1.339 Wörter)
A21: Wörter je Audio-Stunde | B21: 9300 | E21: Wörter/h | F21: ACX: ~9.300 Wörter je fertiger Stunde (acx.com); Smoke-Kalibrierung unten
A22: Ø Wörter je Katalogwerk (PD) | B22: =18600000/187 -> 99465.241 | E22: Wörter | F22: PROJEKTSTAND: 187 Werke / 18,6 Mio. Wörter
A23: Ø Wörter je Verlagstitel | B23: 80000 | E23: Wörter | F23: Pilot-Obergrenze AP_cockpit_v2
A24: Wörter je Normseite (1.800 Zeichen) | B24: 250 | E24: Wörter | F24: Annahme CFO
A26: SMOKE-TEST-KALIBRIERUNG (Lauf 5, 24.10.2026)
A27: Wörter Smoke-Werk (EN) | B27: 1339 | E27: Wörter | F27: PIPELINE.md
A28: Textkosten gesamt | B28: 0.0685 | E28: $ | F28: PIPELINE.md
A29: Modal gesamt (500+520) | B29: 0.1574 | E29: $ | F29: PIPELINE.md
A30: Audio-Minuten EN+DE | B30: 13.4 | E30: min | F30: PIPELINE.md (2 × 6,7 min)
A31: → Text je 1.000 Wörter (gemessen) | B31: =$B$28/$B$27*1000 -> 0.05115758 | E31: $/1.000 W | F31: liegt unter Ansatz 0,09 $ (Ansatz bleibt, konservativ)
A32: → Modal je Audio-h (gemessen, roh) | B32: =$B$29/($B$30/60) -> 0.70477612 | E32: $/Audio-h | F32: vgl. Ansatz 0,94 + Wortzeiten
A33: → Wörter je Audio-h Chatterbox roh / nach Tempo 0,73 | B33: =$B$27/(6.7/60)*0.73 -> 8753.4627 | E33: Wörter/h | F33: PROJEKTSTAND 15.10. atempo 0,73
A35: KOSTEN JE WERK (Ø Katalogwerk, EN+DE, in EUR)
A36: Audio-Stunden je Sprache | B36: =$B$22/$B$21 -> 10.695187 | E36: h | F36: Formel
A37: Text EN+DE | B37: =$B$22/1000*$B$13/$B$7 -> 7.9977411 | E37: €/Werk | F37: Formel
A38: Basis-Audio EN+DE (Chatterbox) | B38: =2*$B$36*$B$14/$B$7 -> 17.963863 | E38: €/Werk | F38: Formel
A39: Wortzeiten EN+DE | B39: =2*$B$36*$B$16/$B$7 -> 2.9093586 | E39: €/Werk | F39: Formel
A40: Premium-Audio EN+DE (Gemini 2027) | B40: =2*$B$36*$B$15/$B$7 -> 30.958998 | E40: €/Werk | F40: Formel
A41: Hörspiel-Schicht (VC + 57b + Messung) | B41: =($B$17+$B$18+$B$19)/$B$7 -> 1.3669258 | E41: €/Werk | F41: Formel
A42: → Katalogwerk Basis (Text + Basis-Audio + Wortzeiten) | B42: =$B$37+$B$38+$B$39 -> 28.870963 | E42: €/Werk | F42: TÆLLA-Katalog / SOMNIO
A43: → Zusatz Premium-Hörbuch (Gemini statt Chatterbox) | B43: =$B$40 -> 30.958998 | E43: €/Werk | F43: Patenschaft Hörbuch
A44: → Zusatz Hörspiel (Premium + Schicht) | B44: =$B$40+$B$41 -> 32.325924 | E44: €/Werk | F44: Patenschaft Hörspiel / Auftrag
A45: Verlagstitel: BFSG-EPUB ohne Audio | B45: =$B$23/1000*$B$20/$B$7 -> 0.27756599 | E45: €/Titel | F45: Formel
A46: Verlagstitel: Audio-Stunden (1 Sprache) | B46: =$B$23/$B$21 -> 8.6021505 | E46: h | F46: Formel
A47: Verlagstitel: Media Overlays mit Basis-Vertonung (1 Sprache) | B47: =$B$45+$B$46*($B$14+$B$16)/$B$7 -> 8.6717433 | E47: €/Titel | F47: Formel
A48: Verlagstitel: Alignment Verlagsaudio | B48: =$B$45+$B$46*$B$16/$B$7 -> 1.4475661 | E48: €/Titel | F48: Wortzeiten-Satz; STT-Kosten 58_3rd_prty nicht gemessen
A49: Vertonung Premium je Audio-h | B49: =($B$15+$B$16)/$B$7 -> 1.5833457 | E49: €/Audio-h | F49: Formel
A50: Übersetzung/Modernisierung je Normseite | B50: =$B$24/1000*$B$13/$B$7 -> 0.020101849 | E50: €/NS | F50: Formel
A51: Pilot (Text EN+DE, Audio DE, Wortzeiten, Hörspiel-Kapitel) | B51: =$B$23/1000*$B$13/$B$7+$B$46*($B$14+$B$16)/$B$7+$B$41 -> 16.193695 | E51: €/Pilot | F51: Formel
A53: TÆLLA APP (B2C)
A54: Launch (Monat) | B54: 4 | C54: 3 | D54: 2 | E54: Monat | F54: Annahme – CK entscheidet
A55: MAU bei Launch | B55: 200 | C55: 500 | D55: 1000 | E55: Nutzer | F55: Annahme
A56: MAU-Wachstum je Monat | B56: 0.08 | C56: 0.15 | D56: 0.22 | E56: Anteil | F56: Annahme
A57: Marktpotenzial MAU (S-Kurve: Wachstum flacht zum Potenzial hin ab) | B57: 50000 | C57: 200000 | D57: 500000 | E57: Nutzer | F57: Anker: 4,2 Mio. digitale Hörbuch-Nutzer·innen DE 2025 inkl. Abo (Börsenverein, Buchmarkt kompakt 2025/26) → ca. 1 / 5 / 12 %; BookBeat knapp 1,2 Mio. Zahlende in 8 Märkten (PM 02/2026)
A58: Neu zahlend je Monat (Anteil MAU) | B58: 0.005 | C58: 0.01 | D58: 0.015 | E58: Anteil | F58: Annahme
A59: Churn je Monat (Zahlende) | B59: 0.08 | C59: 0.06 | D59: 0.04 | E59: Anteil | F59: Annahme
A60: Anteil Vollzugang unter Zahlenden | B60: 0.3 | C60: 0.4 | D60: 0.5 | E60: Anteil | F60: Annahme
A61: Anteil Monatszahler (Rest Jahr) | B61: 0.7 | C61: 0.6 | D61: 0.5 | E61: Anteil | F61: Annahme
A62: Anteil Zahlung über App-Store (Rest Stripe/taella.io) | B62: 0.6 | C62: 0.5 | D62: 0.4 | E62: Anteil | F62: Annahme – Weg offen (PROJEKTSTAND 12.10.)
A63: Patenschaften je Monat (ab Launch) | B63: 0.5 | C63: 2 | D63: 5 | E63: Stück | F63: Annahme
A64: Anteil Patenschaft Hörspiel | B64: 0.3 | C64: 0.4 | D64: 0.5 | E64: Anteil | F64: Annahme
A65: Auftrags-Hörspiele je Monat (ab Launch) | B65: 0 | C65: 0.5 | D65: 1 | E65: Stück | F65: Annahme
A66: Katalog-Neuwerke je Monat (Basis EN+DE) | B66: 4 | C66: 8 | D66: 12 | E66: Werke | F66: Annahme; 237 Werke offen (PROJEKTSTAND 11.10.)
A67: Preis Hörbuch-Zugang Monat (brutto) | B67: 5.99 | E67: € | F67: PROJEKTSTAND 12.10. Preisstruktur
A68: Preis Hörbuch-Zugang Jahr (brutto) | B68: 59.99 | E68: € | F68: PROJEKTSTAND 12.10.
A69: Preis Vollzugang Monat (brutto) | B69: 7.99 | E69: € | F69: PROJEKTSTAND 12.10.
A70: Preis Vollzugang Jahr (brutto) | B70: 79.99 | E70: € | F70: PROJEKTSTAND 12.10.
A71: Patenschaft Hörbuch (brutto, ohne Auto-Verlängerung) | B71: 59.99 | E71: € | F71: PROJEKTSTAND 12.10.
A72: Patenschaft Hörspiel (brutto) | B72: 74.99 | E72: € | F72: PROJEKTSTAND 12.10.
A73: Auftrags-Hörspiel (brutto) | B73: 149 | E73: € | F73: Vorschlag CFO – Preis offen (CK)
A74: App-Store-Provision (Small Business) | B74: 0.15 | E74: Anteil | F74: Apple Small Business Program 15 % (developer.apple.com); Google Abos 15 %
A75: Stripe EWR-Karten Prozent | B75: 0.015 | E75: Anteil | F75: stripe.com/de/pricing: 1,5 % + 0,25 €
A76: Stripe fix je Zahlung | B76: 0.25 | E76: € | F76: stripe.com/de/pricing
A77: Hosting/CDN variabel je MAU | B77: 0.01 | E77: €/MAU/Monat | F77: Annahme
A78: → Ø Erlös je Hörbuch-Zahler/Monat (brutto) | B78: =B61*$B$67+(1-B61)*$B$68/12 -> 5.69275 | C78: =C61*$B$67+(1-C61)*$B$68/12 -> 5.5936667 | D78: =D61*$B$67+(1-D61)*$B$68/12 -> 5.4945833 | E78: € | F78: Formel
A79: → Ø Erlös je Vollzugang-Zahler/Monat (brutto) | B79: =B61*$B$69+(1-B61)*$B$70/12 -> 7.59275 | C79: =C61*$B$69+(1-C61)*$B$70/12 -> 7.4603333 | D79: =D61*$B$69+(1-D61)*$B$70/12 -> 7.3279167 | E79: € | F79: Formel
A81: READ LAYER VERLAGSDIENSTLEISTUNGEN (B2B, Preise netto)
A82: Erster Auftrag (Monat) | B82: 5 | C82: 4 | D82: 3 | E82: Monat | F82: Annahme; Leipzig 18.–21.03.2027 = Monat 3
A83: Pilot-Aufträge je Monat | B83: 0.3 | C83: 0.7 | D83: 1.5 | E83: Stück | F83: Annahme
A84: Anteil Barter (Pilot gegen TÆLLA-Präsenz) | B84: 0.3 | C84: 0.3 | D84: 0.2 | E84: Anteil | F84: AP_cockpit_v2
A85: Folgeauftrag je Pilot | B85: 0.3 | C85: 0.4 | D85: 0.5 | E85: Anteil | F85: Annahme
A86: Verzug Pilot → Folgeauftrag | B86: 3 | E86: Monate | F86: Anrechnung innerhalb 3 Monaten (AP_cockpit_v2)
A87: Titel je Folgeauftrag (BFSG-EPUB + MO) | B87: 5 | C87: 5 | D87: 8 | E87: Titel | F87: Annahme
A88: BFSG-EPUB Direktaufträge je Monat | B88: 0 | C88: 1 | D88: 3 | E88: Titel | F88: Annahme
A89: Anteil mit Media Overlays (Basis-Vertonung) | B89: 0.5 | C89: 0.5 | D89: 0.6 | E89: Anteil | F89: Annahme
A90: Alignment Verlagsaudio je Monat | B90: 0 | C90: 0.5 | D90: 2 | E90: Titel | F90: Annahme
A91: Anteil Alignment mit Schnitt-Aufschlag | B91: 0.5 | E91: Anteil | F91: Annahme
A92: Vertonung Premium je Monat | B92: 0 | C92: 5 | D92: 20 | E92: Audio-h | F92: Annahme
A93: Übersetzung je Monat | B93: 0 | C93: 50 | D93: 300 | E93: Normseiten | F93: Annahme
A94: Modernisierung je Monat | B94: 0 | C94: 0 | D94: 100 | E94: Normseiten | F94: Annahme
A95: Zusatzformate Kundenpaket je Monat (A-003) | B95: 0 | C95: 1 | D95: 4 | E95: Formate | F95: Annahme
A96: Preis Pilot | B96: 490 | E96: € | F96: AP_cockpit_v2 (anrechenbar)
A97: Preis BFSG-EPUB 3 je Titel (ohne Audio) | B97: 149 | E97: € | F97: Markt: EPUB-Konvertierung 119–350 €/Titel, Bsp. 200 € (ki-syndikat.de/usecases/verlag/23-buchproduktion-epub-generierung); barrierefrei nicht veröffentlicht
A98: Aufpreis Media Overlays mit Basis-Vertonung je Titel | B98: 390 | E98: € | F98: Markt: KI-Vertonung Bookwire ca. 500–1.200 €/Titel (ki-syndikat.de/tools/bookwire, Redaktionsschätzung)
A99: Alignment Verlagsaudio je Titel (Audio kapitelweise) | B99: 190 | E99: € | F99: Markt: kein Dienstleisterpreis gefunden – Vorschlag CFO
A100: Schnitt: manuelle Prüfzeit je Audio-h | B100: 15 | E100: min | F100: Vorschlag CFO: Stichprobe + Korrektur Abweichungen Text–Audio
A101: Schnitt: Mindestaufschlag je Titel | B101: 95 | E101: € | F101: Vorschlag CFO
A102: → Schnitt-Aufschlag je Titel (Ø Verlagstitel) | B102: =MAX($B$101,$B$46*$B$100/60*$B$10) -> 129.03226 | E102: € | F102: Formel: Audio-h × Prüfzeit × Stundensatz
A103: Vertonung Premium je fertiger Audio-h | B103: 89 | E103: € | F103: Markt: Sprecher·in ca. 200–500 €/PFH (bookfoundry.ai Leitfaden 2026); ACX 300–400 $/PFH (acx.com)
A104: Übersetzung je Normseite (KI + Prüfung) | B104: 6 | E104: € | F104: Markt: Literaturübersetzung Ø 18,72 €/NS 2018 (VdÜ, literaturuebersetzer.de)
A105: Modernisierung je Normseite | B105: 4 | E105: € | F105: Vorschlag CFO (unter Übersetzung)
A106: Zusatzformat je Titel (DAISY, VTT, SRT, …) | B106: 49 | E106: € | F106: Vorschlag CFO; EPUB 3 MO im Titelpreis enthalten
A108: SOMNIO PUBLISHING
...

Sheet TÆLLA
A1: TÆLLA App (B2C) — 24 Monate ab 01/2027
A3: Kennzahl | B3: ="vorsichtig – "&Annahmen!$B$133 -> vorsichtig – teures Hobby | C3: ="mittel – "&Annahmen!$C$133 -> mittel – profitabler Nebenerwerb | D3: ="stark – "&Annahmen!$D$133 -> stark – skalierbares Business
A4: Break-even monatlich (erster Monat Ergebnis > 0) | B4: =IFERROR("Monat "&MATCH(1,AA18:AA41,0)&" ("&INDEX($B$18:$B$41,MATCH(1,AA18:AA41,0))&")","nicht in 24 M") -> nicht in 24 M | C4: =IFERROR("Monat "&MATCH(1,AA47:AA70,0)&" ("&INDEX($B$47:$B$70,MATCH(1,AA47:AA70,0))&")","nicht in 24 M") -> Monat 16 (04/2028) | D4: =IFERROR("Monat "&MATCH(1,AA76:AA99,0)&" ("&INDEX($B$76:$B$99,MATCH(1,AA76:AA99,0))&")","nicht in 24 M") -> Monat 12 (12/2027)
A5: Break-even kumuliert (erster Monat kum. ≥ 0) | B5: =IFERROR("Monat "&MATCH(1,AB18:AB41,0)&" ("&INDEX($B$18:$B$41,MATCH(1,AB18:AB41,0))&")","nicht in 24 M") -> nicht in 24 M | C5: =IFERROR("Monat "&MATCH(1,AB47:AB70,0)&" ("&INDEX($B$47:$B$70,MATCH(1,AB47:AB70,0))&")","nicht in 24 M") -> nicht in 24 M | D5: =IFERROR("Monat "&MATCH(1,AB76:AB99,0)&" ("&INDEX($B$76:$B$99,MATCH(1,AB76:AB99,0))&")","nicht in 24 M") -> Monat 19 (07/2028)
A6: Deckungsbeitrag (netto, nach Gebühren)
A7: DB je Hörbuch-Zahler/Monat – Stripe | B7: =Annahmen!$B$78/(1+Annahmen!$B$8)*(1-Annahmen!$B$75)-Annahmen!$B$76*(Annahmen!$B$61+(1-Annahmen!$B$61)/12) -> 4.5308162 | C7: =Annahmen!$C$78/(1+Annahmen!$B$8)*(1-Annahmen!$B$75)-Annahmen!$B$76*(Annahmen!$C$61+(1-Annahmen!$C$61)/12) -> 4.4717185 | D7: =Annahmen!$D$78/(1+Annahmen!$B$8)*(1-Annahmen!$B$75)-Annahmen!$B$76*(Annahmen!$D$61+(1-Annahmen!$D$61)/12) -> 4.4126208
A8: DB je Hörbuch-Zahler/Monat – App-Store | B8: =Annahmen!$B$78/(1+Annahmen!$B$8)*(1-Annahmen!$B$74) -> 4.06625 | C8: =Annahmen!$C$78/(1+Annahmen!$B$8)*(1-Annahmen!$B$74) -> 3.9954762 | D8: =Annahmen!$D$78/(1+Annahmen!$B$8)*(1-Annahmen!$B$74) -> 3.9247024
A9: DB je Vollzugang-Zahler/Monat – Stripe | B9: =Annahmen!$B$79/(1+Annahmen!$B$8)*(1-Annahmen!$B$75)-Annahmen!$B$76*(Annahmen!$B$61+(1-Annahmen!$B$61)/12) -> 6.1035053 | C9: =Annahmen!$C$79/(1+Annahmen!$B$8)*(1-Annahmen!$B$75)-Annahmen!$B$76*(Annahmen!$C$61+(1-Annahmen!$C$61)/12) -> 6.0168165 | D9: =Annahmen!$D$79/(1+Annahmen!$B$8)*(1-Annahmen!$B$75)-Annahmen!$B$76*(Annahmen!$D$61+(1-Annahmen!$D$61)/12) -> 5.9301278
A10: DB je Vollzugang-Zahler/Monat – App-Store | B10: =Annahmen!$B$79/(1+Annahmen!$B$8)*(1-Annahmen!$B$74) -> 5.4233929 | C10: =Annahmen!$C$79/(1+Annahmen!$B$8)*(1-Annahmen!$B$74) -> 5.3288095 | D10: =Annahmen!$D$79/(1+Annahmen!$B$8)*(1-Annahmen!$B$74) -> 5.2342262
A11: DB je Patenschaft Hörbuch (Stripe) | B11: =Annahmen!$B$71/(1+Annahmen!$B$8)*(1-Annahmen!$B$75)-Annahmen!$B$76-Annahmen!$B$43 -> 18.44659 | C11: =Annahmen!$B$71/(1+Annahmen!$B$8)*(1-Annahmen!$B$75)-Annahmen!$B$76-Annahmen!$B$43 -> 18.44659 | D11: =Annahmen!$B$71/(1+Annahmen!$B$8)*(1-Annahmen!$B$75)-Annahmen!$B$76-Annahmen!$B$43 -> 18.44659
A12: DB je Patenschaft Hörspiel (Stripe) | B12: =Annahmen!$B$72/(1+Annahmen!$B$8)*(1-Annahmen!$B$75)-Annahmen!$B$76-Annahmen!$B$44 -> 29.495631 | C12: =Annahmen!$B$72/(1+Annahmen!$B$8)*(1-Annahmen!$B$75)-Annahmen!$B$76-Annahmen!$B$44 -> 29.495631 | D12: =Annahmen!$B$72/(1+Annahmen!$B$8)*(1-Annahmen!$B$75)-Annahmen!$B$76-Annahmen!$B$44 -> 29.495631
A13: Katalogkosten je Werk (Basis EN+DE) | B13: =Annahmen!$B$42 -> 28.870963 | C13: =Annahmen!$B$42 -> 28.870963 | D13: =Annahmen!$B$42 -> 28.870963
A16: ="Szenario vorsichtig – "&Annahmen!$B$133 -> Szenario vorsichtig – teures Hobby
A17: Monat | B17: Datum | C17: MAU | D17: Neu zahlend | E17: Zahlende gesamt | F17: davon Hörbuch | G17: davon Voll | H17: Abo-Umsatz brutto | I17: Paten Hörbuch | J17: Paten Hörspiel | K17: Paten-Umsatz brutto | L17: Auftrags-Hörspiele | M17: Auftrag brutto | N17: Umsatz brutto | O17: Umsatz netto | P17: Zahlungs-gebühren | Q17: Katalog-Neuwerke | R17: Katalog-kosten | S17: Produktion Paten/Auftrag | T17: Hosting variabel | U17: Fixkosten anteilig | V17: Marketing | W17: Personal-bedarf FTE | X17: Personal-kosten | Y17: Ergebnis | Z17: Ergebnis kumuliert | AA17: BE monatl. | AB17: BE kum.
A18: 1 | B18: 01/2027 | C18: =IF($A18<Annahmen!$B$54,0,Annahmen!$B$55) -> 0 | D18: =C18*Annahmen!$B$58 -> 0 | E18: =D18 -> 0 | F18: =E18*(1-Annahmen!$B$60) -> 0 | G18: =E18*Annahmen!$B$60 -> 0 | H18: =F18*Annahmen!$B$78+G18*Annahmen!$B$79 -> 0 | I18: =IF($A18>=Annahmen!$B$54,Annahmen!$B$63*(1-Annahmen!$B$64),0) -> 0 | J18: =IF($A18>=Annahmen!$B$54,Annahmen!$B$63*Annahmen!$B$64,0) -> 0 | K18: =I18*Annahmen!$B$71+J18*Annahmen!$B$72 -> 0 | L18: =IF($A18>=Annahmen!$B$54,Annahmen!$B$65,0) -> 0 | M18: =L18*Annahmen!$B$73 -> 0 | N18: =H18+K18+M18 -> 0 | O18: =N18/(1+Annahmen!$B$8) -> 0 | P18: =O18*(Annahmen!$B$62*Annahmen!$B$74+(1-Annahmen!$B$62)*Annahmen!$B$75)+(E18*Annahmen!$B$61+E18*(1-Annahmen!$B$61)/12+I18+J18+L18)*(1-Annahmen!$B$62)*Annahmen!$B$76 -> 0 | Q18: =Annahmen!$B$66 -> 4 | R18: =Q18*Annahmen!$B$42 -> 115.48385 | S18: =I18*Annahmen!$B$43+(J18+L18)*Annahmen!$B$44 -> 0 | T18: =C18*Annahmen!$B$77 -> 0 | U18: =SUMPRODUCT((((Annahmen!$C$145:$C$155="monatlich")*(Annahmen!$D$145:$D$155<=$A18))+((Annahmen!$C$145:$C$155="einmalig")*(Annahmen!$D$145:$D$155=$A18)))*Annahmen!$B$145:$B$155*Annahmen!$E$145:$E$155) -> 232.38508 | V18: =IF($A18>=Annahmen!$B$54,Annahmen!$B$134,0) -> 0 | W18: =MAX(0,(E18-Annahmen!$B$138)/Annahmen!$B$139) -> 0 | X18: =W18*Annahmen!$B$137 -> 0 | Y18: =O18-P18-R18-S18-T18-U18-V18-X18 -> -347.86893 | Z18: =Y18 -> -347.86893 | AA18: =IF(Y18>0,1,0) -> 0 | AB18: =IF(Z18>=0,1,0) -> 0
A19: 2 | B19: 02/2027 | C19: =IF($A19<Annahmen!$B$54,0,IF($A19=Annahmen!$B$54,Annahmen!$B$55,C18*(1+Annahmen!$B$56*(1-C18/Annahmen!$B$57)))) -> 0 | D19: =C19*Annahmen!$B$58 -> 0 | E19: =E18*(1-Annahmen!$B$59)+D19 -> 0 | F19: =E19*(1-Annahmen!$B$60) -> 0 | G19: =E19*Annahmen!$B$60 -> 0 | H19: =F19*Annahmen!$B$78+G19*Annahmen!$B$79 -> 0 | I19: =IF($A19>=Annahmen!$B$54,Annahmen!$B$63*(1-Annahmen!$B$64),0) -> 0 | J19: =IF($A19>=Annahmen!$B$54,Annahmen!$B$63*Annahmen!$B$64,0) -> 0 | K19: =I19*Annahmen!$B$71+J19*Annahmen!$B$72 -> 0 | L19: =IF($A19>=Annahmen!$B$54,Annahmen!$B$65,0) -> 0 | M19: =L19*Annahmen!$B$73 -> 0 | N19: =H19+K19+M19 -> 0 | O19: =N19/(1+Annahmen!$B$8) -> 0 | P19: =O19*(Annahmen!$B$62*Annahmen!$B$74+(1-Annahmen!$B$62)*Annahmen!$B$75)+(E19*Annahmen!$B$61+E19*(1-Annahmen!$B$61)/12+I19+J19+L19)*(1-Annahmen!$B$62)*Annahmen!$B$76 -> 0 | Q19: =Annahmen!$B$66 -> 4 | R19: =Q19*Annahmen!$B$42 -> 115.48385 | S19: =I19*Annahmen!$B$43+(J19+L19)*Annahmen!$B$44 -> 0 | T19: =C19*Annahmen!$B$77 -> 0 | U19: =SUMPRODUCT((((Annahmen!$C$145:$C$155="monatlich")*(Annahmen!$D$145:$D$155<=$A19))+((Annahmen!$C$145:$C$155="einmalig")*(Annahmen!$D$145:$D$155=$A19)))*Annahmen!$B$145:$B$155*Annahmen!$E$145:$E$155) -> 92.320468 | V19: =IF($A19>=Annahmen!$B$54,Annahmen!$B$134,0) -> 0 | W19: =MAX(0,(E19-Annahmen!$B$138)/Annahmen!$B$139) -> 0 | X19: =W19*Annahmen!$B$137 -> 0 | Y19: =O19-P19-R19-S19-T19-U19-V19-X19 -> -207.80432 | Z19: =Z18+Y19 -> -555.67325 | AA19: =IF(Y19>0,1,0) -> 0 | AB19: =IF(Z19>=0,1,0) -> 0
A20: 3 | B20: 03/2027 | C20: =IF($A20<Annahmen!$B$54,0,IF($A20=Annahmen!$B$54,Annahmen!$B$55,C19*(1+Annahmen!$B$56*(1-C19/Annahmen!$B$57)))) -> 0 | D20: =C20*Annahmen!$B$58 -> 0 | E20: =E19*(1-Annahmen!$B$59)+D20 -> 0 | F20: =E20*(1-Annahmen!$B$60) -> 0 | G20: =E20*Annahmen!$B$60 -> 0 | H20: =F20*Annahmen!$B$78+G20*Annahmen!$B$79 -> 0 | I20: =IF($A20>=Annahmen!$B$54,Annahmen!$B$63*(1-Annahmen!$B$64),0) -> 0 | J20: =IF($A20>=Annahmen!$B$54,Annahmen!$B$63*Annahmen!$B$64,0) -> 0 | K20: =I20*Annahmen!$B$71+J20*Annahmen!$B$72 -> 0 | L20: =IF($A20>=Annahmen!$B$54,Annahmen!$B$65,0) -> 0 | M20: =L20*Annahmen!$B$73 -> 0 | N20: =H20+K20+M20 -> 0 | O20: =N20/(1+Annahmen!$B$8) -> 0 | P20: =O20*(Annahmen!$B$62*Annahmen!$B$74+(1-Annahmen!$B$62)*Annahmen!$B$75)+(E20*Annahmen!$B$61+E20*(1-Annahmen!$B$61)/12+I20+J20+L20)*(1-Annahmen!$B$62)*Annahmen!$B$76 -> 0 | Q20: =Annahmen!$B$66 -> 4 | R20: =Q20*Annahmen!$B$42 -> 115.48385 | S20: =I20*Annahmen!$B$43+(J20+L20)*Annahmen!$B$44 -> 0 | T20: =C20*Annahmen!$B$77 -> 0 | U20: =SUMPRODUCT((((Annahmen!$C$145:$C$155="monatlich")*(Annahmen!$D$145:$D$155<=$A20))+((Annahmen!$C$145:$C$155="einmalig")*(Annahmen!$D$145:$D$155=$A20)))*Annahmen!$B$145:$B$155*Annahmen!$E$145:$E$155) -> 69.98508 | V20: =IF($A20>=Annahmen!$B$54,Annahmen!$B$134,0) -> 0 | W20: =MAX(0,(E20-Annahmen!$B$138)/Annahmen!$B$139) -> 0 | X20: =W20*Annahmen!$B$137 -> 0 | Y20: =O20-P20-R20-S20-T20-U20-V20-X20 -> -185.46893 | Z20: =Z19+Y20 -> -741.14218 | AA20: =IF(Y20>0,1,0) -> 0 | AB20: =IF(Z20>=0,1,0) -> 0
A21: 4 | B21: 04/2027 | C21: =IF($A21<Annahmen!$B$54,0,IF($A21=Annahmen!$B$54,Annahmen!$B$55,C20*(1+Annahmen!$B$56*(1-C20/Annahmen!$B$57)))) -> 200 | D21: =C21*Annahmen!$B$58 -> 1 | E21: =E20*(1-Annahmen!$B$59)+D21 -> 1 | F21: =E21*(1-Annahmen!$B$60) -> 0.7 | G21: =E21*Annahmen!$B$60 -> 0.3 | H21: =F21*Annahmen!$B$78+G21*Annahmen!$B$79 -> 6.26275 | I21: =IF($A21>=Annahmen!$B$54,Annahmen!$B$63*(1-Annahmen!$B$64),0) -> 0.35 | J21: =IF($A21>=Annahmen!$B$54,Annahmen!$B$63*Annahmen!$B$64,0) -> 0.15 | K21: =I21*Annahmen!$B$71+J21*Annahmen!$B$72 -> 32.245 | L21: =IF($A21>=Annahmen!$B$54,Annahmen!$B$65,0) -> 0 | M21: =L21*Annahmen!$B$73 -> 0 | N21: =H21+K21+M21 -> 38.50775 | O21: =N21/(1+Annahmen!$B$8) -> 32.359454 | P21: =O21*(Annahmen!$B$62*Annahmen!$B$74+(1-Annahmen!$B$62)*Annahmen!$B$75)+(E21*Annahmen!$B$61+E21*(1-Annahmen!$B$61)/12+I21+J21+L21)*(1-Annahmen!$B$62)*Annahmen!$B$76 -> 3.2290076 | Q21: =Annahmen!$B$66 -> 4 | R21: =Q21*Annahmen!$B$42 -> 115.48385 | S21: =I21*Annahmen!$B$43+(J21+L21)*Annahmen!$B$44 -> 15.684538 | T21: =C21*Annahmen!$B$77 -> 2 | U21: =SUMPRODUCT((((Annahmen!$C$145:$C$155="monatlich")*(Annahmen!$D$145:$D$155<=$A21))+((Annahmen!$C$145:$C$155="einmalig")*(Annahmen!$D$145:$D$155=$A21)))*Annahmen!$B$145:$B$155*Annahmen!$E$145:$E$155) -> 69.98508 | V21: =IF($A21>=Annahmen!$B$54,Annahmen!$B$134,0) -> 200 | W21: =MAX(0,(E21-Annahmen!$B$138)/Annahmen!$B$139) -> 0 | X21: =W21*Annahmen!$B$137 -> 0 | Y21: =O21-P21-R21-S21-T21-U21-V21-X21 -> -374.02302 | Z21: =Z20+Y21 -> -1115.1652 | AA21: =IF(Y21>0,1,0) -> 0 | AB21: =IF(Z21>=0,1,0) -> 0
A22: 5 | B22: 05/2027 | C22: =IF($A22<Annahmen!$B$54,0,IF($A22=Annahmen!$B$54,Annahmen!$B$55,C21*(1+Annahmen!$B$56*(1-C21/Annahmen!$B$57)))) -> 215.936 | D22: =C22*Annahmen!$B$58 -> 1.07968 | E22: =E21*(1-Annahmen!$B$59)+D22 -> 1.99968 | F22: =E22*(1-Annahmen!$B$60) -> 1.399776 | G22: =E22*Annahmen!$B$60 -> 0.599904 | H22: =F22*Annahmen!$B$78+G22*Annahmen!$B$79 -> 12.523496 | I22: =IF($A22>=Annahmen!$B$54,Annahmen!$B$63*(1-Annahmen!$B$64),0) -> 0.35 | J22: =IF($A22>=Annahmen!$B$54,Annahmen!$B$63*Annahmen!$B$64,0) -> 0.15 | K22: =I22*Annahmen!$B$71+J22*Annahmen!$B$72 -> 32.245 | L22: =IF($A22>=Annahmen!$B$54,Annahmen!$B$65,0) -> 0 | M22: =L22*Annahmen!$B$73 -> 0 | N22: =H22+K22+M22 -> 44.768496 | O22: =N22/(1+Annahmen!$B$8) -> 37.620585 | P22: =O22*(Annahmen!$B$62*Annahmen!$B$74+(1-Annahmen!$B$62)*Annahmen!$B$75)+(E22*Annahmen!$B$61+E22*(1-Annahmen!$B$61)/12+I22+J22+L22)*(1-Annahmen!$B$62)*Annahmen!$B$76 -> 3.8065529 | Q22: =Annahmen!$B$66 -> 4 | R22: =Q22*Annahmen!$B$42 -> 115.48385 | S22: =I22*Annahmen!$B$43+(J22+L22)*Annahmen!$B$44 -> 15.684538 | T22: =C22*Annahmen!$B$77 -> 2.15936 | U22: =SUMPRODUCT((((Annahmen!$C$145:$C$155="monatlich")*(Annahmen!$D$145:$D$155<=$A22))+((Annahmen!$C$145:$C$155="einmalig")*(Annahmen!$D$145:$D$155=$A22)))*Annahmen!$B$145:$B$155*Annahmen!$E$145:$E$155) -> 309.98508 | V22: =IF($A22>=Annahmen!$B$54,Annahmen!$B$134,0) -> 200 | W22: =MAX(0,(E22-Annahmen!$B$138)/Annahmen!$B$139) -> 0 | X22: =W22*Annahmen!$B$137 -> 0 | Y22: =O22-P22-R22-S22-T22-U22-V22-X22 -> -609.4988 | Z22: =Z21+Y22 -> -1724.664 | AA22: =IF(Y22>0,1,0) -> 0 | AB22: =IF(Z22>=0,1,0) -> 0
A23: 6 | B23: 06/2027 | C23: =IF($A23<Annahmen!$B$54,0,IF($A23=Annahmen!$B$54,Annahmen!$B$55,C22*(1+Annahmen!$B$56*(1-C22/Annahmen!$B$57)))) -> 233.13627 | D23: =C23*Annahmen!$B$58 -> 1.1656814 | E23: =E22*(1-Annahmen!$B$59)+D23 -> 3.005387 | F23: =E23*(1-Annahmen!$B$60) -> 2.1037709 | G23: =E23*Annahmen!$B$60 -> 0.90161609 | H23: =F23*Annahmen!$B$78+G23*Annahmen!$B$79 -> 18.821987 | I23: =IF($A23>=Annahmen!$B$54,Annahmen!$B$63*(1-Annahmen!$B$64),0) -> 0.35 | J23: =IF($A23>=Annahmen!$B$54,Annahmen!$B$63*Annahmen!$B$64,0) -> 0.15 | K23: =I23*Annahmen!$B$71+J23*Annahmen!$B$72 -> 32.245 | L23: =IF($A23>=Annahmen!$B$54,Annahmen!$B$65,0) -> 0 | M23: =L23*Annahmen!$B$73 -> 0 | N23: =H23+K23+M23 -> 51.066987 | O23: =N23/(1+Annahmen!$B$8) -> 42.913435 | P23: =O23*(Annahmen!$B$62*Annahmen!$B$74+(1-Annahmen!$B$62)*Annahmen!$B$75)+(E23*Annahmen!$B$61+E23*(1-Annahmen!$B$61)/12+I23+J23+L23)*(1-Annahmen!$B$62)*Annahmen!$B$76 -> 4.3875803 | Q23: =Annahmen!$B$66 -> 4 | R23: =Q23*Annahmen!$B$42 -> 115.48385 | S23: =I23*Annahmen!$B$43+(J23+L23)*Annahmen!$B$44 -> 15.684538 | T23: =C23*Annahmen!$B$77 -> 2.3313627 | U23: =SUMPRODUCT((((Annahmen!$C$145:$C$155="monatlich")*(Annahmen!$D$145:$D$155<=$A23))+((Annahmen!$C$145:$C$155="einmalig")*(Annahmen!$D$145:$D$155=$A23)))*Annahmen!$B$145:$B$155*Annahmen!$E$145:$E$155) -> 69.98508 | V23: =IF($A23>=Annahmen!$B$54,Annahmen!$B$134,0) -> 200 | W23: =MAX(0,(E23-Annahmen!$B$138)/Annahmen!$B$139) -> 0 | X23: =W23*Annahmen!$B$137 -> 0 | Y23: =O23-P23-R23-S23-T23-U23-V23-X23 -> -364.95898 | Z23: =Z22+Y23 -> -2089.623 | AA23: =IF(Y23>0,1,0) -> 0 | AB23: =IF(Z23>=0,1,0) -> 0
A24: 7 | B24: 07/2027 | C24: =IF($A24<Annahmen!$B$54,0,IF($A24=Annahmen!$B$54,Annahmen!$B$55,C23*(1+Annahmen!$B$56*(1-C23/Annahmen!$B$57)))) -> 251.70021 | D24: =C24*Annahmen!$B$58 -> 1.2585011 | E24: =E23*(1-Annahmen!$B$59)+D24 -> 4.0234571 | F24: =E24*(1-Annahmen!$B$60) -> 2.81642 | G24: =E24*Annahmen!$B$60 -> 1.2070371 | H24: =F24*Annahmen!$B$78+G24*Annahmen!$B$79 -> 25.197906 | I24: =IF($A24>=Annahmen!$B$54,Annahmen!$B$63*(1-Annahmen!$B$64),0) -> 0.35 | J24: =IF($A24>=Annahmen!$B$54,Annahmen!$B$63*Annahmen!$B$64,0) -> 0.15 | K24: =I24*Annahmen!$B$71+J24*Annahmen!$B$72 -> 32.245 | L24: =IF($A24>=Annahmen!$B$54,Annahmen!$B$65,0) -> 0 | M24: =L24*Annahmen!$B$73 -> 0 | N24: =H24+K24+M24 -> 57.442906 | O24: =N24/(1+Annahmen!$B$8) -> 48.271349 | P24: =O24*(Annahmen!$B$62*Annahmen!$B$74+(1-Annahmen!$B$62)*Annahmen!$B$75)+(E24*Annahmen!$B$61+E24*(1-Annahmen!$B$61)/12+I24+J24+L24)*(1-Annahmen!$B$62)*Annahmen!$B$76 -> 4.9757502 | Q24: =Annahmen!$B$66 -> 4 | R24: =Q24*Annahmen!$B$42 -> 115.48385 | S24: =I24*Annahmen!$B$43+(J24+L24)*Annahmen!$B$44 -> 15.684538 | T24: =C24*Annahmen!$B$77 -> 2.5170021 | U24: =SUMPRODUCT((((Annahmen!$C$145:$C$155="monatlich")*(Annahmen!$D$145:$D$155<=$A24))+((Annahmen!$C$145:$C$155="einmalig")*(Annahmen!$D$145:$D$155=$A24)))*Annahmen!$B$145:$B$155*Annahmen!$E$145:$E$155) -> 69.98508 | V24: =IF($A24>=Annahmen!$B$54,Annahmen!$B$134,0) -> 200 | W24: =MAX(0,(E24-Annahmen!$B$138)/Annahmen!$B$139) -> 0 | X24: =W24*Annahmen!$B$137 -> 0 | Y24: =O24-P24-R24-S24-T24-U24-V24-X24 -> -360.37487 | Z24: =Z23+Y24 -> -2449.9978 | AA24: =IF(Y24>0,1,0) -> 0 | AB24: =IF(Z24>=0,1,0) -> 0
A25: 8 | B25: 08/2027 | C25: =IF($A25<Annahmen!$B$54,0,IF($A25=Annahmen!$B$54,Annahmen!$B$55,C24*(1+Annahmen!$B$56*(1-C24/Annahmen!$B$57)))) -> 271.73486 | D25: =C25*Annahmen!$B$58 -> 1.3586743 | E25: =E24*(1-Annahmen!$B$59)+D25 -> 5.0602548 | F25: =E25*(1-Annahmen!$B$60) -> 3.5421784 | G25: =E25*Annahmen!$B$60 -> 1.5180765 | H25: =F25*Annahmen!$B$78+G25*Annahmen!$B$79 -> 31.691111 | I25: =IF($A25>=Annahmen!$B$54,Annahmen!$B$63*(1-Annahmen!$B$64),0) -> 0.35 | J25: =IF($A25>=Annahmen!$B$54,Annahmen!$B$63*Annahmen!$B$64,0) -> 0.15 | K25: =I25*Annahmen!$B$71+J25*Annahmen!$B$72 -> 32.245 | L25: =IF($A25>=Annahmen!$B$54,Annahmen!$B$65,0) -> 0 | M25: =L25*Annahmen!$B$73 -> 0 | N25: =H25+K25+M25 -> 63.936111 | O25: =N25/(1+Annahmen!$B$8) -> 53.727824 | P25: =O25*(Annahmen!$B$62*Annahmen!$B$74+(1-Annahmen!$B$62)*Annahmen!$B$75)+(E25*Annahmen!$B$61+E25*(1-Annahmen!$B$61)/12+I25+J25+L25)*(1-Annahmen!$B$62)*Annahmen!$B$76 -> 5.5747396 | Q25: =Annahmen!$B$66 -> 4 | R25: =Q25*Annahmen!$B$42 -> 115.48385 | S25: =I25*Annahmen!$B$43+(J25+L25)*Annahmen!$B$44 -> 15.684538 | T25: =C25*Annahmen!$B$77 -> 2.7173486 | U25: =SUMPRODUCT((((Annahmen!$C$145:$C$155="monatlich")*(Annahmen!$D$145:$D$155<=$A25))+((Annahmen!$C$145:$C$155="einmalig")*(Annahmen!$D$145:$D$155=$A25)))*Annahmen!$B$145:$B$155*Annahmen!$E$145:$E$155) -> 69.98508 | V25: =IF($A25>=Annahmen!$B$54,Annahmen!$B$134,0) -> 200 | W25: =MAX(0,(E25-Annahmen!$B$138)/Annahmen!$B$139) -> 0 | X25: =W25*Annahmen!$B$137 -> 0 | Y25: =O25-P25-R25-S25-T25-U25-V25-X25 -> -355.71773 | Z25: =Z24+Y25 -> -2805.7156 | AA25: =IF(Y25>0,1,0) -> 0 | AB25: =IF(Z25>=0,1,0) -> 0
A26: 9 | B26: 09/2027 | C26: =IF($A26<Annahmen!$B$54,0,IF($A26=Annahmen!$B$54,Annahmen!$B$55,C25*(1+Annahmen!$B$56*(1-C25/Annahmen!$B$57)))) -> 293.35551 | D26: =C26*Annahmen!$B$58 -> 1.4667776 | E26: =E25*(1-Annahmen!$B$59)+D26 -> 6.122212 | F26: =E26*(1-Annahmen!$B$60) -> 4.2855484 | G26: =E26*Annahmen!$B$60 -> 1.8366636 | H26: =F26*Annahmen!$B$78+G26*Annahmen!$B$79 -> 38.341883 | I26: =IF($A26>=Annahmen!$B$54,Annahmen!$B$63*(1-Annahmen!$B$64),0) -> 0.35 | J26: =IF($A26>=Annahmen!$B$54,Annahmen!$B$63*Annahmen!$B$64,0) -> 0.15 | K26: =I26*Annahmen!$B$71+J26*Annahmen!$B$72 -> 32.245 | L26: =IF($A26>=Annahmen!$B$54,Annahmen!$B$65,0) -> 0 | M26: =L26*Annahmen!$B$73 -> 0 | N26: =H26+K26+M26 -> 70.586883 | O26: =N26/(1+Annahmen!$B$8) -> 59.316709 | P26: =O26*(Annahmen!$B$62*Annahmen!$B$74+(1-Annahmen!$B$62)*Annahmen!$B$75)+(E26*Annahmen!$B$61+E26*(1-Annahmen!$B$61)/12+I26+J26+L26)*(1-Annahmen!$B$62)*Annahmen!$B$76 -> 6.1882644 | Q26: =Annahmen!$B$66 -> 4 | R26: =Q26*Annahmen!$B$42 -> 115.48385 | S26: =I26*Annahmen!$B$43+(J26+L26)*Annahmen!$B$44 -> 15.684538 | T26: =C26*Annahmen!$B$77 -> 2.9335551 | U26: =SUMPRODUCT((((Annahmen!$C$145:$C$155="monatlich")*(Annahmen!$D$145:$D$155<=$A26))+((Annahmen!$C$145:$C$155="einmalig")*(Annahmen!$D$145:$D$155=$A26)))*Annahmen!$B$145:$B$155*Annahmen!$E$145:$E$155) -> 69.98508 | V26: =IF($A26>=Annahmen!$B$54,Annahmen!$B$134,0) -> 200 | W26: =MAX(0,(E26-Annahmen!$B$138)/Annahmen!$B$139) -> 0 | X26: =W26*Annahmen!$B$137 -> 0 | Y26: =O26-P26-R26-S26-T26-U26-V26-X26 -> -350.95858 | Z26: =Z25+Y26 -> -3156.6742 | AA26: =IF(Y26>0,1,0) -> 0 | AB26: =IF(Z26>=0,1,0) -> 0
A27: 10 | B27: 10/2027 | C27: =IF($A27<Annahmen!$B$54,0,IF($A27=Annahmen!$B$54,Annahmen!$B$55,C26*(1+Annahmen!$B$56*(1-C26/Annahmen!$B$57)))) -> 316.68626 | D27: =C27*Annahmen!$B$58 -> 1.5834313 | E27: =E26*(1-Annahmen!$B$59)+D27 -> 7.2158663 | F27: =E27*(1-Annahmen!$B$60) -> 5.0511064 | G27: =E27*Annahmen!$B$60 -> 2.1647599 | H27: =F27*Annahmen!$B$78+G27*Annahmen!$B$79 -> 45.191167 | I27: =IF($A27>=Annahmen!$B$54,Annahmen!$B$63*(1-Annahmen!$B$64),0) -> 0.35 | J27: =IF($A27>=Annahmen!$B$54,Annahmen!$B$63*Annahmen!$B$64,0) -> 0.15 | K27: =I27*Annahmen!$B$71+J27*Annahmen!$B$72 -> 32.245 | L27: =IF($A27>=Annahmen!$B$54,Annahmen!$B$65,0) -> 0 | M27: =L27*Annahmen!$B$73 -> 0 | N27: =H27+K27+M27 -> 77.436167 | O27: =N27/(1+Annahmen!$B$8) -> 65.072409 | P27: =O27*(Annahmen!$B$62*Annahmen!$B$74+(1-Annahmen!$B$62)*Annahmen!$B$75)+(E27*Annahmen!$B$61+E27*(1-Annahmen!$B$61)/12+I27+J27+L27)*(1-Annahmen!$B$62)*Annahmen!$B$76 -> 6.8201016 | Q27: =Annahmen!$B$66 -> 4 | R27: =Q27*Annahmen!$B$42 -> 115.48385 | S27: =I27*Annahmen!$B$43+(J27+L27)*Annahmen!$B$44 -> 15.684538 | T27: =C27*Annahmen!$B$77 -> 3.1668626 | U27: =SUMPRODUCT((((Annahmen!$C$145:$C$155="monatlich")*(Annahmen!$D$145:$D$155<=$A27))+((Annahmen!$C$145:$C$155="einmalig")*(Annahmen!$D$145:$D$155=$A27)))*Annahmen!$B$145:$B$155*Annahmen!$E$145:$E$155) -> 69.98508 | V27: =IF($A27>=Annahmen!$B$54,Annahmen!$B$134,0) -> 200 | W27: =MAX(0,(E27-Annahmen!$B$138)/Annahmen!$B$139) -> 0 | X27: =W27*Annahmen!$B$137 -> 0 | Y27: =O27-P27-R27-S27-T27-U27-V27-X27 -> -346.06802 | Z27: =Z26+Y27 -> -3502.7422 | AA27: =IF(Y27>0,1,0) -> 0 | AB27: =IF(Z27>=0,1,0) -> 0
A28: 11 | B28: 11/2027 | C28: =IF($A28<Annahmen!$B$54,0,IF($A28=Annahmen!$B$54,Annahmen!$B$55,C27*(1+Annahmen!$B$56*(1-C27/Annahmen!$B$57)))) -> 341.8607 | D28: =C28*Annahmen!$B$58 -> 1.7093035 | E28: =E27*(1-Annahmen!$B$59)+D28 -> 8.3479005 | F28: =E28*(1-Annahmen!$B$60) -> 5.8435304 | G28: =E28*Annahmen!$B$60 -> 2.5043702 | H28: =F28*Annahmen!$B$78+G28*Annahmen!$B$79 -> 52.280814 | I28: =IF($A28>=Annahmen!$B$54,Annahmen!$B$63*(1-Annahmen!$B$64),0) -> 0.35 | J28: =IF($A28>=Annahmen!$B$54,Annahmen!$B$63*Annahmen!$B$64,0) -> 0.15 | K28: =I28*Annahmen!$B$71+J28*Annahmen!$B$72 -> 32.245 | L28: =IF($A28>=Annahmen!$B$54,Annahmen!$B$65,0) -> 0 | M28: =L28*Annahmen!$B$73 -> 0 | N28: =H28+K28+M28 -> 84.525814 | O28: =N28/(1+Annahmen!$B$8) -> 71.030096 | P28: =O28*(Annahmen!$B$62*Annahmen!$B$74+(1-Annahmen!$B$62)*Annahmen!$B$75)+(E28*Annahmen!$B$61+E28*(1-Annahmen!$B$61)/12+I28+J28+L28)*(1-Annahmen!$B$62)*Annahmen!$B$76 -> 7.474112 | Q28: =Annahmen!$B$66 -> 4 | R28: =Q28*Annahmen!$B$42 -> 115.48385 | S28: =I28*Annahmen!$B$43+(J28+L28)*Annahmen!$B$44 -> 15.684538 | T28: =C28*Annahmen!$B$77 -> 3.418607 | U28: =SUMPRODUCT((((Annahmen!$C$145:$C$155="monatlich")*(Annahmen!$D$145:$D$155<=$A28))+((Annahmen!$C$145:$C$155="einmalig")*(Annahmen!$D$145:$D$155=$A28)))*Annahmen!$B$145:$B$155*Annahmen!$E$145:$E$155) -> 69.98508 | V28: =IF($A28>=Annahmen!$B$54,Annahmen!$B$134,0) -> 200 | W28: =MAX(0,(E28-Annahmen!$B$138)/Annahmen!$B$139) -> 0 | X28: =W28*Annahmen!$B$137 -> 0 | Y28: =O28-P28-R28-S28-T28-U28-V28-X28 -> -341.01609 | Z28: =Z27+Y28 -> -3843.7583 | AA28: =IF(Y28>0,1,0) -> 0 | AB28: =IF(Z28>=0,1,0) -> 0
A29: 12 | B29: 12/2027 | C29: =IF($A29<Annahmen!$B$54,0,IF($A29=Annahmen!$B$54,Annahmen!$B$55,C28*(1+Annahmen!$B$56*(1-C28/Annahmen!$B$57)))) -> 369.02256 | D29: =C29*Annahmen!$B$58 -> 1.8451128 | E29: =E28*(1-Annahmen!$B$59)+D29 -> 9.5251813 | F29: =E29*(1-Annahmen!$B$60) -> 6.6676269 | G29: =E29*Annahmen!$B$60 -> 2.8575544 | H29: =F29*Annahmen!$B$78+G29*Annahmen!$B$79 -> 59.653829 | I29: =IF($A29>=Annahmen!$B$54,Annahmen!$B$63*(1-Annahmen!$B$64),0) -> 0.35 | J29: =IF($A29>=Annahmen!$B$54,Annahmen!$B$63*Annahmen!$B$64,0) -> 0.15 | K29: =I29*Annahmen!$B$71+J29*Annahmen!$B$72 -> 32.245 | L29: =IF($A29>=Annahmen!$B$54,Annahmen!$B$65,0) -> 0 | M29: =L29*Annahmen!$B$73 -> 0 | N29: =H29+K29+M29 -> 91.898829 | O29: =N29/(1+Annahmen!$B$8) -> 77.225907 | P29: =O29*(Annahmen!$B$62*Annahmen!$B$74+(1-Annahmen!$B$62)*Annahmen!$B$75)+(E29*Annahmen!$B$61+E29*(1-Annahmen!$B$61)/12+I29+J29+L29)*(1-Annahmen!$B$62)*Annahmen!$B$76 -> 8.1542627 | Q29: =Annahmen!$B$66 -> 4 | R29: =Q29*Annahmen!$B$42 -> 115.48385 | S29: =I29*Annahmen!$B$43+(J29+L29)*Annahmen!$B$44 -> 15.684538 | T29: =C29*Annahmen!$B$77 -> 3.6902256 | U29: =SUMPRODUCT((((Annahmen!$C$145:$C$155="monatlich")*(Annahmen!$D$145:$D$155<=$A29))+((Annahmen!$C$145:$C$155="einmalig")*(Annahmen!$D$145:$D$155=$A29)))*Annahmen!$B$145:$B$155*Annahmen!$E$145:$E$155) -> 69.98508 | V29: =IF($A29>=Annahmen!$B$54,Annahmen!$B$134,0) -> 200 | W29: =MAX(0,(E29-Annahmen!$B$138)/Annahmen!$B$139) -> 0 | X29: =W29*Annahmen!$B$137 -> 0 | Y29: =O29-P29-R29-S29-T29-U29-V29-X29 -> -335.77205 | Z29: =Z28+Y29 -> -4179.5303 | AA29: =IF(Y29>0,1,0) -> 0 | AB29: =IF(Z29>=0,1,0) -> 0
A30: 13 | B30: 01/2028 | C30: =IF($A30<Annahmen!$B$54,0,IF($A30=Annahmen!$B$54,Annahmen!$B$55,C29*(1+Annahmen!$B$56*(1-C29/Annahmen!$B$57)))) -> 398.32648 | D30: =C30*Annahmen!$B$58 -> 1.9916324 | E30: =E29*(1-Annahmen!$B$59)+D30 -> 10.754799 | F30: =E30*(1-Annahmen!$B$60) -> 7.5283594 | G30: =E30*Annahmen!$B$60 -> 3.2264398 | H30: =F30*Annahmen!$B$78+G30*Annahmen!$B$79 -> 67.354619 | I30: =IF($A30>=Annahmen!$B$54,Annahmen!$B$63*(1-Annahmen!$B$64),0) -> 0.35 | J30: =IF($A30>=Annahmen!$B$54,Annahmen!$B$63*Annahmen!$B$64,0) -> 0.15 | K30: =I30*Annahmen!$B$71+J30*Annahmen!$B$72 -> 32.245 | L30: =IF($A30>=Annahmen!$B$54,Annahmen!$B$65,0) -> 0 | M30: =L30*Annahmen!$B$73 -> 0 | N30: =H30+K30+M30 -> 99.599619 | O30: =N30/(1+Annahmen!$B$8) -> 83.697158 | P30: =O30*(Annahmen!$B$62*Annahmen!$B$74+(1-Annahmen!$B$62)*Annahmen!$B$75)+(E30*Annahmen!$B$61+E30*(1-Annahmen!$B$61)/12+I30+J30+L30)*(1-Annahmen!$B$62)*Annahmen!$B$76 -> 8.8646502 | Q30: =Annahmen!$B$66 -> 4 | R30: =Q30*Annahmen!$B$42 -> 115.48385 | S30: =I30*Annahmen!$B$43+(J30+L30)*Annahmen!$B$44 -> 15.684538 | T30: =C30*Annahmen!$B$77 -> 3.9832648 | U30: =SUMPRODUCT((((Annahmen!$C$145:$C$155="monatlich")*(Annahmen!$D$145:$D$155<=$A30))+((Annahmen!$C$145:$C$155="einmalig")*(Annahmen!$D$145:$D$155=$A30)))*Annahmen!$B$145:$B$155*Annahmen!$E$145:$E$155) -> 69.98508 | V30: =IF($A30>=Annahmen!$B$54,Annahmen!$B$134,0) -> 200 | W30: =MAX(0,(E30-Annahmen!$B$138)/Annahmen!$B$139) -> 0 | X30: =W30*Annahmen!$B$137 -> 0 | Y30: =O30-P30-R30-S30-T30-U30-V30-X30 -> -330.30423 | Z30: =Z29+Y30 -> -4509.8346 | AA30: =IF(Y30>0,1,0) -> 0 | AB30: =IF(Z30>=0,1,0) -> 0
... A41: 24 | B41: 12/2028 | C41: =IF($A41<Annahmen!$B$54,0,IF($A41=Annahmen!$B$54,Annahmen!$B$55,C40*(1+Annahmen!$B$56*(1-C40/Annahmen!$B$57)))) -> 919.71099 | D41: =C41*Annahmen!$B$58 -> 4.5985549 | E41: =E40*(1-Annahmen!$B$59)+D41 -> 30.113255 | F41: =E41*(1-Annahmen!$B$60) -> 21.079279 | G41: =E41*Annahmen!$B$60 -> 9.0339766 | H41: =F41*Annahmen!$B$78+G41*Annahmen!$B$79 -> 188.59179 | I41: =IF($A41>=Annahmen!$B$54,Annahmen!$B$63*(1-Annahmen!$B$64),0) -> 0.35 | J41: =IF($A41>=Annahmen!$B$54,Annahmen!$B$63*Annahmen!$B$64,0) -> 0.15 | K41: =I41*Annahmen!$B$71+J41*Annahmen!$B$72 -> 32.245 | L41: =IF($A41>=Annahmen!$B$54,Annahmen!$B$65,0) -> 0 | M41: =L41*Annahmen!$B$73 -> 0 | N41: =H41+K41+M41 -> 220.83679 | O41: =N41/(1+Annahmen!$B$8) -> 185.57713 | P41: =O41*(Annahmen!$B$62*Annahmen!$B$74+(1-Annahmen!$B$62)*Annahmen!$B$75)+(E41*Annahmen!$B$61+E41*(1-Annahmen!$B$61)/12+I41+J41+L41)*(1-Annahmen!$B$62)*Annahmen!$B$76 -> 20.048616 | Q41: =Annahmen!$B$66 -> 4 | R41: =Q41*Annahmen!$B$42 -> 115.48385 | S41: =I41*Annahmen!$B$43+(J41+L41)*Annahmen!$B$44 -> 15.684538 | T41: =C41*Annahmen!$B$77 -> 9.1971099 | U41: =SUMPRODUCT((((Annahmen!$C$145:$C$155="monatlich")*(Annahmen!$D$145:$D$155<=$A41))+((Annahmen!$C$145:$C$155="einmalig")*(Annahmen!$D$145:$D$155=$A41)))*Annahmen!$B$145:$B$155*Annahmen!$E$145:$E$155) -> 69.98508 | V41: =IF($A41>=Annahmen!$B$54,Annahmen!$B$134,0) -> 200 | W41: =MAX(0,(E41-Annahmen!$B$138)/Annahmen!$B$139) -> 0 | X41: =W41*Annahmen!$B$137 -> 0 | Y41: =O41-P41-R41-S41-T41-U41-V41-X41 -> -244.82206 | Z41: =Z40+Y41 -> -7682.2729 | AA41: =IF(Y41>0,1,0) -> 0 | AB41: =IF(Z41>=0,1,0) -> 0
A45: ="Szenario mittel – "&Annahmen!$C$133 -> Szenario mittel – profitabler Nebenerwerb
A46: Monat | B46: Datum | C46: MAU | D46: Neu zahlend | E46: Zahlende gesamt | F46: davon Hörbuch | G46: davon Voll | H46: Abo-Umsatz brutto | I46: Paten Hörbuch | J46: Paten Hörspiel | K46: Paten-Umsatz brutto | L46: Auftrags-Hörspiele | M46: Auftrag brutto | N46: Umsatz brutto | O46: Umsatz netto | P46: Zahlungs-gebühren | Q46: Katalog-Neuwerke | R46: Katalog-kosten | S46: Produktion Paten/Auftrag | T46: Hosting variabel | U46: Fixkosten anteilig | V46: Marketing | W46: Personal-bedarf FTE | X46: Personal-kosten | Y46: Ergebnis | Z46: Ergebnis kumuliert | AA46: BE monatl. | AB46: BE kum.
A47: 1 | B47: 01/2027 | C47: =IF($A47<Annahmen!$C$54,0,Annahmen!$C$55) -> 0 | D47: =C47*Annahmen!$C$58 -> 0 | E47: =D47 -> 0 | F47: =E47*(1-Annahmen!$C$60) -> 0 | G47: =E47*Annahmen!$C$60 -> 0 | H47: =F47*Annahmen!$C$78+G47*Annahmen!$C$79 -> 0 | I47: =IF($A47>=Annahmen!$C$54,Annahmen!$C$63*(1-Annahmen!$C$64),0) -> 0 | J47: =IF($A47>=Annahmen!$C$54,Annahmen!$C$63*Annahmen!$C$64,0) -> 0 | K47: =I47*Annahmen!$B$71+J47*Annahmen!$B$72 -> 0 | L47: =IF($A47>=Annahmen!$C$54,Annahmen!$C$65,0) -> 0 | M47: =L47*Annahmen!$B$73 -> 0 | N47: =H47+K47+M47 -> 0 | O47: =N47/(1+Annahmen!$B$8) -> 0 | P47: =O47*(Annahmen!$C$62*Annahmen!$B$74+(1-Annahmen!$C$62)*Annahmen!$B$75)+(E47*Annahmen!$C$61+E47*(1-Annahmen!$C$61)/12+I47+J47+L47)*(1-Annahmen!$C$62)*Annahmen!$B$76 -> 0 | Q47: =Annahmen!$C$66 -> 8 | R47: =Q47*Annahmen!$B$42 -> 230.9677 | S47: =I47*Annahmen!$B$43+(J47+L47)*Annahmen!$B$44 -> 0 | T47: =C47*Annahmen!$B$77 -> 0 | U47: =SUMPRODUCT((((Annahmen!$C$145:$C$155="monatlich")*(Annahmen!$D$145:$D$155<=$A47))+((Annahmen!$C$145:$C$155="einmalig")*(Annahmen!$D$145:$D$155=$A47)))*Annahmen!$B$145:$B$155*Annahmen!$E$145:$E$155) -> 232.38508 | V47: =IF($A47>=Annahmen!$C$54,Annahmen!$C$134,0) -> 0 | W47: =MAX(0,(E47-Annahmen!$B$138)/Annahmen!$B$139) -> 0 | X47: =W47*Annahmen!$B$137 -> 0 | Y47: =O47-P47-R47-S47-T47-U47-V47-X47 -> -463.35278 | Z47: =Y47 -> -463.35278 | AA47: =IF(Y47>0,1,0) -> 0 | AB47: =IF(Z47>=0,1,0) -> 0
A48: 2 | B48: 02/2027 | C48: =IF($A48<Annahmen!$C$54,0,IF($A48=Annahmen!$C$54,Annahmen!$C$55,C47*(1+Annahmen!$C$56*(1-C47/Annahmen!$C$57)))) -> 0 | D48: =C48*Annahmen!$C$58 -> 0 | E48: =E47*(1-Annahmen!$C$59)+D48 -> 0 | F48: =E48*(1-Annahmen!$C$60) -> 0 | G48: =E48*Annahmen!$C$60 -> 0 | H48: =F48*Annahmen!$C$78+G48*Annahmen!$C$79 -> 0 | I48: =IF($A48>=Annahmen!$C$54,Annahmen!$C$63*(1-Annahmen!$C$64),0) -> 0 | J48: =IF($A48>=Annahmen!$C$54,Annahmen!$C$63*Annahmen!$C$64,0) -> 0 | K48: =I48*Annahmen!$B$71+J48*Annahmen!$B$72 -> 0 | L48: =IF($A48>=Annahmen!$C$54,Annahmen!$C$65,0) -> 0 | M48: =L48*Annahmen!$B$73 -> 0 | N48: =H48+K48+M48 -> 0 | O48: =N48/(1+Annahmen!$B$8) -> 0 | P48: =O48*(Annahmen!$C$62*Annahmen!$B$74+(1-Annahmen!$C$62)*Annahmen!$B$75)+(E48*Annahmen!$C$61+E48*(1-Annahmen!$C$61)/12+I48+J48+L48)*(1-Annahmen!$C$62)*Annahmen!$B$76 -> 0 | Q48: =Annahmen!$C$66 -> 8 | R48: =Q48*Annahmen!$B$42 -> 230.9677 | S48: =I48*Annahmen!$B$43+(J48+L48)*Annahmen!$B$44 -> 0 | T48: =C48*Annahmen!$B$77 -> 0 | U48: =SUMPRODUCT((((Annahmen!$C$145:$C$155="monatlich")*(Annahmen!$D$145:$D$155<=$A48))+((Annahmen!$C$145:$C$155="einmalig")*(Annahmen!$D$145:$D$155=$A48)))*Annahmen!$B$145:$B$155*Annahmen!$E$145:$E$155) -> 92.320468 | V48: =IF($A48>=Annahmen!$C$54,Annahmen!$C$134,0) -> 0 | W48: =MAX(0,(E48-Annahmen!$B$138)/Annahmen!$B$139) -> 0 | X48: =W48*Annahmen!$B$137 -> 0 | Y48: =O48-P48-R48-S48-T48-U48-V48-X48 -> -323.28817 | Z48: =Z47+Y48 -> -786.64095 | AA48: =IF(Y48>0,1,0) -> 0 | AB48: =IF(Z48>=0,1,0) -> 0
A49: 3 | B49: 03/2027 | C49: =IF($A49<Annahmen!$C$54,0,IF($A49=Annahmen!$C$54,Annahmen!$C$55,C48*(1+Annahmen!$C$56*(1-C48/Annahmen!$C$57)))) -> 500 | D49: =C49*Annahmen!$C$58 -> 5 | E49: =E48*(1-Annahmen!$C$59)+D49 -> 5 | F49: =E49*(1-Annahmen!$C$60) -> 3 | G49: =E49*Annahmen!$C$60 -> 2 | H49: =F49*Annahmen!$C$78+G49*Annahmen!$C$79 -> 31.701667 | I49: =IF($A49>=Annahmen!$C$54,Annahmen!$C$63*(1-Annahmen!$C$64),0) -> 1.2 | J49: =IF($A49>=Annahmen!$C$54,Annahmen!$C$63*Annahmen!$C$64,0) -> 0.8 | K49: =I49*Annahmen!$B$71+J49*Annahmen!$B$72 -> 131.98 | L49: =IF($A49>=Annahmen!$C$54,Annahmen!$C$65,0) -> 0.5 | M49: =L49*Annahmen!$B$73 -> 74.5 | N49: =H49+K49+M49 -> 238.18167 | O49: =N49/(1+Annahmen!$B$8) -> 200.15266 | P49: =O49*(Annahmen!$C$62*Annahmen!$B$74+(1-Annahmen!$C$62)*Annahmen!$B$75)+(E49*Annahmen!$C$61+E49*(1-Annahmen!$C$61)/12+I49+J49+L49)*(1-Annahmen!$C$62)*Annahmen!$B$76 -> 17.220928 | Q49: =Annahmen!$C$66 -> 8 | R49: =Q49*Annahmen!$B$42 -> 230.9677 | S49: =I49*Annahmen!$B$43+(J49+L49)*Annahmen!$B$44 -> 79.174498 | T49: =C49*Annahmen!$B$77 -> 5 | U49: =SUMPRODUCT((((Annahmen!$C$145:$C$155="monatlich")*(Annahmen!$D$145:$D$155<=$A49))+((Annahmen!$C$145:$C$155="einmalig")*(Annahmen!$D$145:$D$155=$A49)))*Annahmen!$B$145:$B$155*Annahmen!$E$145:$E$155) -> 69.98508 | V49: =IF($A49>=Annahmen!$C$54,Annahmen!$C$134,0) -> 500 | W49: =MAX(0,(E49-Annahmen!$B$138)/Annahmen!$B$139) -> 0 | X49: =W49*Annahmen!$B$137 -> 0 | Y49: =O49-P49-R49-S49-T49-U49-V49-X49 -> -702.19555 | Z49: =Z48+Y49 -> -1488.8365 | AA49: =IF(Y49>0,1,0) -> 0 | AB49: =IF(Z49>=0,1,0) -> 0
A50: 4 | B50: 04/2027 | C50: =IF($A50<Annahmen!$C$54,0,IF($A50=Annahmen!$C$54,Annahmen!$C$55,C49*(1+Annahmen!$C$56*(1-C49/Annahmen!$C$57)))) -> 574.8125 | D50: =C50*Annahmen!$C$58 -> 5.748125 | E50: =E49*(1-Annahmen!$C$59)+D50 -> 10.448125 | F50: =E50*(1-Annahmen!$C$60) -> 6.268875 | G50: =E50*Annahmen!$C$60 -> 4.17925 | H50: =F50*Annahmen!$C$78+G50*Annahmen!$C$79 -> 66.244595 | I50: =IF($A50>=Annahmen!$C$54,Annahmen!$C$63*(1-Annahmen!$C$64),0) -> 1.2 | J50: =IF($A50>=Annahmen!$C$54,Annahmen!$C$63*Annahmen!$C$64,0) -> 0.8 | K50: =I50*Annahmen!$B$71+J50*Annahmen!$B$72 -> 131.98 | L50: =IF($A50>=Annahmen!$C$54,Annahmen!$C$65,0) -> 0.5 | M50: =L50*Annahmen!$B$73 -> 74.5 | N50: =H50+K50+M50 -> 272.7246 | O50: =N50/(1+Annahmen!$B$8) -> 229.18033 | P50: =O50*(Annahmen!$C$62*Annahmen!$B$74+(1-Annahmen!$C$62)*Annahmen!$B$75)+(E50*Annahmen!$C$61+E50*(1-Annahmen!$C$61)/12+I50+J50+L50)*(1-Annahmen!$C$62)*Annahmen!$B$76 -> 20.047021 | Q50: =Annahmen!$C$66 -> 8 | R50: =Q50*Annahmen!$B$42 -> 230.9677 | S50: =I50*Annahmen!$B$43+(J50+L50)*Annahmen!$B$44 -> 79.174498 | T50: =C50*Annahmen!$B$77 -> 5.748125 | U50: =SUMPRODUCT((((Annahmen!$C$145:$C$155="monatlich")*(Annahmen!$D$145:$D$155<=$A50))+((Annahmen!$C$145:$C$155="einmalig")*(Annahmen!$D$145:$D$155=$A50)))*Annahmen!$B$145:$B$155*Annahmen!$E$145:$E$155) -> 69.98508 | V50: =IF($A50>=Annahmen!$C$54,Annahmen!$C$134,0) -> 500 | W50: =MAX(0,(E50-Annahmen!$B$138)/Annahmen!$B$139) -> 0 | X50: =W50*Annahmen!$B$137 -> 0 | Y50: =O50-P50-R50-S50-T50-U50-V50-X50 -> -676.74209 | Z50: =Z49+Y50 -> -2165.5786 | AA50: =IF(Y50>0,1,0) -> 0 | AB50: =IF(Z50>=0,1,0) -> 0
A51: 5 | B51: 05/2027 | C51: =IF($A51<Annahmen!$C$54,0,IF($A51=Annahmen!$C$54,Annahmen!$C$55,C50*(1+Annahmen!$C$56*(1-C50/Annahmen!$C$57)))) -> 660.78657 | D51: =C51*Annahmen!$C$58 -> 6.6078657 | E51: =E50*(1-Annahmen!$C$59)+D51 -> 16.429103 | F51: =E51*(1-Annahmen!$C$60) -> 9.8574619 | G51: =E51*Annahmen!$C$60 -> 6.5716413 | H51: =F51*Annahmen!$C$78+G51*Annahmen!$C$79 -> 104.16599 | I51: =IF($A51>=Annahmen!$C$54,Annahmen!$C$63*(1-Annahmen!$C$64),0) -> 1.2 | J51: =IF($A51>=Annahmen!$C$54,Annahmen!$C$63*Annahmen!$C$64,0) -> 0.8 | K51: =I51*Annahmen!$B$71+J51*Annahmen!$B$72 -> 131.98 | L51: =IF($A51>=Annahmen!$C$54,Annahmen!$C$65,0) -> 0.5 | M51: =L51*Annahmen!$B$73 -> 74.5 | N51: =H51+K51+M51 -> 310.64599 | O51: =N51/(1+Annahmen!$B$8) -> 261.04705 | P51: =O51*(Annahmen!$C$62*Annahmen!$B$74+(1-Annahmen!$C$62)*Annahmen!$B$75)+(E51*Annahmen!$C$61+E51*(1-Annahmen!$C$61)/12+I51+J51+L51)*(1-Annahmen!$C$62)*Annahmen!$B$76 -> 23.149519 | Q51: =Annahmen!$C$66 -> 8 | R51: =Q51*Annahmen!$B$42 -> 230.9677 | S51: =I51*Annahmen!$B$43+(J51+L51)*Annahmen!$B$44 -> 79.174498 | T51: =C51*Annahmen!$B$77 -> 6.6078657 | U51: =SUMPRODUCT((((Annahmen!$C$145:$C$155="monatlich")*(Annahmen!$D$145:$D$155<=$A51))+((Annahmen!$C$145:$C$155="einmalig")*(Annahmen!$D$145:$D$155=$A51)))*Annahmen!$B$145:$B$155*Annahmen!$E$145:$E$155) -> 309.98508 | V51: =IF($A51>=Annahmen!$C$54,Annahmen!$C$134,0) -> 500 | W51: =MAX(0,(E51-Annahmen!$B$138)/Annahmen!$B$139) -> 0 | X51: =W51*Annahmen!$B$137 -> 0 | Y51: =O51-P51-R51-S51-T51-U51-V51-X51 -> -888.83761 | Z51: =Z50+Y51 -> -3054.4162 | AA51: =IF(Y51>0,1,0) -> 0 | AB51: =IF(Z51>=0,1,0) -> 0
A52: 6 | B52: 06/2027 | C52: =IF($A52<Annahmen!$C$54,0,IF($A52=Annahmen!$C$54,Annahmen!$C$55,C51*(1+Annahmen!$C$56*(1-C51/Annahmen!$C$57)))) -> 759.57707 | D52: =C52*Annahmen!$C$58 -> 7.5957707 | E52: =E51*(1-Annahmen!$C$59)+D52 -> 23.039128 | F52: =E52*(1-Annahmen!$C$60) -> 13.823477 | G52: =E52*Annahmen!$C$60 -> 9.2156511 | H52: =F52*Annahmen!$C$78+G52*Annahmen!$C$79 -> 146.07575 | I52: =IF($A52>=Annahmen!$C$54,Annahmen!$C$63*(1-Annahmen!$C$64),0) -> 1.2 | J52: =IF($A52>=Annahmen!$C$54,Annahmen!$C$63*Annahmen!$C$64,0) -> 0.8 | K52: =I52*Annahmen!$B$71+J52*Annahmen!$B$72 -> 131.98 | L52: =IF($A52>=Annahmen!$C$54,Annahmen!$C$65,0) -> 0.5 | M52: =L52*Annahmen!$B$73 -> 74.5 | N52: =H52+K52+M52 -> 352.55575 | O52: =N52/(1+Annahmen!$B$8) -> 296.26534 | P52: =O52*(Annahmen!$C$62*Annahmen!$B$74+(1-Annahmen!$C$62)*Annahmen!$B$75)+(E52*Annahmen!$C$61+E52*(1-Annahmen!$C$61)/12+I52+J52+L52)*(1-Annahmen!$C$62)*Annahmen!$B$76 -> 26.578321 | Q52: =Annahmen!$C$66 -> 8 | R52: =Q52*Annahmen!$B$42 -> 230.9677 | S52: =I52*Annahmen!$B$43+(J52+L52)*Annahmen!$B$44 -> 79.174498 | T52: =C52*Annahmen!$B$77 -> 7.5957707 | U52: =SUMPRODUCT((((Annahmen!$C$145:$C$155="monatlich")*(Annahmen!$D$145:$D$155<=$A52))+((Annahmen!$C$145:$C$155="einmalig")*(Annahmen!$D$145:$D$155=$A52)))*Annahmen!$B$145:$B$155*Annahmen!$E$145:$E$155) -> 69.98508 | V52: =IF($A52>=Annahmen!$C$54,Annahmen!$C$134,0) -> 500 | W52: =MAX(0,(E52-Annahmen!$B$138)/Annahmen!$B$139) -> 0 | X52: =W52*Annahmen!$B$137 -> 0 | Y52: =O52-P52-R52-S52-T52-U52-V52-X52 -> -618.03604 | Z52: =Z51+Y52 -> -3672.4522 | AA52: =IF(Y52>0,1,0) -> 0 | AB52: =IF(Z52>=0,1,0) -> 0
A53: 7 | B53: 07/2027 | C53: =IF($A53<Annahmen!$C$54,0,IF($A53=Annahmen!$C$54,Annahmen!$C$55,C52*(1+Annahmen!$C$56*(1-C52/Annahmen!$C$57)))) -> 873.08092 | D53: =C53*Annahmen!$C$58 -> 8.7308092 | E53: =E52*(1-Annahmen!$C$59)+D53 -> 30.387589 | F53: =E53*(1-Annahmen!$C$60) -> 18.232554 | G53: =E53*Annahmen!$C$60 -> 12.155036 | H53: =F53*Annahmen!$C$78+G53*Annahmen!$C$79 -> 192.66744 | I53: =IF($A53>=Annahmen!$C$54,Annahmen!$C$63*(1-Annahmen!$C$64),0) -> 1.2 | J53: =IF($A53>=Annahmen!$C$54,Annahmen!$C$63*Annahmen!$C$64,0) -> 0.8 | K53: =I53*Annahmen!$B$71+J53*Annahmen!$B$72 -> 131.98 | L53: =IF($A53>=Annahmen!$C$54,Annahmen!$C$65,0) -> 0.5 | M53: =L53*Annahmen!$B$73 -> 74.5 | N53: =H53+K53+M53 -> 399.14744 | O53: =N53/(1+Annahmen!$B$8) -> 335.41802 | P53: =O53*(Annahmen!$C$62*Annahmen!$B$74+(1-Annahmen!$C$62)*Annahmen!$B$75)+(E53*Annahmen!$C$61+E53*(1-Annahmen!$C$61)/12+I53+J53+L53)*(1-Annahmen!$C$62)*Annahmen!$B$76 -> 30.390171 | Q53: =Annahmen!$C$66 -> 8 | R53: =Q53*Annahmen!$B$42 -> 230.9677 | S53: =I53*Annahmen!$B$43+(J53+L53)*Annahmen!$B$44 -> 79.174498 | T53: =C53*Annahmen!$B$77 -> 8.7308092 | U53: =SUMPRODUCT((((Annahmen!$C$145:$C$155="monatlich")*(Annahmen!$D$145:$D$155<=$A53))+((Annahmen!$C$145:$C$155="einmalig")*(Annahmen!$D$145:$D$155=$A53)))*Annahmen!$B$145:$B$155*Annahmen!$E$145:$E$155) -> 69.98508 | V53: =IF($A53>=Annahmen!$C$54,Annahmen!$C$134,0) -> 500 | W53: =MAX(0,(E53-Annahmen!$B$138)/Annahmen!$B$139) -> 0 | X53: =W53*Annahmen!$B$137 -> 0 | Y53: =O53-P53-R53-S53-T53-U53-V53-X53 -> -583.83024 | Z53: =Z52+Y53 -> -4256.2825 | AA53: =IF(Y53>0,1,0) -> 0 | AB53: =IF(Z53>=0,1,0) -> 0
A54: 8 | B54: 08/2027 | C54: =IF($A54<Annahmen!$C$54,0,IF($A54=Annahmen!$C$54,Annahmen!$C$55,C53*(1+Annahmen!$C$56*(1-C53/Annahmen!$C$57)))) -> 1003.4714 | D54: =C54*Annahmen!$C$58 -> 10.034714 | E54: =E53*(1-Annahmen!$C$59)+D54 -> 38.599047 | F54: =E54*(1-Annahmen!$C$60) -> 23.159428 | G54: =E54*Annahmen!$C$60 -> 15.439619 | H54: =F54*Annahmen!$C$78+G54*Annahmen!$C$79 -> 244.73083 | I54: =IF($A54>=Annahmen!$C$54,Annahmen!$C$63*(1-Annahmen!$C$64),0) -> 1.2 | J54: =IF($A54>=Annahmen!$C$54,Annahmen!$C$63*Annahmen!$C$64,0) -> 0.8 | K54: =I54*Annahmen!$B$71+J54*Annahmen!$B$72 -> 131.98 | L54: =IF($A54>=Annahmen!$C$54,Annahmen!$C$65,0) -> 0.5 | M54: =L54*Annahmen!$B$73 -> 74.5 | N54: =H54+K54+M54 -> 451.21083 | O54: =N54/(1+Annahmen!$B$8) -> 379.16876 | P54: =O54*(Annahmen!$C$62*Annahmen!$B$74+(1-Annahmen!$C$62)*Annahmen!$B$75)+(E54*Annahmen!$C$61+E54*(1-Annahmen!$C$61)/12+I54+J54+L54)*(1-Annahmen!$C$62)*Annahmen!$B$76 -> 34.649681 | Q54: =Annahmen!$C$66 -> 8 | R54: =Q54*Annahmen!$B$42 -> 230.9677 | S54: =I54*Annahmen!$B$43+(J54+L54)*Annahmen!$B$44 -> 79.174498 | T54: =C54*Annahmen!$B$77 -> 10.034714 | U54: =SUMPRODUCT((((Annahmen!$C$145:$C$155="monatlich")*(Annahmen!$D$145:$D$155<=$A54))+((Annahmen!$C$145:$C$155="einmalig")*(Annahmen!$D$145:$D$155=$A54)))*Annahmen!$B$145:$B$155*Annahmen!$E$145:$E$155) -> 69.98508 | V54: =IF($A54>=Annahmen!$C$54,Annahmen!$C$134,0) -> 500 | W54: =MAX(0,(E54-Annahmen!$B$138)/Annahmen!$B$139) -> 0 | X54: =W54*Annahmen!$B$137 -> 0 | Y54: =O54-P54-R54-S54-T54-U54-V54-X54 -> -545.64291 | Z54: =Z53+Y54 -> -4801.9254 | AA54: =IF(Y54>0,1,0) -> 0 | AB54: =IF(Z54>=0,1,0) -> 0
A55: 9 | B55: 09/2027 | C55: =IF($A55<Annahmen!$C$54,0,IF($A55=Annahmen!$C$54,Annahmen!$C$55,C54*(1+Annahmen!$C$56*(1-C54/Annahmen!$C$57)))) -> 1153.2368 | D55: =C55*Annahmen!$C$58 -> 11.532368 | E55: =E54*(1-Annahmen!$C$59)+D55 -> 47.815473 | F55: =E55*(1-Annahmen!$C$60) -> 28.689284 | G55: =E55*Annahmen!$C$60 -> 19.126189 | H55: =F55*Annahmen!$C$78+G55*Annahmen!$C$79 -> 303.16604 | I55: =IF($A55>=Annahmen!$C$54,Annahmen!$C$63*(1-Annahmen!$C$64),0) -> 1.2 | J55: =IF($A55>=Annahmen!$C$54,Annahmen!$C$63*Annahmen!$C$64,0) -> 0.8 | K55: =I55*Annahmen!$B$71+J55*Annahmen!$B$72 -> 131.98 | L55: =IF($A55>=Annahmen!$C$54,Annahmen!$C$65,0) -> 0.5 | M55: =L55*Annahmen!$B$73 -> 74.5 | N55: =H55+K55+M55 -> 509.64604 | O55: =N55/(1+Annahmen!$B$8) -> 428.27398 | P55: =O55*(Annahmen!$C$62*Annahmen!$B$74+(1-Annahmen!$C$62)*Annahmen!$B$75)+(E55*Annahmen!$C$61+E55*(1-Annahmen!$C$61)/12+I55+J55+L55)*(1-Annahmen!$C$62)*Annahmen!$B$76 -> 39.430495 | Q55: =Annahmen!$C$66 -> 8 | R55: =Q55*Annahmen!$B$42 -> 230.9677 | S55: =I55*Annahmen!$B$43+(J55+L55)*Annahmen!$B$44 -> 79.174498 | T55: =C55*Annahmen!$B$77 -> 11.532368 | U55: =SUMPRODUCT((((Annahmen!$C$145:$C$155="monatlich")*(Annahmen!$D$145:$D$155<=$A55))+((Annahmen!$C$145:$C$155="einmalig")*(Annahmen!$D$145:$D$155=$A55)))*Annahmen!$B$145:$B$155*Annahmen!$E$145:$E$155) -> 69.98508 | V55: =IF($A55>=Annahmen!$C$54,Annahmen!$C$134,0) -> 500 | W55: =MAX(0,(E55-Annahmen!$B$138)/Annahmen!$B$139) -> 0 | X55: =W55*Annahmen!$B$137 -> 0 | Y55: =O55-P55-R55-S55-T55-U55-V55-X55 -> -502.81616 | Z55: =Z54+Y55 -> -5304.7416 | AA55: =IF(Y55>0,1,0) -> 0 | AB55: =IF(Z55>=0,1,0) -> 0
A56: 10 | B56: 10/2027 | C56: =IF($A56<Annahmen!$C$54,0,IF($A56=Annahmen!$C$54,Annahmen!$C$55,C55*(1+Annahmen!$C$56*(1-C55/Annahmen!$C$57)))) -> 1325.2249 | D56: =C56*Annahmen!$C$58 -> 13.252249 | E56: =E55*(1-Annahmen!$C$59)+D56 -> 58.198794 | F56: =E56*(1-Annahmen!$C$60) -> 34.919276 | G56: =E56*Annahmen!$C$60 -> 23.279517 | H56: =F56*Annahmen!$C$78+G56*Annahmen!$C$79 -> 368.99975 | I56: =IF($A56>=Annahmen!$C$54,Annahmen!$C$63*(1-Annahmen!$C$64),0) -> 1.2 | J56: =IF($A56>=Annahmen!$C$54,Annahmen!$C$63*Annahmen!$C$64,0) -> 0.8 | K56: =I56*Annahmen!$B$71+J56*Annahmen!$B$72 -> 131.98 | L56: =IF($A56>=Annahmen!$C$54,Annahmen!$C$65,0) -> 0.5 | M56: =L56*Annahmen!$B$73 -> 74.5 | N56: =H56+K56+M56 -> 575.47975 | O56: =N56/(1+Annahmen!$B$8) -> 483.59643 | P56: =O56*(Annahmen!$C$62*Annahmen!$B$74+(1-Annahmen!$C$62)*Annahmen!$B$75)+(E56*Annahmen!$C$61+E56*(1-Annahmen!$C$61)/12+I56+J56+L56)*(1-Annahmen!$C$62)*Annahmen!$B$76 -> 44.81661 | Q56: =Annahmen!$C$66 -> 8 | R56: =Q56*Annahmen!$B$42 -> 230.9677 | S56: =I56*Annahmen!$B$43+(J56+L56)*Annahmen!$B$44 -> 79.174498 | T56: =C56*Annahmen!$B$77 -> 13.252249 | U56: =SUMPRODUCT((((Annahmen!$C$145:$C$155="monatlich")*(Annahmen!$D$145:$D$155<=$A56))+((Annahmen!$C$145:$C$155="einmalig")*(Annahmen!$D$145:$D$155=$A56)))*Annahmen!$B$145:$B$155*Annahmen!$E$145:$E$155) -> 69.98508 | V56: =IF($A56>=Annahmen!$C$54,Annahmen!$C$134,0) -> 500 | W56: =MAX(0,(E56-Annahmen!$B$138)/Annahmen!$B$139) -> 0 | X56: =W56*Annahmen!$B$137 -> 0 | Y56: =O56-P56-R56-S56-T56-U56-V56-X56 -> -454.59971 | Z56: =Z55+Y56 -> -5759.3413 | AA56: =IF(Y56>0,1,0) -> 0 | AB56: =IF(Z56>=0,1,0) -> 0
A57: 11 | B57: 11/2027 | C57: =IF($A57<Annahmen!$C$54,0,IF($A57=Annahmen!$C$54,Annahmen!$C$55,C56*(1+Annahmen!$C$56*(1-C56/Annahmen!$C$57)))) -> 1522.6915 | D57: =C57*Annahmen!$C$58 -> 15.226915 | E57: =E56*(1-Annahmen!$C$59)+D57 -> 69.933781 | F57: =E57*(1-Annahmen!$C$60) -> 41.960268 | G57: =E57*Annahmen!$C$60 -> 27.973512 | H57: =F57*Annahmen!$C$78+G57*Annahmen!$C$79 -> 443.40348 | I57: =IF($A57>=Annahmen!$C$54,Annahmen!$C$63*(1-Annahmen!$C$64),0) -> 1.2 | J57: =IF($A57>=Annahmen!$C$54,Annahmen!$C$63*Annahmen!$C$64,0) -> 0.8 | K57: =I57*Annahmen!$B$71+J57*Annahmen!$B$72 -> 131.98 | L57: =IF($A57>=Annahmen!$C$54,Annahmen!$C$65,0) -> 0.5 | M57: =L57*Annahmen!$B$73 -> 74.5 | N57: =H57+K57+M57 -> 649.88348 | O57: =N57/(1+Annahmen!$B$8) -> 546.12057 | P57: =O57*(Annahmen!$C$62*Annahmen!$B$74+(1-Annahmen!$C$62)*Annahmen!$B$75)+(E57*Annahmen!$C$61+E57*(1-Annahmen!$C$61)/12+I57+J57+L57)*(1-Annahmen!$C$62)*Annahmen!$B$76 -> 50.903871 | Q57: =Annahmen!$C$66 -> 8 | R57: =Q57*Annahmen!$B$42 -> 230.9677 | S57: =I57*Annahmen!$B$43+(J57+L57)*Annahmen!$B$44 -> 79.174498 | T57: =C57*Annahmen!$B$77 -> 15.226915 | U57: =SUMPRODUCT((((Annahmen!$C$145:$C$155="monatlich")*(Annahmen!$D$145:$D$155<=$A57))+((Annahmen!$C$145:$C$155="einmalig")*(Annahmen!$D$145:$D$155=$A57)))*Annahmen!$B$145:$B$155*Annahmen!$E$145:$E$155) -> 69.98508 | V57: =IF($A57>=Annahmen!$C$54,Annahmen!$C$134,0) -> 500 | W57: =MAX(0,(E57-Annahmen!$B$138)/Annahmen!$B$139) -> 0 | X57: =W57*Annahmen!$B$137 -> 0 | Y57: =O57-P57-R57-S57-T57-U57-V57-X57 -> -400.13749 | Z57: =Z56+Y57 -> -6159.4788 | AA57: =IF(Y57>0,1,0) -> 0 | AB57: =IF(Z57>=0,1,0) -> 0
A58: 12 | B58: 12/2027 | C58: =IF($A58<Annahmen!$C$54,0,IF($A58=Annahmen!$C$54,Annahmen!$C$55,C57*(1+Annahmen!$C$56*(1-C57/Annahmen!$C$57)))) -> 1749.3562 | D58: =C58*Annahmen!$C$58 -> 17.493562 | E58: =E57*(1-Annahmen!$C$59)+D58 -> 83.231316 | F58: =E58*(1-Annahmen!$C$60) -> 49.93879 | G58: =E58*Annahmen!$C$60 -> 33.292526 | H58: =F58*Annahmen!$C$78+G58*Annahmen!$C$79 -> 527.71429 | I58: =IF($A58>=Annahmen!$C$54,Annahmen!$C$63*(1-Annahmen!$C$64),0) -> 1.2 | J58: =IF($A58>=Annahmen!$C$54,Annahmen!$C$63*Annahmen!$C$64,0) -> 0.8 | K58: =I58*Annahmen!$B$71+J58*Annahmen!$B$72 -> 131.98 | L58: =IF($A58>=Annahmen!$C$54,Annahmen!$C$65,0) -> 0.5 | M58: =L58*Annahmen!$B$73 -> 74.5 | N58: =H58+K58+M58 -> 734.19429 | O58: =N58/(1+Annahmen!$B$8) -> 616.96999 | P58: =O58*(Annahmen!$C$62*Annahmen!$B$74+(1-Annahmen!$C$62)*Annahmen!$B$75)+(E58*Annahmen!$C$61+E58*(1-Annahmen!$C$61)/12+I58+J58+L58)*(1-Annahmen!$C$62)*Annahmen!$B$76 -> 57.80167 | Q58: =Annahmen!$C$66 -> 8 | R58: =Q58*Annahmen!$B$42 -> 230.9677 | S58: =I58*Annahmen!$B$43+(J58+L58)*Annahmen!$B$44 -> 79.174498 | T58: =C58*Annahmen!$B$77 -> 17.493562 | U58: =SUMPRODUCT((((Annahmen!$C$145:$C$155="monatlich")*(Annahmen!$D$145:$D$155<=$A58))+((Annahmen!$C$145:$C$155="einmalig")*(Annahmen!$D$145:$D$155=$A58)))*Annahmen!$B$145:$B$155*Annahmen!$E$145:$E$155) -> 69.98508 | V58: =IF($A58>=Annahmen!$C$54,Annahmen!$C$134,0) -> 500 | W58: =MAX(0,(E58-Annahmen!$B$138)/Annahmen!$B$139) -> 0 | X58: =W58*Annahmen!$B$137 -> 0 | Y58: =O58-P58-R58-S58-T58-U58-V58-X58 -> -338.45252 | Z58: =Z57+Y58 -> -6497.9313 | AA58: =IF(Y58>0,1,0) -> 0 | AB58: =IF(Z58>=0,1,0) -> 0
A59: 13 | B59: 01/2028 | C59: =IF($A59<Annahmen!$C$54,0,IF($A59=Annahmen!$C$54,Annahmen!$C$55,C58*(1+Annahmen!$C$56*(1-C58/Annahmen!$C$57)))) -> 2009.4645 | D59: =C59*Annahmen!$C$58 -> 20.094645 | E59: =E58*(1-Annahmen!$C$59)+D59 -> 98.332082 | F59: =E59*(1-Annahmen!$C$60) -> 58.999249 | G59: =E59*Annahmen!$C$60 -> 39.332833 | H59: =F59*Annahmen!$C$78+G59*Annahmen!$C$79 -> 623.45818 | I59: =IF($A59>=Annahmen!$C$54,Annahmen!$C$63*(1-Annahmen!$C$64),0) -> 1.2 | J59: =IF($A59>=Annahmen!$C$54,Annahmen!$C$63*Annahmen!$C$64,0) -> 0.8 | K59: =I59*Annahmen!$B$71+J59*Annahmen!$B$72 -> 131.98 | L59: =IF($A59>=Annahmen!$C$54,Annahmen!$C$65,0) -> 0.5 | M59: =L59*Annahmen!$B$73 -> 74.5 | N59: =H59+K59+M59 -> 829.93818 | O59: =N59/(1+Annahmen!$B$8) -> 697.42704 | P59: =O59*(Annahmen!$C$62*Annahmen!$B$74+(1-Annahmen!$C$62)*Annahmen!$B$75)+(E59*Annahmen!$C$61+E59*(1-Annahmen!$C$61)/12+I59+J59+L59)*(1-Annahmen!$C$62)*Annahmen!$B$76 -> 65.634854 | Q59: =Annahmen!$C$66 -> 8 | R59: =Q59*Annahmen!$B$42 -> 230.9677 | S59: =I59*Annahmen!$B$43+(J59+L59)*Annahmen!$B$44 -> 79.174498 | T59: =C59*Annahmen!$B$77 -> 20.094645 | U59: =SUMPRODUCT((((Annahmen!$C$145:$C$155="monatlich")*(Annahmen!$D$145:$D$155<=$A59))+((Annahmen!$C$145:$C$155="einmalig")*(Annahmen!$D$145:$D$155=$A59)))*Annahmen!$B$145:$B$155*Annahmen!$E$145:$E$155) -> 69.98508 | V59: =IF($A59>=Annahmen!$C$54,Annahmen!$C$134,0) -> 500 | W59: =MAX(0,(E59-Annahmen!$B$138)/Annahmen!$B$139) -> 0 | X59: =W59*Annahmen!$B$137 -> 0 | Y59: =O59-P59-R59-S59-T59-U59-V59-X59 -> -268.42974 | Z59: =Z58+Y59 -> -6766.361 | AA59: =IF(Y59>0,1,0) -> 0 | AB59: =IF(Z59>=0,1,0) -> 0
... A70: 24 | B70: 12/2028 | C70: =IF($A70<Annahmen!$C$54,0,IF($A70=Annahmen!$C$54,Annahmen!$C$55,C69*(1+Annahmen!$C$56*(1-C69/Annahmen!$C$57)))) -> 9058.7654 | D70: =C70*Annahmen!$C$58 -> 90.587654 | E70: =E69*(1-Annahmen!$C$59)+D70 -> 497.36837 | F70: =E70*(1-Annahmen!$C$60) -> 298.42102 | G70: =E70*Annahmen!$C$60 -> 198.94735 | H70: =F70*Annahmen!$C$78+G70*Annahmen!$C$79 -> 3153.4813 | I70: =IF($A70>=Annahmen!$C$54,Annahmen!$C$63*(1-Annahmen!$C$64),0) -> 1.2 | J70: =IF($A70>=Annahmen!$C$54,Annahmen!$C$63*Annahmen!$C$64,0) -> 0.8 | K70: =I70*Annahmen!$B$71+J70*Annahmen!$B$72 -> 131.98 | L70: =IF($A70>=Annahmen!$C$54,Annahmen!$C$65,0) -> 0.5 | M70: =L70*Annahmen!$B$73 -> 74.5 | N70: =H70+K70+M70 -> 3359.9613 | O70: =N70/(1+Annahmen!$B$8) -> 2823.4969 | P70: =O70*(Annahmen!$C$62*Annahmen!$B$74+(1-Annahmen!$C$62)*Annahmen!$B$75)+(E70*Annahmen!$C$61+E70*(1-Annahmen!$C$61)/12+I70+J70+L70)*(1-Annahmen!$C$62)*Annahmen!$B$76 -> 272.62599 | Q70: =Annahmen!$C$66 -> 8 | R70: =Q70*Annahmen!$B$42 -> 230.9677 | S70: =I70*Annahmen!$B$43+(J70+L70)*Annahmen!$B$44 -> 79.174498 | T70: =C70*Annahmen!$B$77 -> 90.587654 | U70: =SUMPRODUCT((((Annahmen!$C$145:$C$155="monatlich")*(Annahmen!$D$145:$D$155<=$A70))+((Annahmen!$C$145:$C$155="einmalig")*(Annahmen!$D$145:$D$155=$A70)))*Annahmen!$B$145:$B$155*Annahmen!$E$145:$E$155) -> 69.98508 | V70: =IF($A70>=Annahmen!$C$54,Annahmen!$C$134,0) -> 500 | W70: =MAX(0,(E70-Annahmen!$B$138)/Annahmen!$B$139) -> 0 | X70: =W70*Annahmen!$B$137 -> 0 | Y70: =O70-P70-R70-S70-T70-U70-V70-X70 -> 1580.1559 | Z70: =Z69+Y70 -> -998.25198 | AA70: =IF(Y70>0,1,0) -> 1 | AB70: =IF(Z70>=0,1,0) -> 0
A74: ="Szenario stark – "&Annahmen!$D$133 -> Szenario stark – skalierbares Business
A75: Monat | B75: Datum | C75: MAU | D75: Neu zahlend | E75: Zahlende gesamt | F75: davon Hörbuch | G75: davon Voll | H75: Abo-Umsatz brutto | I75: Paten Hörbuch | J75: Paten Hörspiel | K75: Paten-Umsatz brutto | L75: Auftrags-Hörspiele | M75: Auftrag brutto | N75: Umsatz brutto | O75: Umsatz netto | P75: Zahlungs-gebühren | Q75: Katalog-Neuwerke | R75: Katalog-kosten | S75: Produktion Paten/Auftrag | T75: Hosting variabel | U75: Fixkosten anteilig | V75: Marketing | W75: Personal-bedarf FTE | X75: Personal-kosten | Y75: Ergebnis | Z75: Ergebnis kumuliert | AA75: BE monatl. | AB75: BE kum.
A76: 1 | B76: 01/2027 | C76: =IF($A76<Annahmen!$D$54,0,Annahmen!$D$55) -> 0 | D76: =C76*Annahmen!$D$58 -> 0 | E76: =D76 -> 0 | F76: =E76*(1-Annahmen!$D$60) -> 0 | G76: =E76*Annahmen!$D$60 -> 0 | H76: =F76*Annahmen!$D$78+G76*Annahmen!$D$79 -> 0 | I76: =IF($A76>=Annahmen!$D$54,Annahmen!$D$63*(1-Annahmen!$D$64),0) -> 0 | J76: =IF($A76>=Annahmen!$D$54,Annahmen!$D$63*Annahmen!$D$64,0) -> 0 | K76: =I76*Annahmen!$B$71+J76*Annahmen!$B$72 -> 0 | L76: =IF($A76>=Annahmen!$D$54,Annahmen!$D$65,0) -> 0 | M76: =L76*Annahmen!$B$73 -> 0 | N76: =H76+K76+M76 -> 0 | O76: =N76/(1+Annahmen!$B$8) -> 0 | P76: =O76*(Annahmen!$D$62*Annahmen!$B$74+(1-Annahmen!$D$62)*Annahmen!$B$75)+(E76*Annahmen!$D$61+E76*(1-Annahmen!$D$61)/12+I76+J76+L76)*(1-Annahmen!$D$62)*Annahmen!$B$76 -> 0 | Q76: =Annahmen!$D$66 -> 12 | R76: =Q76*Annahmen!$B$42 -> 346.45155 | S76: =I76*Annahmen!$B$43+(J76+L76)*Annahmen!$B$44 -> 0 | T76: =C76*Annahmen!$B$77 -> 0 | U76: =SUMPRODUCT((((Annahmen!$C$145:$C$155="monatlich")*(Annahmen!$D$145:$D$155<=$A76))+((Annahmen!$C$145:$C$155="einmalig")*(Annahmen!$D$145:$D$155=$A76)))*Annahmen!$B$145:$B$155*Annahmen!$E$145:$E$155) -> 232.38508 | V76: =IF($A76>=Annahmen!$D$54,Annahmen!$D$134,0) -> 0 | W76: =MAX(0,(E76-Annahmen!$B$138)/Annahmen!$B$139) -> 0 | X76: =W76*Annahmen!$B$137 -> 0 | Y76: =O76-P76-R76-S76-T76-U76-V76-X76 -> -578.83663 | Z76: =Y76 -> -578.83663 | AA76: =IF(Y76>0,1,0) -> 0 | AB76: =IF(Z76>=0,1,0) -> 0
A77: 2 | B77: 02/2027 | C77: =IF($A77<Annahmen!$D$54,0,IF($A77=Annahmen!$D$54,Annahmen!$D$55,C76*(1+Annahmen!$D$56*(1-C76/Annahmen!$D$57)))) -> 1000 | D77: =C77*Annahmen!$D$58 -> 15 | E77: =E76*(1-Annahmen!$D$59)+D77 -> 15 | F77: =E77*(1-Annahmen!$D$60) -> 7.5 | G77: =E77*Annahmen!$D$60 -> 7.5 | H77: =F77*Annahmen!$D$78+G77*Annahmen!$D$79 -> 96.16875 | I77: =IF($A77>=Annahmen!$D$54,Annahmen!$D$63*(1-Annahmen!$D$64),0) -> 2.5 | J77: =IF($A77>=Annahmen!$D$54,Annahmen!$D$63*Annahmen!$D$64,0) -> 2.5 | K77: =I77*Annahmen!$B$71+J77*Annahmen!$B$72 -> 337.45 | L77: =IF($A77>=Annahmen!$D$54,Annahmen!$D$65,0) -> 1 | M77: =L77*Annahmen!$B$73 -> 149 | N77: =H77+K77+M77 -> 582.61875 | O77: =N77/(1+Annahmen!$B$8) -> 489.59559 | P77: =O77*(Annahmen!$D$62*Annahmen!$B$74+(1-Annahmen!$D$62)*Annahmen!$B$75)+(E77*Annahmen!$D$61+E77*(1-Annahmen!$D$61)/12+I77+J77+L77)*(1-Annahmen!$D$62)*Annahmen!$B$76 -> 35.900846 | Q77: =Annahmen!$D$66 -> 12 | R77: =Q77*Annahmen!$B$42 -> 346.45155 | S77: =I77*Annahmen!$B$43+(J77+L77)*Annahmen!$B$44 -> 190.53823 | T77: =C77*Annahmen!$B$77 -> 10 | U77: =SUMPRODUCT((((Annahmen!$C$145:$C$155="monatlich")*(Annahmen!$D$145:$D$155<=$A77))+((Annahmen!$C$145:$C$155="einmalig")*(Annahmen!$D$145:$D$155=$A77)))*Annahmen!$B$145:$B$155*Annahmen!$E$145:$E$155) -> 92.320468 | V77: =IF($A77>=Annahmen!$D$54,Annahmen!$D$134,0) -> 2000 | W77: =MAX(0,(E77-Annahmen!$B$138)/Annahmen!$B$139) -> 0 | X77: =W77*Annahmen!$B$137 -> 0 | Y77: =O77-P77-R77-S77-T77-U77-V77-X77 -> -2185.6155 | Z77: =Z76+Y77 -> -2764.4521 | AA77: =IF(Y77>0,1,0) -> 0 | AB77: =IF(Z77>=0,1,0) -> 0
A78: 3 | B78: 03/2027 | C78: =IF($A78<Annahmen!$D$54,0,IF($A78=Annahmen!$D$54,Annahmen!$D$55,C77*(1+Annahmen!$D$56*(1-C77/Annahmen!$D$57)))) -> 1219.56 | D78: =C78*Annahmen!$D$58 -> 18.2934 | E78: =E77*(1-Annahmen!$D$59)+D78 -> 32.6934 | F78: =E78*(1-Annahmen!$D$60) -> 16.3467 | G78: =E78*Annahmen!$D$60 -> 16.3467 | H78: =F78*Annahmen!$D$78+G78*Annahmen!$D$79 -> 209.60556 | I78: =IF($A78>=Annahmen!$D$54,Annahmen!$D$63*(1-Annahmen!$D$64),0) -> 2.5 | J78: =IF($A78>=Annahmen!$D$54,Annahmen!$D$63*Annahmen!$D$64,0) -> 2.5 | K78: =I78*Annahmen!$B$71+J78*Annahmen!$B$72 -> 337.45 | L78: =IF($A78>=Annahmen!$D$54,Annahmen!$D$65,0) -> 1 | M78: =L78*Annahmen!$B$73 -> 149 | N78: =H78+K78+M78 -> 696.05556 | O78: =N78/(1+Annahmen!$B$8) -> 584.92064 | P78: =O78*(Annahmen!$D$62*Annahmen!$B$74+(1-Annahmen!$D$62)*Annahmen!$B$75)+(E78*Annahmen!$D$61+E78*(1-Annahmen!$D$61)/12+I78+J78+L78)*(1-Annahmen!$D$62)*Annahmen!$B$76 -> 43.915863 | Q78: =Annahmen!$D$66 -> 12 | R78: =Q78*Annahmen!$B$42 -> 346.45155 | S78: =I78*Annahmen!$B$43+(J78+L78)*Annahmen!$B$44 -> 190.53823 | T78: =C78*Annahmen!$B$77 -> 12.1956 | U78: =SUMPRODUCT((((Annahmen!$C$145:$C$155="monatlich")*(Annahmen!$D$145:$D$155<=$A78))+((Annahmen!$C$145:$C$155="einmalig")*(Annahmen!$D$145:$D$155=$A78)))*Annahmen!$B$145:$B$155*Annahmen!$E$145:$E$155) -> 69.98508 | V78: =IF($A78>=Annahmen!$D$54,Annahmen!$D$134,0) -> 2000 | W78: =MAX(0,(E78-Annahmen!$B$138)/Annahmen!$B$139) -> 0 | X78: =W78*Annahmen!$B$137 -> 0 | Y78: =O78-P78-R78-S78-T78-U78-V78-X78 -> -2078.1657 | Z78: =Z77+Y78 -> -4842.6178 | AA78: =IF(Y78>0,1,0) -> 0 | AB78: =IF(Z78>=0,1,0) -> 0
A79: 4 | B79: 04/2027 | C79: =IF($A79<Annahmen!$D$54,0,IF($A79=Annahmen!$D$54,Annahmen!$D$55,C78*(1+Annahmen!$D$56*(1-C78/Annahmen!$D$57)))) -> 1487.2088 | D79: =C79*Annahmen!$D$58 -> 22.308132 | E79: =E78*(1-Annahmen!$D$59)+D79 -> 53.693796 | F79: =E79*(1-Annahmen!$D$60) -> 26.846898 | G79: =E79*Annahmen!$D$60 -> 26.846898 | H79: =F79*Annahmen!$D$78+G79*Annahmen!$D$79 -> 344.24435 | I79: =IF($A79>=Annahmen!$D$54,Annahmen!$D$63*(1-Annahmen!$D$64),0) -> 2.5 | J79: =IF($A79>=Annahmen!$D$54,Annahmen!$D$63*Annahmen!$D$64,0) -> 2.5 | K79: =I79*Annahmen!$B$71+J79*Annahmen!$B$72 -> 337.45 | L79: =IF($A79>=Annahmen!$D$54,Annahmen!$D$65,0) -> 1 | M79: =L79*Annahmen!$B$73 -> 149 | N79: =H79+K79+M79 -> 830.69435 | O79: =N79/(1+Annahmen!$B$8) -> 698.06248 | P79: =O79*(Annahmen!$D$62*Annahmen!$B$74+(1-Annahmen!$D$62)*Annahmen!$B$75)+(E79*Annahmen!$D$61+E79*(1-Annahmen!$D$61)/12+I79+J79+L79)*(1-Annahmen!$D$62)*Annahmen!$B$76 -> 53.428932 | Q79: =Annahmen!$D$66 -> 12 | R79: =Q79*Annahmen!$B$42 -> 346.45155 | S79: =I79*Annahmen!$B$43+(J79+L79)*Annahmen!$B$44 -> 190.53823 | T79: =C79*Annahmen!$B$77 -> 14.872088 | U79: =SUMPRODUCT((((Annahmen!$C$145:$C$155="monatlich")*(Annahmen!$D$145:$D$155<=$A79))+((Annahmen!$C$145:$C$155="einmalig")*(Annahmen!$D$145:$D$155=$A79)))*Annahmen!$B$145:$B$155*Annahmen!$E$145:$E$155) -> 69.98508 | V79: =IF($A79>=Annahmen!$D$54,Annahmen!$D$134,0) -> 2000 | W79: =MAX(0,(E79-Annahmen!$B$138)/Annahmen!$B$139) -> 0 | X79: =W79*Annahmen!$B$137 -> 0 | Y79: =O79-P79-R79-S79-T79-U79-V79-X79 -> -1977.2134 | Z79: =Z78+Y79 -> -6819.8312 | AA79: =IF(Y79>0,1,0) -> 0 | AB79: =IF(Z79>=0,1,0) -> 0
A80: 5 | B80: 05/2027 | C80: =IF($A80<Annahmen!$D$54,0,IF($A80=Annahmen!$D$54,Annahmen!$D$55,C79*(1+Annahmen!$D$56*(1-C79/Annahmen!$D$57)))) -> 1813.4215 | D80: =C80*Annahmen!$D$58 -> 27.201323 | E80: =E79*(1-Annahmen!$D$59)+D80 -> 78.747367 | F80: =E80*(1-Annahmen!$D$60) -> 39.373683 | G80: =E80*Annahmen!$D$60 -> 39.373683 | H80: =F80*Annahmen!$D$78+G80*Annahmen!$D$79 -> 504.86905 | I80: =IF($A80>=Annahmen!$D$54,Annahmen!$D$63*(1-Annahmen!$D$64),0) -> 2.5 | J80: =IF($A80>=Annahmen!$D$54,Annahmen!$D$63*Annahmen!$D$64,0) -> 2.5 | K80: =I80*Annahmen!$B$71+J80*Annahmen!$B$72 -> 337.45 | L80: =IF($A80>=Annahmen!$D$54,Annahmen!$D$65,0) -> 1 | M80: =L80*Annahmen!$B$73 -> 149 | N80: =H80+K80+M80 -> 991.31905 | O80: =N80/(1+Annahmen!$B$8) -> 833.04122 | P80: =O80*(Annahmen!$D$62*Annahmen!$B$74+(1-Annahmen!$D$62)*Annahmen!$B$75)+(E80*Annahmen!$D$61+E80*(1-Annahmen!$D$61)/12+I80+J80+L80)*(1-Annahmen!$D$62)*Annahmen!$B$76 -> 64.778068 | Q80: =Annahmen!$D$66 -> 12 | R80: =Q80*Annahmen!$B$42 -> 346.45155 | S80: =I80*Annahmen!$B$43+(J80+L80)*Annahmen!$B$44 -> 190.53823 | T80: =C80*Annahmen!$B$77 -> 18.134215 | U80: =SUMPRODUCT((((Annahmen!$C$145:$C$155="monatlich")*(Annahmen!$D$145:$D$155<=$A80))+((Annahmen!$C$145:$C$155="einmalig")*(Annahmen!$D$145:$D$155=$A80)))*Annahmen!$B$145:$B$155*Annahmen!$E$145:$E$155) -> 309.98508 | V80: =IF($A80>=Annahmen!$D$54,Annahmen!$D$134,0) -> 2000 | W80: =MAX(0,(E80-Annahmen!$B$138)/Annahmen!$B$139) -> 0 | X80: =W80*Annahmen!$B$137 -> 0 | Y80: =O80-P80-R80-S80-T80-U80-V80-X80 -> -2096.8459 | Z80: =Z79+Y80 -> -8916.6771 | AA80: =IF(Y80>0,1,0) -> 0 | AB80: =IF(Z80>=0,1,0) -> 0
A81: 6 | B81: 06/2027 | C81: =IF($A81<Annahmen!$D$54,0,IF($A81=Annahmen!$D$54,Annahmen!$D$55,C80*(1+Annahmen!$D$56*(1-C80/Annahmen!$D$57)))) -> 2210.9273 | D81: =C81*Annahmen!$D$58 -> 33.16391 | E81: =E80*(1-Annahmen!$D$59)+D81 -> 108.76138 | F81: =E81*(1-Annahmen!$D$60) -> 54.380691 | G81: =E81*Annahmen!$D$60 -> 54.380691 | H81: =F81*Annahmen!$D$78+G81*Annahmen!$D$79 -> 697.29641 | I81: =IF($A81>=Annahmen!$D$54,Annahmen!$D$63*(1-Annahmen!$D$64),0) -> 2.5 | J81: =IF($A81>=Annahmen!$D$54,Annahmen!$D$63*Annahmen!$D$64,0) -> 2.5 | K81: =I81*Annahmen!$B$71+J81*Annahmen!$B$72 -> 337.45 | L81: =IF($A81>=Annahmen!$D$54,Annahmen!$D$65,0) -> 1 | M81: =L81*Annahmen!$B$73 -> 149 | N81: =H81+K81+M81 -> 1183.7464 | O81: =N81/(1+Annahmen!$B$8) -> 994.74488 | P81: =O81*(Annahmen!$D$62*Annahmen!$B$74+(1-Annahmen!$D$62)*Annahmen!$B$75)+(E81*Annahmen!$D$61+E81*(1-Annahmen!$D$61)/12+I81+J81+L81)*(1-Annahmen!$D$62)*Annahmen!$B$76 -> 78.374259 | Q81: =Annahmen!$D$66 -> 12 | R81: =Q81*Annahmen!$B$42 -> 346.45155 | S81: =I81*Annahmen!$B$43+(J81+L81)*Annahmen!$B$44 -> 190.53823 | T81: =C81*Annahmen!$B$77 -> 22.109273 | U81: =SUMPRODUCT((((Annahmen!$C$145:$C$155="monatlich")*(Annahmen!$D$145:$D$155<=$A81))+((Annahmen!$C$145:$C$155="einmalig")*(Annahmen!$D$145:$D$155=$A81)))*Annahmen!$B$145:$B$155*Annahmen!$E$145:$E$155) -> 69.98508 | V81: =IF($A81>=Annahmen!$D$54,Annahmen!$D$134,0) -> 2000 | W81: =MAX(0,(E81-Annahmen!$B$138)/Annahmen!$B$139) -> 0 | X81: =W81*Annahmen!$B$137 -> 0 | Y81: =O81-P81-R81-S81-T81-U81-V81-X81 -> -1712.7135 | Z81: =Z80+Y81 -> -10629.391 | AA81: =IF(Y81>0,1,0) -> 0 | AB81: =IF(Z81>=0,1,0) -> 0
A82: 7 | B82: 07/2027 | C82: =IF($A82<Annahmen!$D$54,0,IF($A82=Annahmen!$D$54,Annahmen!$D$55,C81*(1+Annahmen!$D$56*(1-C81/Annahmen!$D$57)))) -> 2695.1805 | D82: =C82*Annahmen!$D$58 -> 40.427708 | E82: =E81*(1-Annahmen!$D$59)+D82 -> 144.83863 | F82: =E82*(1-Annahmen!$D$60) -> 72.419317 | G82: =E82*Annahmen!$D$60 -> 72.419317 | H82: =F82*Annahmen!$D$78+G82*Annahmen!$D$79 -> 928.59669 | I82: =IF($A82>=Annahmen!$D$54,Annahmen!$D$63*(1-Annahmen!$D$64),0) -> 2.5 | J82: =IF($A82>=Annahmen!$D$54,Annahmen!$D$63*Annahmen!$D$64,0) -> 2.5 | K82: =I82*Annahmen!$B$71+J82*Annahmen!$B$72 -> 337.45 | L82: =IF($A82>=Annahmen!$D$54,Annahmen!$D$65,0) -> 1 | M82: =L82*Annahmen!$B$73 -> 149 | N82: =H82+K82+M82 -> 1415.0467 | O82: =N82/(1+Annahmen!$B$8) -> 1189.1149 | P82: =O82*(Annahmen!$D$62*Annahmen!$B$74+(1-Annahmen!$D$62)*Annahmen!$B$75)+(E82*Annahmen!$D$61+E82*(1-Annahmen!$D$61)/12+I82+J82+L82)*(1-Annahmen!$D$62)*Annahmen!$B$76 -> 94.717065 | Q82: =Annahmen!$D$66 -> 12 | R82: =Q82*Annahmen!$B$42 -> 346.45155 | S82: =I82*Annahmen!$B$43+(J82+L82)*Annahmen!$B$44 -> 190.53823 | T82: =C82*Annahmen!$B$77 -> 26.951805 | U82: =SUMPRODUCT((((Annahmen!$C$145:$C$155="monatlich")*(Annahmen!$D$145:$D$155<=$A82))+((Annahmen!$C$145:$C$155="einmalig")*(Annahmen!$D$145:$D$155=$A82)))*Annahmen!$B$145:$B$155*Annahmen!$E$145:$E$155) -> 69.98508 | V82: =IF($A82>=Annahmen!$D$54,Annahmen!$D$134,0) -> 2000 | W82: =MAX(0,(E82-Annahmen!$B$138)/Annahmen!$B$139) -> 0 | X82: =W82*Annahmen!$B$137 -> 0 | Y82: =O82-P82-R82-S82-T82-U82-V82-X82 -> -1539.5289 | Z82: =Z81+Y82 -> -12168.92 | AA82: =IF(Y82>0,1,0) -> 0 | AB82: =IF(Z82>=0,1,0) -> 0
A83: 8 | B83: 08/2027 | C83: =IF($A83<Annahmen!$D$54,0,IF($A83=Annahmen!$D$54,Annahmen!$D$55,C82*(1+Annahmen!$D$56*(1-C82/Annahmen!$D$57)))) -> 3284.9241 | D83: =C83*Annahmen!$D$58 -> 49.273861 | E83: =E82*(1-Annahmen!$D$59)+D83 -> 188.31895 | F83: =E83*(1-Annahmen!$D$60) -> 94.159475 | G83: =E83*Annahmen!$D$60 -> 94.159475 | H83: =F83*Annahmen!$D$78+G83*Annahmen!$D$79 -> 1207.3599 | I83: =IF($A83>=Annahmen!$D$54,Annahmen!$D$63*(1-Annahmen!$D$64),0) -> 2.5 | J83: =IF($A83>=Annahmen!$D$54,Annahmen!$D$63*Annahmen!$D$64,0) -> 2.5 | K83: =I83*Annahmen!$B$71+J83*Annahmen!$B$72 -> 337.45 | L83: =IF($A83>=Annahmen!$D$54,Annahmen!$D$65,0) -> 1 | M83: =L83*Annahmen!$B$73 -> 149 | N83: =H83+K83+M83 -> 1693.8099 | O83: =N83/(1+Annahmen!$B$8) -> 1423.3696 | P83: =O83*(Annahmen!$D$62*Annahmen!$B$74+(1-Annahmen!$D$62)*Annahmen!$B$75)+(E83*Annahmen!$D$61+E83*(1-Annahmen!$D$61)/12+I83+J83+L83)*(1-Annahmen!$D$62)*Annahmen!$B$76 -> 114.41342 | Q83: =Annahmen!$D$66 -> 12 | R83: =Q83*Annahmen!$B$42 -> 346.45155 | S83: =I83*Annahmen!$B$43+(J83+L83)*Annahmen!$B$44 -> 190.53823 | T83: =C83*Annahmen!$B$77 -> 32.849241 | U83: =SUMPRODUCT((((Annahmen!$C$145:$C$155="monatlich")*(Annahmen!$D$145:$D$155<=$A83))+((Annahmen!$C$145:$C$155="einmalig")*(Annahmen!$D$145:$D$155=$A83)))*Annahmen!$B$145:$B$155*Annahmen!$E$145:$E$155) -> 69.98508 | V83: =IF($A83>=Annahmen!$D$54,Annahmen!$D$134,0) -> 2000 | W83: =MAX(0,(E83-Annahmen!$B$138)/Annahmen!$B$139) -> 0 | X83: =W83*Annahmen!$B$137 -> 0 | Y83: =O83-P83-R83-S83-T83-U83-V83-X83 -> -1330.8679 | Z83: =Z82+Y83 -> -13499.787 | AA83: =IF(Y83>0,1,0) -> 0 | AB83: =IF(Z83>=0,1,0) -> 0
A84: 9 | B84: 09/2027 | C84: =IF($A84<Annahmen!$D$54,0,IF($A84=Annahmen!$D$54,Annahmen!$D$55,C83*(1+Annahmen!$D$56*(1-C83/Annahmen!$D$57)))) -> 4002.8594 | D84: =C84*Annahmen!$D$58 -> 60.042892 | E84: =E83*(1-Annahmen!$D$59)+D84 -> 240.82908 | F84: =E84*(1-Annahmen!$D$60) -> 120.41454 | G84: =E84*Annahmen!$D$60 -> 120.41454 | H84: =F84*Annahmen!$D$78+G84*Annahmen!$D$79 -> 1544.0155 | I84: =IF($A84>=Annahmen!$D$54,Annahmen!$D$63*(1-Annahmen!$D$64),0) -> 2.5 | J84: =IF($A84>=Annahmen!$D$54,Annahmen!$D$63*Annahmen!$D$64,0) -> 2.5 | K84: =I84*Annahmen!$B$71+J84*Annahmen!$B$72 -> 337.45 | L84: =IF($A84>=Annahmen!$D$54,Annahmen!$D$65,0) -> 1 | M84: =L84*Annahmen!$B$73 -> 149 | N84: =H84+K84+M84 -> 2030.4655 | O84: =N84/(1+Annahmen!$B$8) -> 1706.2735 | P84: =O84*(Annahmen!$D$62*Annahmen!$B$74+(1-Annahmen!$D$62)*Annahmen!$B$75)+(E84*Annahmen!$D$61+E84*(1-Annahmen!$D$61)/12+I84+J84+L84)*(1-Annahmen!$D$62)*Annahmen!$B$76 -> 138.20023 | Q84: =Annahmen!$D$66 -> 12 | R84: =Q84*Annahmen!$B$42 -> 346.45155 | S84: =I84*Annahmen!$B$43+(J84+L84)*Annahmen!$B$44 -> 190.53823 | T84: =C84*Annahmen!$B$77 -> 40.028594 | U84: =SUMPRODUCT((((Annahmen!$C$145:$C$155="monatlich")*(Annahmen!$D$145:$D$155<=$A84))+((Annahmen!$C$145:$C$155="einmalig")*(Annahmen!$D$145:$D$155=$A84)))*Annahmen!$B$145:$B$155*Annahmen!$E$145:$E$155) -> 69.98508 | V84: =IF($A84>=Annahmen!$D$54,Annahmen!$D$134,0) -> 2000 | W84: =MAX(0,(E84-Annahmen!$B$138)/Annahmen!$B$139) -> 0 | X84: =W84*Annahmen!$B$137 -> 0 | Y84: =O84-P84-R84-S84-T84-U84-V84-X84 -> -1078.9302 | Z84: =Z83+Y84 -> -14578.718 | AA84: =IF(Y84>0,1,0) -> 0 | AB84: =IF(Z84>=0,1,0) -> 0
A85: 10 | B85: 10/2027 | C85: =IF($A85<Annahmen!$D$54,0,IF($A85=Annahmen!$D$54,Annahmen!$D$55,C84*(1+Annahmen!$D$56*(1-C84/Annahmen!$D$57)))) -> 4876.4385 | D85: =C85*Annahmen!$D$58 -> 73.146577 | E85: =E84*(1-Annahmen!$D$59)+D85 -> 304.3425 | F85: =E85*(1-Annahmen!$D$60) -> 152.17125 | G85: =E85*Annahmen!$D$60 -> 152.17125 | H85: =F85*Annahmen!$D$78+G85*Annahmen!$D$79 -> 1951.2158 | I85: =IF($A85>=Annahmen!$D$54,Annahmen!$D$63*(1-Annahmen!$D$64),0) -> 2.5 | J85: =IF($A85>=Annahmen!$D$54,Annahmen!$D$63*Annahmen!$D$64,0) -> 2.5 | K85: =I85*Annahmen!$B$71+J85*Annahmen!$B$72 -> 337.45 | L85: =IF($A85>=Annahmen!$D$54,Annahmen!$D$65,0) -> 1 | M85: =L85*Annahmen!$B$73 -> 149 | N85: =H85+K85+M85 -> 2437.6658 | O85: =N85/(1+Annahmen!$B$8) -> 2048.4587 | P85: =O85*(Annahmen!$D$62*Annahmen!$B$74+(1-Annahmen!$D$62)*Annahmen!$B$75)+(E85*Annahmen!$D$61+E85*(1-Annahmen!$D$61)/12+I85+J85+L85)*(1-Annahmen!$D$62)*Annahmen!$B$76 -> 166.97148 | Q85: =Annahmen!$D$66 -> 12 | R85: =Q85*Annahmen!$B$42 -> 346.45155 | S85: =I85*Annahmen!$B$43+(J85+L85)*Annahmen!$B$44 -> 190.53823 | T85: =C85*Annahmen!$B$77 -> 48.764385 | U85: =SUMPRODUCT((((Annahmen!$C$145:$C$155="monatlich")*(Annahmen!$D$145:$D$155<=$A85))+((Annahmen!$C$145:$C$155="einmalig")*(Annahmen!$D$145:$D$155=$A85)))*Annahmen!$B$145:$B$155*Annahmen!$E$145:$E$155) -> 69.98508 | V85: =IF($A85>=Annahmen!$D$54,Annahmen!$D$134,0) -> 2000 | W85: =MAX(0,(E85-Annahmen!$B$138)/Annahmen!$B$139) -> 0 | X85: =W85*Annahmen!$B$137 -> 0 | Y85: =O85-P85-R85-S85-T85-U85-V85-X85 -> -774.25204 | Z85: =Z84+Y85 -> -15352.97 | AA85: =IF(Y85>0,1,0) -> 0 | AB85: =IF(Z85>=0,1,0) -> 0
A86: 11 | B86: 11/2027 | C86: =IF($A86<Annahmen!$D$54,0,IF($A86=Annahmen!$D$54,Annahmen!$D$55,C85*(1+Annahmen!$D$56*(1-C85/Annahmen!$D$57)))) -> 5938.7919 | D86: =C86*Annahmen!$D$58 -> 89.081878 | E86: =E85*(1-Annahmen!$D$59)+D86 -> 381.25068 | F86: =E86*(1-Annahmen!$D$60) -> 190.62534 | G86: =E86*Annahmen!$D$60 -> 190.62534 | H86: =F86*Annahmen!$D$78+G86*Annahmen!$D$79 -> 2444.2934 | I86: =IF($A86>=Annahmen!$D$54,Annahmen!$D$63*(1-Annahmen!$D$64),0) -> 2.5 | J86: =IF($A86>=Annahmen!$D$54,Annahmen!$D$63*Annahmen!$D$64,0) -> 2.5 | K86: =I86*Annahmen!$B$71+J86*Annahmen!$B$72 -> 337.45 | L86: =IF($A86>=Annahmen!$D$54,Annahmen!$D$65,0) -> 1 | M86: =L86*Annahmen!$B$73 -> 149 | N86: =H86+K86+M86 -> 2930.7434 | O86: =N86/(1+Annahmen!$B$8) -> 2462.8096 | P86: =O86*(Annahmen!$D$62*Annahmen!$B$74+(1-Annahmen!$D$62)*Annahmen!$B$75)+(E86*Annahmen!$D$61+E86*(1-Annahmen!$D$61)/12+I86+J86+L86)*(1-Annahmen!$D$62)*Annahmen!$B$76 -> 201.81048 | Q86: =Annahmen!$D$66 -> 12 | R86: =Q86*Annahmen!$B$42 -> 346.45155 | S86: =I86*Annahmen!$B$43+(J86+L86)*Annahmen!$B$44 -> 190.53823 | T86: =C86*Annahmen!$B$77 -> 59.387919 | U86: =SUMPRODUCT((((Annahmen!$C$145:$C$155="monatlich")*(Annahmen!$D$145:$D$155<=$A86))+((Annahmen!$C$145:$C$155="einmalig")*(Annahmen!$D$145:$D$155=$A86)))*Annahmen!$B$145:$B$155*Annahmen!$E$145:$E$155) -> 69.98508 | V86: =IF($A86>=Annahmen!$D$54,Annahmen!$D$134,0) -> 2000 | W86: =MAX(0,(E86-Annahmen!$B$138)/Annahmen!$B$139) -> 0 | X86: =W86*Annahmen!$B$137 -> 0 | Y86: =O86-P86-R86-S86-T86-U86-V86-X86 -> -405.36368 | Z86: =Z85+Y86 -> -15758.333 | AA86: =IF(Y86>0,1,0) -> 0 | AB86: =IF(Z86>=0,1,0) -> 0
A87: 12 | B87: 12/2027 | C87: =IF($A87<Annahmen!$D$54,0,IF($A87=Annahmen!$D$54,Annahmen!$D$55,C86*(1+Annahmen!$D$56*(1-C86/Annahmen!$D$57)))) -> 7229.8076 | D87: =C87*Annahmen!$D$58 -> 108.44711 | E87: =E86*(1-Annahmen!$D$59)+D87 -> 474.44776 | F87: =E87*(1-Annahmen!$D$60) -> 237.22388 | G87: =E87*Annahmen!$D$60 -> 237.22388 | H87: =F87*Annahmen!$D$78+G87*Annahmen!$D$79 -> 3041.8032 | I87: =IF($A87>=Annahmen!$D$54,Annahmen!$D$63*(1-Annahmen!$D$64),0) -> 2.5 | J87: =IF($A87>=Annahmen!$D$54,Annahmen!$D$63*Annahmen!$D$64,0) -> 2.5 | K87: =I87*Annahmen!$B$71+J87*Annahmen!$B$72 -> 337.45 | L87: =IF($A87>=Annahmen!$D$54,Annahmen!$D$65,0) -> 1 | M87: =L87*Annahmen!$B$73 -> 149 | N87: =H87+K87+M87 -> 3528.2532 | O87: =N87/(1+Annahmen!$B$8) -> 2964.9187 | P87: =O87*(Annahmen!$D$62*Annahmen!$B$74+(1-Annahmen!$D$62)*Annahmen!$B$75)+(E87*Annahmen!$D$61+E87*(1-Annahmen!$D$61)/12+I87+J87+L87)*(1-Annahmen!$D$62)*Annahmen!$B$76 -> 244.02827 | Q87: =Annahmen!$D$66 -> 12 | R87: =Q87*Annahmen!$B$42 -> 346.45155 | S87: =I87*Annahmen!$B$43+(J87+L87)*Annahmen!$B$44 -> 190.53823 | T87: =C87*Annahmen!$B$77 -> 72.298076 | U87: =SUMPRODUCT((((Annahmen!$C$145:$C$155="monatlich")*(Annahmen!$D$145:$D$155<=$A87))+((Annahmen!$C$145:$C$155="einmalig")*(Annahmen!$D$145:$D$155=$A87)))*Annahmen!$B$145:$B$155*Annahmen!$E$145:$E$155) -> 69.98508 | V87: =IF($A87>=Annahmen!$D$54,Annahmen!$D$134,0) -> 2000 | W87: =MAX(0,(E87-Annahmen!$B$138)/Annahmen!$B$139) -> 0 | X87: =W87*Annahmen!$B$137 -> 0 | Y87: =O87-P87-R87-S87-T87-U87-V87-X87 -> 41.617464 | Z87: =Z86+Y87 -> -15716.716 | AA87: =IF(Y87>0,1,0) -> 1 | AB87: =IF(Z87>=0,1,0) -> 0
A88: 13 | B88: 01/2028 | C88: =IF($A88<Annahmen!$D$54,0,IF($A88=Annahmen!$D$54,Annahmen!$D$55,C87*(1+Annahmen!$D$56*(1-C87/Annahmen!$D$57)))) -> 8797.3664 | D88: =C88*Annahmen!$D$58 -> 131.9605 | E88: =E87*(1-Annahmen!$D$59)+D88 -> 587.43035 | F88: =E88*(1-Annahmen!$D$60) -> 293.71517 | G88: =E88*Annahmen!$D$60 -> 293.71517 | H88: =F88*Annahmen!$D$78+G88*Annahmen!$D$79 -> 3766.1628 | I88: =IF($A88>=Annahmen!$D$54,Annahmen!$D$63*(1-Annahmen!$D$64),0) -> 2.5 | J88: =IF($A88>=Annahmen!$D$54,Annahmen!$D$63*Annahmen!$D$64,0) -> 2.5 | K88: =I88*Annahmen!$B$71+J88*Annahmen!$B$72 -> 337.45 | L88: =IF($A88>=Annahmen!$D$54,Annahmen!$D$65,0) -> 1 | M88: =L88*Annahmen!$B$73 -> 149 | N88: =H88+K88+M88 -> 4252.6128 | O88: =N88/(1+Annahmen!$B$8) -> 3573.6242 | P88: =O88*(Annahmen!$D$62*Annahmen!$B$74+(1-Annahmen!$D$62)*Annahmen!$B$75)+(E88*Annahmen!$D$61+E88*(1-Annahmen!$D$61)/12+I88+J88+L88)*(1-Annahmen!$D$62)*Annahmen!$B$76 -> 295.20879 | Q88: =Annahmen!$D$66 -> 12 | R88: =Q88*Annahmen!$B$42 -> 346.45155 | S88: =I88*Annahmen!$B$43+(J88+L88)*Annahmen!$B$44 -> 190.53823 | T88: =C88*Annahmen!$B$77 -> 87.973664 | U88: =SUMPRODUCT((((Annahmen!$C$145:$C$155="monatlich")*(Annahmen!$D$145:$D$155<=$A88))+((Annahmen!$C$145:$C$155="einmalig")*(Annahmen!$D$145:$D$155=$A88)))*Annahmen!$B$145:$B$155*Annahmen!$E$145:$E$155) -> 69.98508 | V88: =IF($A88>=Annahmen!$D$54,Annahmen!$D$134,0) -> 2000 | W88: =MAX(0,(E88-Annahmen!$B$138)/Annahmen!$B$139) -> 0 | X88: =W88*Annahmen!$B$137 -> 0 | Y88: =O88-P88-R88-S88-T88-U88-V88-X88 -> 583.46691 | Z88: =Z87+Y88 -> -15133.249 | AA88: =IF(Y88>0,1,0) -> 1 | AB88: =IF(Z88>=0,1,0) -> 0
... A99: 24 | B99: 12/2028 | C99: =IF($A99<Annahmen!$D$54,0,IF($A99=Annahmen!$D$54,Annahmen!$D$55,C98*(1+Annahmen!$D$56*(1-C98/Annahmen!$D$57)))) -> 70272.361 | D99: =C99*Annahmen!$D$58 -> 1054.0854 | E99: =E98*(1-Annahmen!$D$59)+D99 -> 5173.6192 | F99: =E99*(1-Annahmen!$D$60) -> 2586.8096 | G99: =E99*Annahmen!$D$60 -> 2586.8096 | H99: =F99*Annahmen!$D$78+G99*Annahmen!$D$79 -> 33169.366 | I99: =IF($A99>=Annahmen!$D$54,Annahmen!$D$63*(1-Annahmen!$D$64),0) -> 2.5 | J99: =IF($A99>=Annahmen!$D$54,Annahmen!$D$63*Annahmen!$D$64,0) -> 2.5 | K99: =I99*Annahmen!$B$71+J99*Annahmen!$B$72 -> 337.45 | L99: =IF($A99>=Annahmen!$D$54,Annahmen!$D$65,0) -> 1 | M99: =L99*Annahmen!$B$73 -> 149 | N99: =H99+K99+M99 -> 33655.816 | O99: =N99/(1+Annahmen!$B$8) -> 28282.199 | P99: =O99*(Annahmen!$D$62*Annahmen!$B$74+(1-Annahmen!$D$62)*Annahmen!$B$75)+(E99*Annahmen!$D$61+E99*(1-Annahmen!$D$61)/12+I99+J99+L99)*(1-Annahmen!$D$62)*Annahmen!$B$76 -> 2372.7283 | Q99: =Annahmen!$D$66 -> 12 | R99: =Q99*Annahmen!$B$42 -> 346.45155 | S99: =I99*Annahmen!$B$43+(J99+L99)*Annahmen!$B$44 -> 190.53823 | T99: =C99*Annahmen!$B$77 -> 702.72361 | U99: =SUMPRODUCT((((Annahmen!$C$145:$C$155="monatlich")*(Annahmen!$D$145:$D$155<=$A99))+((Annahmen!$C$145:$C$155="einmalig")*(Annahmen!$D$145:$D$155=$A99)))*Annahmen!$B$145:$B$155*Annahmen!$E$145:$E$155) -> 69.98508 | V99: =IF($A99>=Annahmen!$D$54,Annahmen!$D$134,0) -> 2000 | W99: =MAX(0,(E99-Annahmen!$B$138)/Annahmen!$B$139) -> 1.3912064 | X99: =W99*Annahmen!$B$137 -> 6260.4288 | Y99: =O99-P99-R99-S99-T99-U99-V99-X99 -> 16339.343 | Z99: =Z98+Y99 -> 62024.354 | AA99: =IF(Y99>0,1,0) -> 1 | AB99: =IF(Z99>=0,1,0) -> 1

Sheet Read Layer
A1: Read Layer Verlagsdienstleistungen (B2B) — 24 Monate ab 01/2027
A3: Kennzahl | B3: ="vorsichtig – "&Annahmen!$B$133 -> vorsichtig – teures Hobby | C3: ="mittel – "&Annahmen!$C$133 -> mittel – profitabler Nebenerwerb | D3: ="stark – "&Annahmen!$D$133 -> stark – skalierbares Business
A4: Break-even monatlich (erster Monat Ergebnis > 0) | B4: =IFERROR("Monat "&MATCH(1,AC18:AC41,0)&" ("&INDEX($B$18:$B$41,MATCH(1,AC18:AC41,0))&")","nicht in 24 M") -> Monat 8 (08/2027) | C4: =IFERROR("Monat "&MATCH(1,AC47:AC70,0)&" ("&INDEX($B$47:$B$70,MATCH(1,AC47:AC70,0))&")","nicht in 24 M") -> Monat 4 (04/2027) | D4: =IFERROR("Monat "&MATCH(1,AC76:AC99,0)&" ("&INDEX($B$76:$B$99,MATCH(1,AC76:AC99,0))&")","nicht in 24 M") -> Monat 3 (03/2027)
A5: Break-even kumuliert (erster Monat kum. ≥ 0) | B5: =IFERROR("Monat "&MATCH(1,AD18:AD41,0)&" ("&INDEX($B$18:$B$41,MATCH(1,AD18:AD41,0))&")","nicht in 24 M") -> Monat 14 (02/2028) | C5: =IFERROR("Monat "&MATCH(1,AD47:AD70,0)&" ("&INDEX($B$47:$B$70,MATCH(1,AD47:AD70,0))&")","nicht in 24 M") -> Monat 4 (04/2027) | D5: =IFERROR("Monat "&MATCH(1,AD76:AD99,0)&" ("&INDEX($B$76:$B$99,MATCH(1,AD76:AD99,0))&")","nicht in 24 M") -> Monat 3 (03/2027)
A6: Deckungsbeitrag je Auftrag (Preis – Rechenkosten)
A7: Pilot (bezahlt) | B7: =Annahmen!$B$96-Annahmen!$B$51 -> 473.80631
A8: BFSG-EPUB ohne Audio | B8: =Annahmen!$B$97-Annahmen!$B$45 -> 148.72243
A9: BFSG-EPUB + Media Overlays | B9: =Annahmen!$B$97+Annahmen!$B$98-Annahmen!$B$47 -> 530.32826
A10: Alignment Verlagsaudio (ohne / mit Schnitt) | B10: =Annahmen!$B$99-Annahmen!$B$48 -> 188.55243 | C10: =Annahmen!$B$99+Annahmen!$B$102-Annahmen!$B$48 -> 317.58469
A11: Schnitt-Aufschlag je Titel (Vorschlag) | B11: =Annahmen!$B$102 -> 129.03226
A12: Vertonung je Audio-h | B12: =Annahmen!$B$103-Annahmen!$B$49 -> 87.416654
A13: Übersetzung je Normseite | B13: =Annahmen!$B$104-Annahmen!$B$50 -> 5.9798982
A14: Barter-Piloten erzeugen Kosten ohne Umsatz. B2B-Zahlung per Rechnung/SEPA – keine Zahlungsgebühren angesetzt. Preise netto zzgl. MwSt.
A16: ="Szenario vorsichtig – "&Annahmen!$B$133 -> Szenario vorsichtig – teures Hobby
A17: Monat | B17: Datum | C17: Piloten | D17: davon Barter | E17: Pilot-Umsatz | F17: Folge-aufträge | G17: Folge-Umsatz (nach Anrechnung) | H17: BFSG-EPUB Titel | I17: Umsatz BFSG/MO | J17: Alignment Titel | K17: Umsatz Alignment | L17: Vertonung Audio-h | M17: Umsatz Vertonung | N17: Übersetzung NS | O17: Umsatz Übersetzung | P17: Modernisierung NS | Q17: Umsatz Moderni-sierung | R17: Zusatz-formate | S17: Umsatz Formate | T17: Umsatz gesamt | U17: Rechen-kosten | V17: Fixkosten anteilig | W17: Marketing | X17: Titel-Äquiv. | Y17: Personal-bedarf FTE | Z17: Personal-kosten | AA17: Ergebnis | AB17: Ergebnis kumuliert | AC17: BE monatl. | AD17: BE kum.
A18: 1 | B18: 01/2027 | C18: =IF($A18>=Annahmen!$B$82,Annahmen!$B$83,0) -> 0 | D18: =C18*Annahmen!$B$84 -> 0 | E18: =(C18-D18)*Annahmen!$B$96 -> 0 | F18: =IF($A18>Annahmen!$B$86,INDEX($C$18:$C$41,$A18-Annahmen!$B$86)*Annahmen!$B$85,0) -> 0 | G18: =F18*(Annahmen!$B$87*(Annahmen!$B$97+Annahmen!$B$98)-Annahmen!$B$96*(1-Annahmen!$B$84)) -> 0 | H18: =IF($A18>=Annahmen!$B$82,Annahmen!$B$88,0) -> 0 | I18: =H18*(Annahmen!$B$97+Annahmen!$B$89*Annahmen!$B$98) -> 0 | J18: =IF($A18>=Annahmen!$B$82,Annahmen!$B$90,0) -> 0 | K18: =J18*(Annahmen!$B$99+Annahmen!$B$91*Annahmen!$B$102) -> 0 | L18: =IF($A18>=Annahmen!$B$82,Annahmen!$B$92,0) -> 0 | M18: =L18*Annahmen!$B$103 -> 0 | N18: =IF($A18>=Annahmen!$B$82,Annahmen!$B$93,0) -> 0 | O18: =N18*Annahmen!$B$104 -> 0 | P18: =IF($A18>=Annahmen!$B$82,Annahmen!$B$94,0) -> 0 | Q18: =P18*Annahmen!$B$105 -> 0 | R18: =IF($A18>=Annahmen!$B$82,Annahmen!$B$95,0) -> 0 | S18: =R18*Annahmen!$B$106 -> 0 | T18: =E18+G18+I18+K18+M18+O18+Q18+S18 -> 0 | U18: =C18*Annahmen!$B$51+F18*Annahmen!$B$87*Annahmen!$B$47+H18*(Annahmen!$B$45+Annahmen!$B$89*(Annahmen!$B$47-Annahmen!$B$45))+J18*Annahmen!$B$48+L18*Annahmen!$B$49+(N18+P18)*Annahmen!$B$50 -> 0 | V18: =SUMPRODUCT((((Annahmen!$C$145:$C$155="monatlich")*(Annahmen!$D$145:$D$155<=$A18))+((Annahmen!$C$145:$C$155="einmalig")*(Annahmen!$D$145:$D$155=$A18)))*Annahmen!$B$145:$B$155*Annahmen!$F$145:$F$155) -> 213.22757 | W18: =Annahmen!$B$135 -> 50 | X18: =C18+F18*Annahmen!$B$87+H18+J18+L18/Annahmen!$B$46+(N18+P18)/(Annahmen!$B$23/Annahmen!$B$24) -> 0 | Y18: =MAX(0,(X18-Annahmen!$B$140)/Annahmen!$B$141) -> 0 | Z18: =Y18*Annahmen!$B$137 -> 0 | AA18: =T18-U18-V18-W18-Z18 -> -263.22757 | AB18: =AA18 -> -263.22757 | AC18: =IF(AA18>0,1,0) -> 0 | AD18: =IF(AB18>=0,1,0) -> 0
A19: 2 | B19: 02/2027 | C19: =IF($A19>=Annahmen!$B$82,Annahmen!$B$83,0) -> 0 | D19: =C19*Annahmen!$B$84 -> 0 | E19: =(C19-D19)*Annahmen!$B$96 -> 0 | F19: =IF($A19>Annahmen!$B$86,INDEX($C$18:$C$41,$A19-Annahmen!$B$86)*Annahmen!$B$85,0) -> 0 | G19: =F19*(Annahmen!$B$87*(Annahmen!$B$97+Annahmen!$B$98)-Annahmen!$B$96*(1-Annahmen!$B$84)) -> 0 | H19: =IF($A19>=Annahmen!$B$82,Annahmen!$B$88,0) -> 0 | I19: =H19*(Annahmen!$B$97+Annahmen!$B$89*Annahmen!$B$98) -> 0 | J19: =IF($A19>=Annahmen!$B$82,Annahmen!$B$90,0) -> 0 | K19: =J19*(Annahmen!$B$99+Annahmen!$B$91*Annahmen!$B$102) -> 0 | L19: =IF($A19>=Annahmen!$B$82,Annahmen!$B$92,0) -> 0 | M19: =L19*Annahmen!$B$103 -> 0 | N19: =IF($A19>=Annahmen!$B$82,Annahmen!$B$93,0) -> 0 | O19: =N19*Annahmen!$B$104 -> 0 | P19: =IF($A19>=Annahmen!$B$82,Annahmen!$B$94,0) -> 0 | Q19: =P19*Annahmen!$B$105 -> 0 | R19: =IF($A19>=Annahmen!$B$82,Annahmen!$B$95,0) -> 0 | S19: =R19*Annahmen!$B$106 -> 0 | T19: =E19+G19+I19+K19+M19+O19+Q19+S19 -> 0 | U19: =C19*Annahmen!$B$51+F19*Annahmen!$B$87*Annahmen!$B$47+H19*(Annahmen!$B$45+Annahmen!$B$89*(Annahmen!$B$47-Annahmen!$B$45))+J19*Annahmen!$B$48+L19*Annahmen!$B$49+(N19+P19)*Annahmen!$B$50 -> 0 | V19: =SUMPRODUCT((((Annahmen!$C$145:$C$155="monatlich")*(Annahmen!$D$145:$D$155<=$A19))+((Annahmen!$C$145:$C$155="einmalig")*(Annahmen!$D$145:$D$155=$A19)))*Annahmen!$B$145:$B$155*Annahmen!$F$145:$F$155) -> 50.827571 | W19: =Annahmen!$B$135 -> 50 | X19: =C19+F19*Annahmen!$B$87+H19+J19+L19/Annahmen!$B$46+(N19+P19)/(Annahmen!$B$23/Annahmen!$B$24) -> 0 | Y19: =MAX(0,(X19-Annahmen!$B$140)/Annahmen!$B$141) -> 0 | Z19: =Y19*Annahmen!$B$137 -> 0 | AA19: =T19-U19-V19-W19-Z19 -> -100.82757 | AB19: =AB18+AA19 -> -364.05514 | AC19: =IF(AA19>0,1,0) -> 0 | AD19: =IF(AB19>=0,1,0) -> 0
A20: 3 | B20: 03/2027 | C20: =IF($A20>=Annahmen!$B$82,Annahmen!$B$83,0) -> 0 | D20: =C20*Annahmen!$B$84 -> 0 | E20: =(C20-D20)*Annahmen!$B$96 -> 0 | F20: =IF($A20>Annahmen!$B$86,INDEX($C$18:$C$41,$A20-Annahmen!$B$86)*Annahmen!$B$85,0) -> 0 | G20: =F20*(Annahmen!$B$87*(Annahmen!$B$97+Annahmen!$B$98)-Annahmen!$B$96*(1-Annahmen!$B$84)) -> 0 | H20: =IF($A20>=Annahmen!$B$82,Annahmen!$B$88,0) -> 0 | I20: =H20*(Annahmen!$B$97+Annahmen!$B$89*Annahmen!$B$98) -> 0 | J20: =IF($A20>=Annahmen!$B$82,Annahmen!$B$90,0) -> 0 | K20: =J20*(Annahmen!$B$99+Annahmen!$B$91*Annahmen!$B$102) -> 0 | L20: =IF($A20>=Annahmen!$B$82,Annahmen!$B$92,0) -> 0 | M20: =L20*Annahmen!$B$103 -> 0 | N20: =IF($A20>=Annahmen!$B$82,Annahmen!$B$93,0) -> 0 | O20: =N20*Annahmen!$B$104 -> 0 | P20: =IF($A20>=Annahmen!$B$82,Annahmen!$B$94,0) -> 0 | Q20: =P20*Annahmen!$B$105 -> 0 | R20: =IF($A20>=Annahmen!$B$82,Annahmen!$B$95,0) -> 0 | S20: =R20*Annahmen!$B$106 -> 0 | T20: =E20+G20+I20+K20+M20+O20+Q20+S20 -> 0 | U20: =C20*Annahmen!$B$51+F20*Annahmen!$B$87*Annahmen!$B$47+H20*(Annahmen!$B$45+Annahmen!$B$89*(Annahmen!$B$47-Annahmen!$B$45))+J20*Annahmen!$B$48+L20*Annahmen!$B$49+(N20+P20)*Annahmen!$B$50 -> 0 | V20: =SUMPRODUCT((((Annahmen!$C$145:$C$155="monatlich")*(Annahmen!$D$145:$D$155<=$A20))+((Annahmen!$C$145:$C$155="einmalig")*(Annahmen!$D$145:$D$155=$A20)))*Annahmen!$B$145:$B$155*Annahmen!$F$145:$F$155) -> 330.82757 | W20: =Annahmen!$B$135 -> 50 | X20: =C20+F20*Annahmen!$B$87+H20+J20+L20/Annahmen!$B$46+(N20+P20)/(Annahmen!$B$23/Annahmen!$B$24) -> 0 | Y20: =MAX(0,(X20-Annahmen!$B$140)/Annahmen!$B$141) -> 0 | Z20: =Y20*Annahmen!$B$137 -> 0 | AA20: =T20-U20-V20-W20-Z20 -> -380.82757 | AB20: =AB19+AA20 -> -744.88271 | AC20: =IF(AA20>0,1,0) -> 0 | AD20: =IF(AB20>=0,1,0) -> 0
A21: 4 | B21: 04/2027 | C21: =IF($A21>=Annahmen!$B$82,Annahmen!$B$83,0) -> 0 | D21: =C21*Annahmen!$B$84 -> 0 | E21: =(C21-D21)*Annahmen!$B$96 -> 0 | F21: =IF($A21>Annahmen!$B$86,INDEX($C$18:$C$41,$A21-Annahmen!$B$86)*Annahmen!$B$85,0) -> 0 | G21: =F21*(Annahmen!$B$87*(Annahmen!$B$97+Annahmen!$B$98)-Annahmen!$B$96*(1-Annahmen!$B$84)) -> 0 | H21: =IF($A21>=Annahmen!$B$82,Annahmen!$B$88,0) -> 0 | I21: =H21*(Annahmen!$B$97+Annahmen!$B$89*Annahmen!$B$98) -> 0 | J21: =IF($A21>=Annahmen!$B$82,Annahmen!$B$90,0) -> 0 | K21: =J21*(Annahmen!$B$99+Annahmen!$B$91*Annahmen!$B$102) -> 0 | L21: =IF($A21>=Annahmen!$B$82,Annahmen!$B$92,0) -> 0 | M21: =L21*Annahmen!$B$103 -> 0 | N21: =IF($A21>=Annahmen!$B$82,Annahmen!$B$93,0) -> 0 | O21: =N21*Annahmen!$B$104 -> 0 | P21: =IF($A21>=Annahmen!$B$82,Annahmen!$B$94,0) -> 0 | Q21: =P21*Annahmen!$B$105 -> 0 | R21: =IF($A21>=Annahmen!$B$82,Annahmen!$B$95,0) -> 0 | S21: =R21*Annahmen!$B$106 -> 0 | T21: =E21+G21+I21+K21+M21+O21+Q21+S21 -> 0 | U21: =C21*Annahmen!$B$51+F21*Annahmen!$B$87*Annahmen!$B$47+H21*(Annahmen!$B$45+Annahmen!$B$89*(Annahmen!$B$47-Annahmen!$B$45))+J21*Annahmen!$B$48+L21*Annahmen!$B$49+(N21+P21)*Annahmen!$B$50 -> 0 | V21: =SUMPRODUCT((((Annahmen!$C$145:$C$155="monatlich")*(Annahmen!$D$145:$D$155<=$A21))+((Annahmen!$C$145:$C$155="einmalig")*(Annahmen!$D$145:$D$155=$A21)))*Annahmen!$B$145:$B$155*Annahmen!$F$145:$F$155) -> 50.827571 | W21: =Annahmen!$B$135 -> 50 | X21: =C21+F21*Annahmen!$B$87+H21+J21+L21/Annahmen!$B$46+(N21+P21)/(Annahmen!$B$23/Annahmen!$B$24) -> 0 | Y21: =MAX(0,(X21-Annahmen!$B$140)/Annahmen!$B$141) -> 0 | Z21: =Y21*Annahmen!$B$137 -> 0 | AA21: =T21-U21-V21-W21-Z21 -> -100.82757 | AB21: =AB20+AA21 -> -845.71028 | AC21: =IF(AA21>0,1,0) -> 0 | AD21: =IF(AB21>=0,1,0) -> 0
A22: 5 | B22: 05/2027 | C22: =IF($A22>=Annahmen!$B$82,Annahmen!$B$83,0) -> 0.3 | D22: =C22*Annahmen!$B$84 -> 0.09 | E22: =(C22-D22)*Annahmen!$B$96 -> 102.9 | F22: =IF($A22>Annahmen!$B$86,INDEX($C$18:$C$41,$A22-Annahmen!$B$86)*Annahmen!$B$85,0) -> 0 | G22: =F22*(Annahmen!$B$87*(Annahmen!$B$97+Annahmen!$B$98)-Annahmen!$B$96*(1-Annahmen!$B$84)) -> 0 | H22: =IF($A22>=Annahmen!$B$82,Annahmen!$B$88,0) -> 0 | I22: =H22*(Annahmen!$B$97+Annahmen!$B$89*Annahmen!$B$98) -> 0 | J22: =IF($A22>=Annahmen!$B$82,Annahmen!$B$90,0) -> 0 | K22: =J22*(Annahmen!$B$99+Annahmen!$B$91*Annahmen!$B$102) -> 0 | L22: =IF($A22>=Annahmen!$B$82,Annahmen!$B$92,0) -> 0 | M22: =L22*Annahmen!$B$103 -> 0 | N22: =IF($A22>=Annahmen!$B$82,Annahmen!$B$93,0) -> 0 | O22: =N22*Annahmen!$B$104 -> 0 | P22: =IF($A22>=Annahmen!$B$82,Annahmen!$B$94,0) -> 0 | Q22: =P22*Annahmen!$B$105 -> 0 | R22: =IF($A22>=Annahmen!$B$82,Annahmen!$B$95,0) -> 0 | S22: =R22*Annahmen!$B$106 -> 0 | T22: =E22+G22+I22+K22+M22+O22+Q22+S22 -> 102.9 | U22: =C22*Annahmen!$B$51+F22*Annahmen!$B$87*Annahmen!$B$47+H22*(Annahmen!$B$45+Annahmen!$B$89*(Annahmen!$B$47-Annahmen!$B$45))+J22*Annahmen!$B$48+L22*Annahmen!$B$49+(N22+P22)*Annahmen!$B$50 -> 4.8581085 | V22: =SUMPRODUCT((((Annahmen!$C$145:$C$155="monatlich")*(Annahmen!$D$145:$D$155<=$A22))+((Annahmen!$C$145:$C$155="einmalig")*(Annahmen!$D$145:$D$155=$A22)))*Annahmen!$B$145:$B$155*Annahmen!$F$145:$F$155) -> 610.82757 | W22: =Annahmen!$B$135 -> 50 | X22: =C22+F22*Annahmen!$B$87+H22+J22+L22/Annahmen!$B$46+(N22+P22)/(Annahmen!$B$23/Annahmen!$B$24) -> 0.3 | Y22: =MAX(0,(X22-Annahmen!$B$140)/Annahmen!$B$141) -> 0 | Z22: =Y22*Annahmen!$B$137 -> 0 | AA22: =T22-U22-V22-W22-Z22 -> -562.78568 | AB22: =AB21+AA22 -> -1408.496 | AC22: =IF(AA22>0,1,0) -> 0 | AD22: =IF(AB22>=0,1,0) -> 0
A23: 6 | B23: 06/2027 | C23: =IF($A23>=Annahmen!$B$82,Annahmen!$B$83,0) -> 0.3 | D23: =C23*Annahmen!$B$84 -> 0.09 | E23: =(C23-D23)*Annahmen!$B$96 -> 102.9 | F23: =IF($A23>Annahmen!$B$86,INDEX($C$18:$C$41,$A23-Annahmen!$B$86)*Annahmen!$B$85,0) -> 0 | G23: =F23*(Annahmen!$B$87*(Annahmen!$B$97+Annahmen!$B$98)-Annahmen!$B$96*(1-Annahmen!$B$84)) -> 0 | H23: =IF($A23>=Annahmen!$B$82,Annahmen!$B$88,0) -> 0 | I23: =H23*(Annahmen!$B$97+Annahmen!$B$89*Annahmen!$B$98) -> 0 | J23: =IF($A23>=Annahmen!$B$82,Annahmen!$B$90,0) -> 0 | K23: =J23*(Annahmen!$B$99+Annahmen!$B$91*Annahmen!$B$102) -> 0 | L23: =IF($A23>=Annahmen!$B$82,Annahmen!$B$92,0) -> 0 | M23: =L23*Annahmen!$B$103 -> 0 | N23: =IF($A23>=Annahmen!$B$82,Annahmen!$B$93,0) -> 0 | O23: =N23*Annahmen!$B$104 -> 0 | P23: =IF($A23>=Annahmen!$B$82,Annahmen!$B$94,0) -> 0 | Q23: =P23*Annahmen!$B$105 -> 0 | R23: =IF($A23>=Annahmen!$B$82,Annahmen!$B$95,0) -> 0 | S23: =R23*Annahmen!$B$106 -> 0 | T23: =E23+G23+I23+K23+M23+O23+Q23+S23 -> 102.9 | U23: =C23*Annahmen!$B$51+F23*Annahmen!$B$87*Annahmen!$B$47+H23*(Annahmen!$B$45+Annahmen!$B$89*(Annahmen!$B$47-Annahmen!$B$45))+J23*Annahmen!$B$48+L23*Annahmen!$B$49+(N23+P23)*Annahmen!$B$50 -> 4.8581085 | V23: =SUMPRODUCT((((Annahmen!$C$145:$C$155="monatlich")*(Annahmen!$D$145:$D$155<=$A23))+((Annahmen!$C$145:$C$155="einmalig")*(Annahmen!$D$145:$D$155=$A23)))*Annahmen!$B$145:$B$155*Annahmen!$F$145:$F$155) -> 50.827571 | W23: =Annahmen!$B$135 -> 50 | X23: =C23+F23*Annahmen!$B$87+H23+J23+L23/Annahmen!$B$46+(N23+P23)/(Annahmen!$B$23/Annahmen!$B$24) -> 0.3 | Y23: =MAX(0,(X23-Annahmen!$B$140)/Annahmen!$B$141) -> 0 | Z23: =Y23*Annahmen!$B$137 -> 0 | AA23: =T23-U23-V23-W23-Z23 -> -2.7856793 | AB23: =AB22+AA23 -> -1411.2816 | AC23: =IF(AA23>0,1,0) -> 0 | AD23: =IF(AB23>=0,1,0) -> 0
A24: 7 | B24: 07/2027 | C24: =IF($A24>=Annahmen!$B$82,Annahmen!$B$83,0) -> 0.3 | D24: =C24*Annahmen!$B$84 -> 0.09 | E24: =(C24-D24)*Annahmen!$B$96 -> 102.9 | F24: =IF($A24>Annahmen!$B$86,INDEX($C$18:$C$41,$A24-Annahmen!$B$86)*Annahmen!$B$85,0) -> 0 | G24: =F24*(Annahmen!$B$87*(Annahmen!$B$97+Annahmen!$B$98)-Annahmen!$B$96*(1-Annahmen!$B$84)) -> 0 | H24: =IF($A24>=Annahmen!$B$82,Annahmen!$B$88,0) -> 0 | I24: =H24*(Annahmen!$B$97+Annahmen!$B$89*Annahmen!$B$98) -> 0 | J24: =IF($A24>=Annahmen!$B$82,Annahmen!$B$90,0) -> 0 | K24: =J24*(Annahmen!$B$99+Annahmen!$B$91*Annahmen!$B$102) -> 0 | L24: =IF($A24>=Annahmen!$B$82,Annahmen!$B$92,0) -> 0 | M24: =L24*Annahmen!$B$103 -> 0 | N24: =IF($A24>=Annahmen!$B$82,Annahmen!$B$93,0) -> 0 | O24: =N24*Annahmen!$B$104 -> 0 | P24: =IF($A24>=Annahmen!$B$82,Annahmen!$B$94,0) -> 0 | Q24: =P24*Annahmen!$B$105 -> 0 | R24: =IF($A24>=Annahmen!$B$82,Annahmen!$B$95,0) -> 0 | S24: =R24*Annahmen!$B$106 -> 0 | T24: =E24+G24+I24+K24+M24+O24+Q24+S24 -> 102.9 | U24: =C24*Annahmen!$B$51+F24*Annahmen!$B$87*Annahmen!$B$47+H24*(Annahmen!$B$45+Annahmen!$B$89*(Annahmen!$B$47-Annahmen!$B$45))+J24*Annahmen!$B$48+L24*Annahmen!$B$49+(N24+P24)*Annahmen!$B$50 -> 4.8581085 | V24: =SUMPRODUCT((((Annahmen!$C$145:$C$155="monatlich")*(Annahmen!$D$145:$D$155<=$A24))+((Annahmen!$C$145:$C$155="einmalig")*(Annahmen!$D$145:$D$155=$A24)))*Annahmen!$B$145:$B$155*Annahmen!$F$145:$F$155) -> 50.827571 | W24: =Annahmen!$B$135 -> 50 | X24: =C24+F24*Annahmen!$B$87+H24+J24+L24/Annahmen!$B$46+(N24+P24)/(Annahmen!$B$23/Annahmen!$B$24) -> 0.3 | Y24: =MAX(0,(X24-Annahmen!$B$140)/Annahmen!$B$141) -> 0 | Z24: =Y24*Annahmen!$B$137 -> 0 | AA24: =T24-U24-V24-W24-Z24 -> -2.7856793 | AB24: =AB23+AA24 -> -1414.0673 | AC24: =IF(AA24>0,1,0) -> 0 | AD24: =IF(AB24>=0,1,0) -> 0
A25: 8 | B25: 08/2027 | C25: =IF($A25>=Annahmen!$B$82,Annahmen!$B$83,0) -> 0.3 | D25: =C25*Annahmen!$B$84 -> 0.09 | E25: =(C25-D25)*Annahmen!$B$96 -> 102.9 | F25: =IF($A25>Annahmen!$B$86,INDEX($C$18:$C$41,$A25-Annahmen!$B$86)*Annahmen!$B$85,0) -> 0.09 | G25: =F25*(Annahmen!$B$87*(Annahmen!$B$97+Annahmen!$B$98)-Annahmen!$B$96*(1-Annahmen!$B$84)) -> 211.68 | H25: =IF($A25>=Annahmen!$B$82,Annahmen!$B$88,0) -> 0 | I25: =H25*(Annahmen!$B$97+Annahmen!$B$89*Annahmen!$B$98) -> 0 | J25: =IF($A25>=Annahmen!$B$82,Annahmen!$B$90,0) -> 0 | K25: =J25*(Annahmen!$B$99+Annahmen!$B$91*Annahmen!$B$102) -> 0 | L25: =IF($A25>=Annahmen!$B$82,Annahmen!$B$92,0) -> 0 | M25: =L25*Annahmen!$B$103 -> 0 | N25: =IF($A25>=Annahmen!$B$82,Annahmen!$B$93,0) -> 0 | O25: =N25*Annahmen!$B$104 -> 0 | P25: =IF($A25>=Annahmen!$B$82,Annahmen!$B$94,0) -> 0 | Q25: =P25*Annahmen!$B$105 -> 0 | R25: =IF($A25>=Annahmen!$B$82,Annahmen!$B$95,0) -> 0 | S25: =R25*Annahmen!$B$106 -> 0 | T25: =E25+G25+I25+K25+M25+O25+Q25+S25 -> 314.58 | U25: =C25*Annahmen!$B$51+F25*Annahmen!$B$87*Annahmen!$B$47+H25*(Annahmen!$B$45+Annahmen!$B$89*(Annahmen!$B$47-Annahmen!$B$45))+J25*Annahmen!$B$48+L25*Annahmen!$B$49+(N25+P25)*Annahmen!$B$50 -> 8.7603929 | V25: =SUMPRODUCT((((Annahmen!$C$145:$C$155="monatlich")*(Annahmen!$D$145:$D$155<=$A25))+((Annahmen!$C$145:$C$155="einmalig")*(Annahmen!$D$145:$D$155=$A25)))*Annahmen!$B$145:$B$155*Annahmen!$F$145:$F$155) -> 50.827571 | W25: =Annahmen!$B$135 -> 50 | X25: =C25+F25*Annahmen!$B$87+H25+J25+L25/Annahmen!$B$46+(N25+P25)/(Annahmen!$B$23/Annahmen!$B$24) -> 0.75 | Y25: =MAX(0,(X25-Annahmen!$B$140)/Annahmen!$B$141) -> 0 | Z25: =Y25*Annahmen!$B$137 -> 0 | AA25: =T25-U25-V25-W25-Z25 -> 204.99204 | AB25: =AB24+AA25 -> -1209.0753 | AC25: =IF(AA25>0,1,0) -> 1 | AD25: =IF(AB25>=0,1,0) -> 0
A26: 9 | B26: 09/2027 | C26: =IF($A26>=Annahmen!$B$82,Annahmen!$B$83,0) -> 0.3 | D26: =C26*Annahmen!$B$84 -> 0.09 | E26: =(C26-D26)*Annahmen!$B$96 -> 102.9 | F26: =IF($A26>Annahmen!$B$86,INDEX($C$18:$C$41,$A26-Annahmen!$B$86)*Annahmen!$B$85,0) -> 0.09 | G26: =F26*(Annahmen!$B$87*(Annahmen!$B$97+Annahmen!$B$98)-Annahmen!$B$96*(1-Annahmen!$B$84)) -> 211.68 | H26: =IF($A26>=Annahmen!$B$82,Annahmen!$B$88,0) -> 0 | I26: =H26*(Annahmen!$B$97+Annahmen!$B$89*Annahmen!$B$98) -> 0 | J26: =IF($A26>=Annahmen!$B$82,Annahmen!$B$90,0) -> 0 | K26: =J26*(Annahmen!$B$99+Annahmen!$B$91*Annahmen!$B$102) -> 0 | L26: =IF($A26>=Annahmen!$B$82,Annahmen!$B$92,0) -> 0 | M26: =L26*Annahmen!$B$103 -> 0 | N26: =IF($A26>=Annahmen!$B$82,Annahmen!$B$93,0) -> 0 | O26: =N26*Annahmen!$B$104 -> 0 | P26: =IF($A26>=Annahmen!$B$82,Annahmen!$B$94,0) -> 0 | Q26: =P26*Annahmen!$B$105 -> 0 | R26: =IF($A26>=Annahmen!$B$82,Annahmen!$B$95,0) -> 0 | S26: =R26*Annahmen!$B$106 -> 0 | T26: =E26+G26+I26+K26+M26+O26+Q26+S26 -> 314.58 | U26: =C26*Annahmen!$B$51+F26*Annahmen!$B$87*Annahmen!$B$47+H26*(Annahmen!$B$45+Annahmen!$B$89*(Annahmen!$B$47-Annahmen!$B$45))+J26*Annahmen!$B$48+L26*Annahmen!$B$49+(N26+P26)*Annahmen!$B$50 -> 8.7603929 | V26: =SUMPRODUCT((((Annahmen!$C$145:$C$155="monatlich")*(Annahmen!$D$145:$D$155<=$A26))+((Annahmen!$C$145:$C$155="einmalig")*(Annahmen!$D$145:$D$155=$A26)))*Annahmen!$B$145:$B$155*Annahmen!$F$145:$F$155) -> 50.827571 | W26: =Annahmen!$B$135 -> 50 | X26: =C26+F26*Annahmen!$B$87+H26+J26+L26/Annahmen!$B$46+(N26+P26)/(Annahmen!$B$23/Annahmen!$B$24) -> 0.75 | Y26: =MAX(0,(X26-Annahmen!$B$140)/Annahmen!$B$141) -> 0 | Z26: =Y26*Annahmen!$B$137 -> 0 | AA26: =T26-U26-V26-W26-Z26 -> 204.99204 | AB26: =AB25+AA26 -> -1004.0832 | AC26: =IF(AA26>0,1,0) -> 1 | AD26: =IF(AB26>=0,1,0) -> 0
A27: 10 | B27: 10/2027 | C27: =IF($A27>=Annahmen!$B$82,Annahmen!$B$83,0) -> 0.3 | D27: =C27*Annahmen!$B$84 -> 0.09 | E27: =(C27-D27)*Annahmen!$B$96 -> 102.9 | F27: =IF($A27>Annahmen!$B$86,INDEX($C$18:$C$41,$A27-Annahmen!$B$86)*Annahmen!$B$85,0) -> 0.09 | G27: =F27*(Annahmen!$B$87*(Annahmen!$B$97+Annahmen!$B$98)-Annahmen!$B$96*(1-Annahmen!$B$84)) -> 211.68 | H27: =IF($A27>=Annahmen!$B$82,Annahmen!$B$88,0) -> 0 | I27: =H27*(Annahmen!$B$97+Annahmen!$B$89*Annahmen!$B$98) -> 0 | J27: =IF($A27>=Annahmen!$B$82,Annahmen!$B$90,0) -> 0 | K27: =J27*(Annahmen!$B$99+Annahmen!$B$91*Annahmen!$B$102) -> 0 | L27: =IF($A27>=Annahmen!$B$82,Annahmen!$B$92,0) -> 0 | M27: =L27*Annahmen!$B$103 -> 0 | N27: =IF($A27>=Annahmen!$B$82,Annahmen!$B$93,0) -> 0 | O27: =N27*Annahmen!$B$104 -> 0 | P27: =IF($A27>=Annahmen!$B$82,Annahmen!$B$94,0) -> 0 | Q27: =P27*Annahmen!$B$105 -> 0 | R27: =IF($A27>=Annahmen!$B$82,Annahmen!$B$95,0) -> 0 | S27: =R27*Annahmen!$B$106 -> 0 | T27: =E27+G27+I27+K27+M27+O27+Q27+S27 -> 314.58 | U27: =C27*Annahmen!$B$51+F27*Annahmen!$B$87*Annahmen!$B$47+H27*(Annahmen!$B$45+Annahmen!$B$89*(Annahmen!$B$47-Annahmen!$B$45))+J27*Annahmen!$B$48+L27*Annahmen!$B$49+(N27+P27)*Annahmen!$B$50 -> 8.7603929 | V27: =SUMPRODUCT((((Annahmen!$C$145:$C$155="monatlich")*(Annahmen!$D$145:$D$155<=$A27))+((Annahmen!$C$145:$C$155="einmalig")*(Annahmen!$D$145:$D$155=$A27)))*Annahmen!$B$145:$B$155*Annahmen!$F$145:$F$155) -> 50.827571 | W27: =Annahmen!$B$135 -> 50 | X27: =C27+F27*Annahmen!$B$87+H27+J27+L27/Annahmen!$B$46+(N27+P27)/(Annahmen!$B$23/Annahmen!$B$24) -> 0.75 | Y27: =MAX(0,(X27-Annahmen!$B$140)/Annahmen!$B$141) -> 0 | Z27: =Y27*Annahmen!$B$137 -> 0 | AA27: =T27-U27-V27-W27-Z27 -> 204.99204 | AB27: =AB26+AA27 -> -799.09121 | AC27: =IF(AA27>0,1,0) -> 1 | AD27: =IF(AB27>=0,1,0) -> 0
A28: 11 | B28: 11/2027 | C28: =IF($A28>=Annahmen!$B$82,Annahmen!$B$83,0) -> 0.3 | D28: =C28*Annahmen!$B$84 -> 0.09 | E28: =(C28-D28)*Annahmen!$B$96 -> 102.9 | F28: =IF($A28>Annahmen!$B$86,INDEX($C$18:$C$41,$A28-Annahmen!$B$86)*Annahmen!$B$85,0) -> 0.09 | G28: =F28*(Annahmen!$B$87*(Annahmen!$B$97+Annahmen!$B$98)-Annahmen!$B$96*(1-Annahmen!$B$84)) -> 211.68 | H28: =IF($A28>=Annahmen!$B$82,Annahmen!$B$88,0) -> 0 | I28: =H28*(Annahmen!$B$97+Annahmen!$B$89*Annahmen!$B$98) -> 0 | J28: =IF($A28>=Annahmen!$B$82,Annahmen!$B$90,0) -> 0 | K28: =J28*(Annahmen!$B$99+Annahmen!$B$91*Annahmen!$B$102) -> 0 | L28: =IF($A28>=Annahmen!$B$82,Annahmen!$B$92,0) -> 0 | M28: =L28*Annahmen!$B$103 -> 0 | N28: =IF($A28>=Annahmen!$B$82,Annahmen!$B$93,0) -> 0 | O28: =N28*Annahmen!$B$104 -> 0 | P28: =IF($A28>=Annahmen!$B$82,Annahmen!$B$94,0) -> 0 | Q28: =P28*Annahmen!$B$105 -> 0 | R28: =IF($A28>=Annahmen!$B$82,Annahmen!$B$95,0) -> 0 | S28: =R28*Annahmen!$B$106 -> 0 | T28: =E28+G28+I28+K28+M28+O28+Q28+S28 -> 314.58 | U28: =C28*Annahmen!$B$51+F28*Annahmen!$B$87*Annahmen!$B$47+H28*(Annahmen!$B$45+Annahmen!$B$89*(Annahmen!$B$47-Annahmen!$B$45))+J28*Annahmen!$B$48+L28*Annahmen!$B$49+(N28+P28)*Annahmen!$B$50 -> 8.7603929 | V28: =SUMPRODUCT((((Annahmen!$C$145:$C$155="monatlich")*(Annahmen!$D$145:$D$155<=$A28))+((Annahmen!$C$145:$C$155="einmalig")*(Annahmen!$D$145:$D$155=$A28)))*Annahmen!$B$145:$B$155*Annahmen!$F$145:$F$155) -> 50.827571 | W28: =Annahmen!$B$135 -> 50 | X28: =C28+F28*Annahmen!$B$87+H28+J28+L28/Annahmen!$B$46+(N28+P28)/(Annahmen!$B$23/Annahmen!$B$24) -> 0.75 | Y28: =MAX(0,(X28-Annahmen!$B$140)/Annahmen!$B$141) -> 0 | Z28: =Y28*Annahmen!$B$137 -> 0 | AA28: =T28-U28-V28-W28-Z28 -> 204.99204 | AB28: =AB27+AA28 -> -594.09918 | AC28: =IF(AA28>0,1,0) -> 1 | AD28: =IF(AB28>=0,1,0) -> 0
A29: 12 | B29: 12/2027 | C29: =IF($A29>=Annahmen!$B$82,Annahmen!$B$83,0) -> 0.3 | D29: =C29*Annahmen!$B$84 -> 0.09 | E29: =(C29-D29)*Annahmen!$B$96 -> 102.9 | F29: =IF($A29>Annahmen!$B$86,INDEX($C$18:$C$41,$A29-Annahmen!$B$86)*Annahmen!$B$85,0) -> 0.09 | G29: =F29*(Annahmen!$B$87*(Annahmen!$B$97+Annahmen!$B$98)-Annahmen!$B$96*(1-Annahmen!$B$84)) -> 211.68 | H29: =IF($A29>=Annahmen!$B$82,Annahmen!$B$88,0) -> 0 | I29: =H29*(Annahmen!$B$97+Annahmen!$B$89*Annahmen!$B$98) -> 0 | J29: =IF($A29>=Annahmen!$B$82,Annahmen!$B$90,0) -> 0 | K29: =J29*(Annahmen!$B$99+Annahmen!$B$91*Annahmen!$B$102) -> 0 | L29: =IF($A29>=Annahmen!$B$82,Annahmen!$B$92,0) -> 0 | M29: =L29*Annahmen!$B$103 -> 0 | N29: =IF($A29>=Annahmen!$B$82,Annahmen!$B$93,0) -> 0 | O29: =N29*Annahmen!$B$104 -> 0 | P29: =IF($A29>=Annahmen!$B$82,Annahmen!$B$94,0) -> 0 | Q29: =P29*Annahmen!$B$105 -> 0 | R29: =IF($A29>=Annahmen!$B$82,Annahmen!$B$95,0) -> 0 | S29: =R29*Annahmen!$B$106 -> 0 | T29: =E29+G29+I29+K29+M29+O29+Q29+S29 -> 314.58 | U29: =C29*Annahmen!$B$51+F29*Annahmen!$B$87*Annahmen!$B$47+H29*(Annahmen!$B$45+Annahmen!$B$89*(Annahmen!$B$47-Annahmen!$B$45))+J29*Annahmen!$B$48+L29*Annahmen!$B$49+(N29+P29)*Annahmen!$B$50 -> 8.7603929 | V29: =SUMPRODUCT((((Annahmen!$C$145:$C$155="monatlich")*(Annahmen!$D$145:$D$155<=$A29))+((Annahmen!$C$145:$C$155="einmalig")*(Annahmen!$D$145:$D$155=$A29)))*Annahmen!$B$145:$B$155*Annahmen!$F$145:$F$155) -> 50.827571 | W29: =Annahmen!$B$135 -> 50 | X29: =C29+F29*Annahmen!$B$87+H29+J29+L29/Annahmen!$B$46+(N29+P29)/(Annahmen!$B$23/Annahmen!$B$24) -> 0.75 | Y29: =MAX(0,(X29-Annahmen!$B$140)/Annahmen!$B$141) -> 0 | Z29: =Y29*Annahmen!$B$137 -> 0 | AA29: =T29-U29-V29-W29-Z29 -> 204.99204 | AB29: =AB28+AA29 -> -389.10714 | AC29: =IF(AA29>0,1,0) -> 1 | AD29: =IF(AB29>=0,1,0) -> 0
A30: 13 | B30: 01/2028 | C30: =IF($A30>=Annahmen!$B$82,Annahmen!$B$83,0) -> 0.3 | D30: =C30*Annahmen!$B$84 -> 0.09 | E30: =(C30-D30)*Annahmen!$B$96 -> 102.9 | F30: =IF($A30>Annahmen!$B$86,INDEX($C$18:$C$41,$A30-Annahmen!$B$86)*Annahmen!$B$85,0) -> 0.09 | G30: =F30*(Annahmen!$B$87*(Annahmen!$B$97+Annahmen!$B$98)-Annahmen!$B$96*(1-Annahmen!$B$84)) -> 211.68 | H30: =IF($A30>=Annahmen!$B$82,Annahmen!$B$88,0) -> 0 | I30: =H30*(Annahmen!$B$97+Annahmen!$B$89*Annahmen!$B$98) -> 0 | J30: =IF($A30>=Annahmen!$B$82,Annahmen!$B$90,0) -> 0 | K30: =J30*(Annahmen!$B$99+Annahmen!$B$91*Annahmen!$B$102) -> 0 | L30: =IF($A30>=Annahmen!$B$82,Annahmen!$B$92,0) -> 0 | M30: =L30*Annahmen!$B$103 -> 0 | N30: =IF($A30>=Annahmen!$B$82,Annahmen!$B$93,0) -> 0 | O30: =N30*Annahmen!$B$104 -> 0 | P30: =IF($A30>=Annahmen!$B$82,Annahmen!$B$94,0) -> 0 | Q30: =P30*Annahmen!$B$105 -> 0 | R30: =IF($A30>=Annahmen!$B$82,Annahmen!$B$95,0) -> 0 | S30: =R30*Annahmen!$B$106 -> 0 | T30: =E30+G30+I30+K30+M30+O30+Q30+S30 -> 314.58 | U30: =C30*Annahmen!$B$51+F30*Annahmen!$B$87*Annahmen!$B$47+H30*(Annahmen!$B$45+Annahmen!$B$89*(Annahmen!$B$47-Annahmen!$B$45))+J30*Annahmen!$B$48+L30*Annahmen!$B$49+(N30+P30)*Annahmen!$B$50 -> 8.7603929 | V30: =SUMPRODUCT((((Annahmen!$C$145:$C$155="monatlich")*(Annahmen!$D$145:$D$155<=$A30))+((Annahmen!$C$145:$C$155="einmalig")*(Annahmen!$D$145:$D$155=$A30)))*Annahmen!$B$145:$B$155*Annahmen!$F$145:$F$155) -> 50.827571 | W30: =Annahmen!$B$135 -> 50 | X30: =C30+F30*Annahmen!$B$87+H30+J30+L30/Annahmen!$B$46+(N30+P30)/(Annahmen!$B$23/Annahmen!$B$24) -> 0.75 | Y30: =MAX(0,(X30-Annahmen!$B$140)/Annahmen!$B$141) -> 0 | Z30: =Y30*Annahmen!$B$137 -> 0 | AA30: =T30-U30-V30-W30-Z30 -> 204.99204 | AB30: =AB29+AA30 -> -184.1151 | AC30: =IF(AA30>0,1,0) -> 1 | AD30: =IF(AB30>=0,1,0) -> 0
... A41: 24 | B41: 12/2028 | C41: =IF($A41>=Annahmen!$B$82,Annahmen!$B$83,0) -> 0.3 | D41: =C41*Annahmen!$B$84 -> 0.09 | E41: =(C41-D41)*Annahmen!$B$96 -> 102.9 | F41: =IF($A41>Annahmen!$B$86,INDEX($C$18:$C$41,$A41-Annahmen!$B$86)*Annahmen!$B$85,0) -> 0.09 | G41: =F41*(Annahmen!$B$87*(Annahmen!$B$97+Annahmen!$B$98)-Annahmen!$B$96*(1-Annahmen!$B$84)) -> 211.68 | H41: =IF($A41>=Annahmen!$B$82,Annahmen!$B$88,0) -> 0 | I41: =H41*(Annahmen!$B$97+Annahmen!$B$89*Annahmen!$B$98) -> 0 | J41: =IF($A41>=Annahmen!$B$82,Annahmen!$B$90,0) -> 0 | K41: =J41*(Annahmen!$B$99+Annahmen!$B$91*Annahmen!$B$102) -> 0 | L41: =IF($A41>=Annahmen!$B$82,Annahmen!$B$92,0) -> 0 | M41: =L41*Annahmen!$B$103 -> 0 | N41: =IF($A41>=Annahmen!$B$82,Annahmen!$B$93,0) -> 0 | O41: =N41*Annahmen!$B$104 -> 0 | P41: =IF($A41>=Annahmen!$B$82,Annahmen!$B$94,0) -> 0 | Q41: =P41*Annahmen!$B$105 -> 0 | R41: =IF($A41>=Annahmen!$B$82,Annahmen!$B$95,0) -> 0 | S41: =R41*Annahmen!$B$106 -> 0 | T41: =E41+G41+I41+K41+M41+O41+Q41+S41 -> 314.58 | U41: =C41*Annahmen!$B$51+F41*Annahmen!$B$87*Annahmen!$B$47+H41*(Annahmen!$B$45+Annahmen!$B$89*(Annahmen!$B$47-Annahmen!$B$45))+J41*Annahmen!$B$48+L41*Annahmen!$B$49+(N41+P41)*Annahmen!$B$50 -> 8.7603929 | V41: =SUMPRODUCT((((Annahmen!$C$145:$C$155="monatlich")*(Annahmen!$D$145:$D$155<=$A41))+((Annahmen!$C$145:$C$155="einmalig")*(Annahmen!$D$145:$D$155=$A41)))*Annahmen!$B$145:$B$155*Annahmen!$F$145:$F$155) -> 50.827571 | W41: =Annahmen!$B$135 -> 50 | X41: =C41+F41*Annahmen!$B$87+H41+J41+L41/Annahmen!$B$46+(N41+P41)/(Annahmen!$B$23/Annahmen!$B$24) -> 0.75 | Y41: =MAX(0,(X41-Annahmen!$B$140)/Annahmen!$B$141) -> 0 | Z41: =Y41*Annahmen!$B$137 -> 0 | AA41: =T41-U41-V41-W41-Z41 -> 204.99204 | AB41: =AB40+AA41 -> 2070.7973 | AC41: =IF(AA41>0,1,0) -> 1 | AD41: =IF(AB41>=0,1,0) -> 1
A45: ="Szenario mittel – "&Annahmen!$C$133 -> Szenario mittel – profitabler Nebenerwerb
A46: Monat | B46: Datum | C46: Piloten | D46: davon Barter | E46: Pilot-Umsatz | F46: Folge-aufträge | G46: Folge-Umsatz (nach Anrechnung) | H46: BFSG-EPUB Titel | I46: Umsatz BFSG/MO | J46: Alignment Titel | K46: Umsatz Alignment | L46: Vertonung Audio-h | M46: Umsatz Vertonung | N46: Übersetzung NS | O46: Umsatz Übersetzung | P46: Modernisierung NS | Q46: Umsatz Moderni-sierung | R46: Zusatz-formate | S46: Umsatz Formate | T46: Umsatz gesamt | U46: Rechen-kosten | V46: Fixkosten anteilig | W46: Marketing | X46: Titel-Äquiv. | Y46: Personal-bedarf FTE | Z46: Personal-kosten | AA46: Ergebnis | AB46: Ergebnis kumuliert | AC46: BE monatl. | AD46: BE kum.
A47: 1 | B47: 01/2027 | C47: =IF($A47>=Annahmen!$C$82,Annahmen!$C$83,0) -> 0 | D47: =C47*Annahmen!$C$84 -> 0 | E47: =(C47-D47)*Annahmen!$B$96 -> 0 | F47: =IF($A47>Annahmen!$B$86,INDEX($C$47:$C$70,$A47-Annahmen!$B$86)*Annahmen!$C$85,0) -> 0 | G47: =F47*(Annahmen!$C$87*(Annahmen!$B$97+Annahmen!$B$98)-Annahmen!$B$96*(1-Annahmen!$C$84)) -> 0 | H47: =IF($A47>=Annahmen!$C$82,Annahmen!$C$88,0) -> 0 | I47: =H47*(Annahmen!$B$97+Annahmen!$C$89*Annahmen!$B$98) -> 0 | J47: =IF($A47>=Annahmen!$C$82,Annahmen!$C$90,0) -> 0 | K47: =J47*(Annahmen!$B$99+Annahmen!$B$91*Annahmen!$B$102) -> 0 | L47: =IF($A47>=Annahmen!$C$82,Annahmen!$C$92,0) -> 0 | M47: =L47*Annahmen!$B$103 -> 0 | N47: =IF($A47>=Annahmen!$C$82,Annahmen!$C$93,0) -> 0 | O47: =N47*Annahmen!$B$104 -> 0 | P47: =IF($A47>=Annahmen!$C$82,Annahmen!$C$94,0) -> 0 | Q47: =P47*Annahmen!$B$105 -> 0 | R47: =IF($A47>=Annahmen!$C$82,Annahmen!$C$95,0) -> 0 | S47: =R47*Annahmen!$B$106 -> 0 | T47: =E47+G47+I47+K47+M47+O47+Q47+S47 -> 0 | U47: =C47*Annahmen!$B$51+F47*Annahmen!$C$87*Annahmen!$B$47+H47*(Annahmen!$B$45+Annahmen!$C$89*(Annahmen!$B$47-Annahmen!$B$45))+J47*Annahmen!$B$48+L47*Annahmen!$B$49+(N47+P47)*Annahmen!$B$50 -> 0 | V47: =SUMPRODUCT((((Annahmen!$C$145:$C$155="monatlich")*(Annahmen!$D$145:$D$155<=$A47))+((Annahmen!$C$145:$C$155="einmalig")*(Annahmen!$D$145:$D$155=$A47)))*Annahmen!$B$145:$B$155*Annahmen!$F$145:$F$155) -> 213.22757 | W47: =Annahmen!$C$135 -> 150 | X47: =C47+F47*Annahmen!$C$87+H47+J47+L47/Annahmen!$B$46+(N47+P47)/(Annahmen!$B$23/Annahmen!$B$24) -> 0 | Y47: =MAX(0,(X47-Annahmen!$B$140)/Annahmen!$B$141) -> 0 | Z47: =Y47*Annahmen!$B$137 -> 0 | AA47: =T47-U47-V47-W47-Z47 -> -363.22757 | AB47: =AA47 -> -363.22757 | AC47: =IF(AA47>0,1,0) -> 0 | AD47: =IF(AB47>=0,1,0) -> 0
A48: 2 | B48: 02/2027 | C48: =IF($A48>=Annahmen!$C$82,Annahmen!$C$83,0) -> 0 | D48: =C48*Annahmen!$C$84 -> 0 | E48: =(C48-D48)*Annahmen!$B$96 -> 0 | F48: =IF($A48>Annahmen!$B$86,INDEX($C$47:$C$70,$A48-Annahmen!$B$86)*Annahmen!$C$85,0) -> 0 | G48: =F48*(Annahmen!$C$87*(Annahmen!$B$97+Annahmen!$B$98)-Annahmen!$B$96*(1-Annahmen!$C$84)) -> 0 | H48: =IF($A48>=Annahmen!$C$82,Annahmen!$C$88,0) -> 0 | I48: =H48*(Annahmen!$B$97+Annahmen!$C$89*Annahmen!$B$98) -> 0 | J48: =IF($A48>=Annahmen!$C$82,Annahmen!$C$90,0) -> 0 | K48: =J48*(Annahmen!$B$99+Annahmen!$B$91*Annahmen!$B$102) -> 0 | L48: =IF($A48>=Annahmen!$C$82,Annahmen!$C$92,0) -> 0 | M48: =L48*Annahmen!$B$103 -> 0 | N48: =IF($A48>=Annahmen!$C$82,Annahmen!$C$93,0) -> 0 | O48: =N48*Annahmen!$B$104 -> 0 | P48: =IF($A48>=Annahmen!$C$82,Annahmen!$C$94,0) -> 0 | Q48: =P48*Annahmen!$B$105 -> 0 | R48: =IF($A48>=Annahmen!$C$82,Annahmen!$C$95,0) -> 0 | S48: =R48*Annahmen!$B$106 -> 0 | T48: =E48+G48+I48+K48+M48+O48+Q48+S48 -> 0 | U48: =C48*Annahmen!$B$51+F48*Annahmen!$C$87*Annahmen!$B$47+H48*(Annahmen!$B$45+Annahmen!$C$89*(Annahmen!$B$47-Annahmen!$B$45))+J48*Annahmen!$B$48+L48*Annahmen!$B$49+(N48+P48)*Annahmen!$B$50 -> 0 | V48: =SUMPRODUCT((((Annahmen!$C$145:$C$155="monatlich")*(Annahmen!$D$145:$D$155<=$A48))+((Annahmen!$C$145:$C$155="einmalig")*(Annahmen!$D$145:$D$155=$A48)))*Annahmen!$B$145:$B$155*Annahmen!$F$145:$F$155) -> 50.827571 | W48: =Annahmen!$C$135 -> 150 | X48: =C48+F48*Annahmen!$C$87+H48+J48+L48/Annahmen!$B$46+(N48+P48)/(Annahmen!$B$23/Annahmen!$B$24) -> 0 | Y48: =MAX(0,(X48-Annahmen!$B$140)/Annahmen!$B$141) -> 0 | Z48: =Y48*Annahmen!$B$137 -> 0 | AA48: =T48-U48-V48-W48-Z48 -> -200.82757 | AB48: =AB47+AA48 -> -564.05514 | AC48: =IF(AA48>0,1,0) -> 0 | AD48: =IF(AB48>=0,1,0) -> 0
A49: 3 | B49: 03/2027 | C49: =IF($A49>=Annahmen!$C$82,Annahmen!$C$83,0) -> 0 | D49: =C49*Annahmen!$C$84 -> 0 | E49: =(C49-D49)*Annahmen!$B$96 -> 0 | F49: =IF($A49>Annahmen!$B$86,INDEX($C$47:$C$70,$A49-Annahmen!$B$86)*Annahmen!$C$85,0) -> 0 | G49: =F49*(Annahmen!$C$87*(Annahmen!$B$97+Annahmen!$B$98)-Annahmen!$B$96*(1-Annahmen!$C$84)) -> 0 | H49: =IF($A49>=Annahmen!$C$82,Annahmen!$C$88,0) -> 0 | I49: =H49*(Annahmen!$B$97+Annahmen!$C$89*Annahmen!$B$98) -> 0 | J49: =IF($A49>=Annahmen!$C$82,Annahmen!$C$90,0) -> 0 | K49: =J49*(Annahmen!$B$99+Annahmen!$B$91*Annahmen!$B$102) -> 0 | L49: =IF($A49>=Annahmen!$C$82,Annahmen!$C$92,0) -> 0 | M49: =L49*Annahmen!$B$103 -> 0 | N49: =IF($A49>=Annahmen!$C$82,Annahmen!$C$93,0) -> 0 | O49: =N49*Annahmen!$B$104 -> 0 | P49: =IF($A49>=Annahmen!$C$82,Annahmen!$C$94,0) -> 0 | Q49: =P49*Annahmen!$B$105 -> 0 | R49: =IF($A49>=Annahmen!$C$82,Annahmen!$C$95,0) -> 0 | S49: =R49*Annahmen!$B$106 -> 0 | T49: =E49+G49+I49+K49+M49+O49+Q49+S49 -> 0 | U49: =C49*Annahmen!$B$51+F49*Annahmen!$C$87*Annahmen!$B$47+H49*(Annahmen!$B$45+Annahmen!$C$89*(Annahmen!$B$47-Annahmen!$B$45))+J49*Annahmen!$B$48+L49*Annahmen!$B$49+(N49+P49)*Annahmen!$B$50 -> 0 | V49: =SUMPRODUCT((((Annahmen!$C$145:$C$155="monatlich")*(Annahmen!$D$145:$D$155<=$A49))+((Annahmen!$C$145:$C$155="einmalig")*(Annahmen!$D$145:$D$155=$A49)))*Annahmen!$B$145:$B$155*Annahmen!$F$145:$F$155) -> 330.82757 | W49: =Annahmen!$C$135 -> 150 | X49: =C49+F49*Annahmen!$C$87+H49+J49+L49/Annahmen!$B$46+(N49+P49)/(Annahmen!$B$23/Annahmen!$B$24) -> 0 | Y49: =MAX(0,(X49-Annahmen!$B$140)/Annahmen!$B$141) -> 0 | Z49: =Y49*Annahmen!$B$137 -> 0 | AA49: =T49-U49-V49-W49-Z49 -> -480.82757 | AB49: =AB48+AA49 -> -1044.8827 | AC49: =IF(AA49>0,1,0) -> 0 | AD49: =IF(AB49>=0,1,0) -> 0
A50: 4 | B50: 04/2027 | C50: =IF($A50>=Annahmen!$C$82,Annahmen!$C$83,0) -> 0.7 | D50: =C50*Annahmen!$C$84 -> 0.21 | E50: =(C50-D50)*Annahmen!$B$96 -> 240.1 | F50: =IF($A50>Annahmen!$B$86,INDEX($C$47:$C$70,$A50-Annahmen!$B$86)*Annahmen!$C$85,0) -> 0 | G50: =F50*(Annahmen!$C$87*(Annahmen!$B$97+Annahmen!$B$98)-Annahmen!$B$96*(1-Annahmen!$C$84)) -> 0 | H50: =IF($A50>=Annahmen!$C$82,Annahmen!$C$88,0) -> 1 | I50: =H50*(Annahmen!$B$97+Annahmen!$C$89*Annahmen!$B$98) -> 344 | J50: =IF($A50>=Annahmen!$C$82,Annahmen!$C$90,0) -> 0.5 | K50: =J50*(Annahmen!$B$99+Annahmen!$B$91*Annahmen!$B$102) -> 127.25806 | L50: =IF($A50>=Annahmen!$C$82,Annahmen!$C$92,0) -> 5 | M50: =L50*Annahmen!$B$103 -> 445 | N50: =IF($A50>=Annahmen!$C$82,Annahmen!$C$93,0) -> 50 | O50: =N50*Annahmen!$B$104 -> 300 | P50: =IF($A50>=Annahmen!$C$82,Annahmen!$C$94,0) -> 0 | Q50: =P50*Annahmen!$B$105 -> 0 | R50: =IF($A50>=Annahmen!$C$82,Annahmen!$C$95,0) -> 1 | S50: =R50*Annahmen!$B$106 -> 49 | T50: =E50+G50+I50+K50+M50+O50+Q50+S50 -> 1505.3581 | U50: =C50*Annahmen!$B$51+F50*Annahmen!$C$87*Annahmen!$B$47+H50*(Annahmen!$B$45+Annahmen!$C$89*(Annahmen!$B$47-Annahmen!$B$45))+J50*Annahmen!$B$48+L50*Annahmen!$B$49+(N50+P50)*Annahmen!$B$50 -> 25.455845 | V50: =SUMPRODUCT((((Annahmen!$C$145:$C$155="monatlich")*(Annahmen!$D$145:$D$155<=$A50))+((Annahmen!$C$145:$C$155="einmalig")*(Annahmen!$D$145:$D$155=$A50)))*Annahmen!$B$145:$B$155*Annahmen!$F$145:$F$155) -> 50.827571 | W50: =Annahmen!$C$135 -> 150 | X50: =C50+F50*Annahmen!$C$87+H50+J50+L50/Annahmen!$B$46+(N50+P50)/(Annahmen!$B$23/Annahmen!$B$24) -> 2.9375 | Y50: =MAX(0,(X50-Annahmen!$B$140)/Annahmen!$B$141) -> 0 | Z50: =Y50*Annahmen!$B$137 -> 0 | AA50: =T50-U50-V50-W50-Z50 -> 1279.0746 | AB50: =AB49+AA50 -> 234.19194 | AC50: =IF(AA50>0,1,0) -> 1 | AD50: =IF(AB50>=0,1,0) -> 1
A51: 5 | B51: 05/2027 | C51: =IF($A51>=Annahmen!$C$82,Annahmen!$C$83,0) -> 0.7 | D51: =C51*Annahmen!$C$84 -> 0.21 | E51: =(C51-D51)*Annahmen!$B$96 -> 240.1 | F51: =IF($A51>Annahmen!$B$86,INDEX($C$47:$C$70,$A51-Annahmen!$B$86)*Annahmen!$C$85,0) -> 0 | G51: =F51*(Annahmen!$C$87*(Annahmen!$B$97+Annahmen!$B$98)-Annahmen!$B$96*(1-Annahmen!$C$84)) -> 0 | H51: =IF($A51>=Annahmen!$C$82,Annahmen!$C$88,0) -> 1 | I51: =H51*(Annahmen!$B$97+Annahmen!$C$89*Annahmen!$B$98) -> 344 | J51: =IF($A51>=Annahmen!$C$82,Annahmen!$C$90,0) -> 0.5 | K51: =J51*(Annahmen!$B$99+Annahmen!$B$91*Annahmen!$B$102) -> 127.25806 | L51: =IF($A51>=Annahmen!$C$82,Annahmen!$C$92,0) -> 5 | M51: =L51*Annahmen!$B$103 -> 445 | N51: =IF($A51>=Annahmen!$C$82,Annahmen!$C$93,0) -> 50 | O51: =N51*Annahmen!$B$104 -> 300 | P51: =IF($A51>=Annahmen!$C$82,Annahmen!$C$94,0) -> 0 | Q51: =P51*Annahmen!$B$105 -> 0 | R51: =IF($A51>=Annahmen!$C$82,Annahmen!$C$95,0) -> 1 | S51: =R51*Annahmen!$B$106 -> 49 | T51: =E51+G51+I51+K51+M51+O51+Q51+S51 -> 1505.3581 | U51: =C51*Annahmen!$B$51+F51*Annahmen!$C$87*Annahmen!$B$47+H51*(Annahmen!$B$45+Annahmen!$C$89*(Annahmen!$B$47-Annahmen!$B$45))+J51*Annahmen!$B$48+L51*Annahmen!$B$49+(N51+P51)*Annahmen!$B$50 -> 25.455845 | V51: =SUMPRODUCT((((Annahmen!$C$145:$C$155="monatlich")*(Annahmen!$D$145:$D$155<=$A51))+((Annahmen!$C$145:$C$155="einmalig")*(Annahmen!$D$145:$D$155=$A51)))*Annahmen!$B$145:$B$155*Annahmen!$F$145:$F$155) -> 610.82757 | W51: =Annahmen!$C$135 -> 150 | X51: =C51+F51*Annahmen!$C$87+H51+J51+L51/Annahmen!$B$46+(N51+P51)/(Annahmen!$B$23/Annahmen!$B$24) -> 2.9375 | Y51: =MAX(0,(X51-Annahmen!$B$140)/Annahmen!$B$141) -> 0 | Z51: =Y51*Annahmen!$B$137 -> 0 | AA51: =T51-U51-V51-W51-Z51 -> 719.07465 | AB51: =AB50+AA51 -> 953.26659 | AC51: =IF(AA51>0,1,0) -> 1 | AD51: =IF(AB51>=0,1,0) -> 1
A52: 6 | B52: 06/2027 | C52: =IF($A52>=Annahmen!$C$82,Annahmen!$C$83,0) -> 0.7 | D52: =C52*Annahmen!$C$84 -> 0.21 | E52: =(C52-D52)*Annahmen!$B$96 -> 240.1 | F52: =IF($A52>Annahmen!$B$86,INDEX($C$47:$C$70,$A52-Annahmen!$B$86)*Annahmen!$C$85,0) -> 0 | G52: =F52*(Annahmen!$C$87*(Annahmen!$B$97+Annahmen!$B$98)-Annahmen!$B$96*(1-Annahmen!$C$84)) -> 0 | H52: =IF($A52>=Annahmen!$C$82,Annahmen!$C$88,0) -> 1 | I52: =H52*(Annahmen!$B$97+Annahmen!$C$89*Annahmen!$B$98) -> 344 | J52: =IF($A52>=Annahmen!$C$82,Annahmen!$C$90,0) -> 0.5 | K52: =J52*(Annahmen!$B$99+Annahmen!$B$91*Annahmen!$B$102) -> 127.25806 | L52: =IF($A52>=Annahmen!$C$82,Annahmen!$C$92,0) -> 5 | M52: =L52*Annahmen!$B$103 -> 445 | N52: =IF($A52>=Annahmen!$C$82,Annahmen!$C$93,0) -> 50 | O52: =N52*Annahmen!$B$104 -> 300 | P52: =IF($A52>=Annahmen!$C$82,Annahmen!$C$94,0) -> 0 | Q52: =P52*Annahmen!$B$105 -> 0 | R52: =IF($A52>=Annahmen!$C$82,Annahmen!$C$95,0) -> 1 | S52: =R52*Annahmen!$B$106 -> 49 | T52: =E52+G52+I52+K52+M52+O52+Q52+S52 -> 1505.3581 | U52: =C52*Annahmen!$B$51+F52*Annahmen!$C$87*Annahmen!$B$47+H52*(Annahmen!$B$45+Annahmen!$C$89*(Annahmen!$B$47-Annahmen!$B$45))+J52*Annahmen!$B$48+L52*Annahmen!$B$49+(N52+P52)*Annahmen!$B$50 -> 25.455845 | V52: =SUMPRODUCT((((Annahmen!$C$145:$C$155="monatlich")*(Annahmen!$D$145:$D$155<=$A52))+((Annahmen!$C$145:$C$155="einmalig")*(Annahmen!$D$145:$D$155=$A52)))*Annahmen!$B$145:$B$155*Annahmen!$F$145:$F$155) -> 50.827571 | W52: =Annahmen!$C$135 -> 150 | X52: =C52+F52*Annahmen!$C$87+H52+J52+L52/Annahmen!$B$46+(N52+P52)/(Annahmen!$B$23/Annahmen!$B$24) -> 2.9375 | Y52: =MAX(0,(X52-Annahmen!$B$140)/Annahmen!$B$141) -> 0 | Z52: =Y52*Annahmen!$B$137 -> 0 | AA52: =T52-U52-V52-W52-Z52 -> 1279.0746 | AB52: =AB51+AA52 -> 2232.3412 | AC52: =IF(AA52>0,1,0) -> 1 | AD52: =IF(AB52>=0,1,0) -> 1
A53: 7 | B53: 07/2027 | C53: =IF($A53>=Annahmen!$C$82,Annahmen!$C$83,0) -> 0.7 | D53: =C53*Annahmen!$C$84 -> 0.21 | E53: =(C53-D53)*Annahmen!$B$96 -> 240.1 | F53: =IF($A53>Annahmen!$B$86,INDEX($C$47:$C$70,$A53-Annahmen!$B$86)*Annahmen!$C$85,0) -> 0.28 | G53: =F53*(Annahmen!$C$87*(Annahmen!$B$97+Annahmen!$B$98)-Annahmen!$B$96*(1-Annahmen!$C$84)) -> 658.56 | H53: =IF($A53>=Annahmen!$C$82,Annahmen!$C$88,0) -> 1 | I53: =H53*(Annahmen!$B$97+Annahmen!$C$89*Annahmen!$B$98) -> 344 | J53: =IF($A53>=Annahmen!$C$82,Annahmen!$C$90,0) -> 0.5 | K53: =J53*(Annahmen!$B$99+Annahmen!$B$91*Annahmen!$B$102) -> 127.25806 | L53: =IF($A53>=Annahmen!$C$82,Annahmen!$C$92,0) -> 5 | M53: =L53*Annahmen!$B$103 -> 445 | N53: =IF($A53>=Annahmen!$C$82,Annahmen!$C$93,0) -> 50 | O53: =N53*Annahmen!$B$104 -> 300 | P53: =IF($A53>=Annahmen!$C$82,Annahmen!$C$94,0) -> 0 | Q53: =P53*Annahmen!$B$105 -> 0 | R53: =IF($A53>=Annahmen!$C$82,Annahmen!$C$95,0) -> 1 | S53: =R53*Annahmen!$B$106 -> 49 | T53: =E53+G53+I53+K53+M53+O53+Q53+S53 -> 2163.9181 | U53: =C53*Annahmen!$B$51+F53*Annahmen!$C$87*Annahmen!$B$47+H53*(Annahmen!$B$45+Annahmen!$C$89*(Annahmen!$B$47-Annahmen!$B$45))+J53*Annahmen!$B$48+L53*Annahmen!$B$49+(N53+P53)*Annahmen!$B$50 -> 37.596285 | V53: =SUMPRODUCT((((Annahmen!$C$145:$C$155="monatlich")*(Annahmen!$D$145:$D$155<=$A53))+((Annahmen!$C$145:$C$155="einmalig")*(Annahmen!$D$145:$D$155=$A53)))*Annahmen!$B$145:$B$155*Annahmen!$F$145:$F$155) -> 50.827571 | W53: =Annahmen!$C$135 -> 150 | X53: =C53+F53*Annahmen!$C$87+H53+J53+L53/Annahmen!$B$46+(N53+P53)/(Annahmen!$B$23/Annahmen!$B$24) -> 4.3375 | Y53: =MAX(0,(X53-Annahmen!$B$140)/Annahmen!$B$141) -> 0 | Z53: =Y53*Annahmen!$B$137 -> 0 | AA53: =T53-U53-V53-W53-Z53 -> 1925.4942 | AB53: =AB52+AA53 -> 4157.8354 | AC53: =IF(AA53>0,1,0) -> 1 | AD53: =IF(AB53>=0,1,0) -> 1
A54: 8 | B54: 08/2027 | C54: =IF($A54>=Annahmen!$C$82,Annahmen!$C$83,0) -> 0.7 | D54: =C54*Annahmen!$C$84 -> 0.21 | E54: =(C54-D54)*Annahmen!$B$96 -> 240.1 | F54: =IF($A54>Annahmen!$B$86,INDEX($C$47:$C$70,$A54-Annahmen!$B$86)*Annahmen!$C$85,0) -> 0.28 | G54: =F54*(Annahmen!$C$87*(Annahmen!$B$97+Annahmen!$B$98)-Annahmen!$B$96*(1-Annahmen!$C$84)) -> 658.56 | H54: =IF($A54>=Annahmen!$C$82,Annahmen!$C$88,0) -> 1 | I54: =H54*(Annahmen!$B$97+Annahmen!$C$89*Annahmen!$B$98) -> 344 | J54: =IF($A54>=Annahmen!$C$82,Annahmen!$C$90,0) -> 0.5 | K54: =J54*(Annahmen!$B$99+Annahmen!$B$91*Annahmen!$B$102) -> 127.25806 | L54: =IF($A54>=Annahmen!$C$82,Annahmen!$C$92,0) -> 5 | M54: =L54*Annahmen!$B$103 -> 445 | N54: =IF($A54>=Annahmen!$C$82,Annahmen!$C$93,0) -> 50 | O54: =N54*Annahmen!$B$104 -> 300 | P54: =IF($A54>=Annahmen!$C$82,Annahmen!$C$94,0) -> 0 | Q54: =P54*Annahmen!$B$105 -> 0 | R54: =IF($A54>=Annahmen!$C$82,Annahmen!$C$95,0) -> 1 | S54: =R54*Annahmen!$B$106 -> 49 | T54: =E54+G54+I54+K54+M54+O54+Q54+S54 -> 2163.9181 | U54: =C54*Annahmen!$B$51+F54*Annahmen!$C$87*Annahmen!$B$47+H54*(Annahmen!$B$45+Annahmen!$C$89*(Annahmen!$B$47-Annahmen!$B$45))+J54*Annahmen!$B$48+L54*Annahmen!$B$49+(N54+P54)*Annahmen!$B$50 -> 37.596285 | V54: =SUMPRODUCT((((Annahmen!$C$145:$C$155="monatlich")*(Annahmen!$D$145:$D$155<=$A54))+((Annahmen!$C$145:$C$155="einmalig")*(Annahmen!$D$145:$D$155=$A54)))*Annahmen!$B$145:$B$155*Annahmen!$F$145:$F$155) -> 50.827571 | W54: =Annahmen!$C$135 -> 150 | X54: =C54+F54*Annahmen!$C$87+H54+J54+L54/Annahmen!$B$46+(N54+P54)/(Annahmen!$B$23/Annahmen!$B$24) -> 4.3375 | Y54: =MAX(0,(X54-Annahmen!$B$140)/Annahmen!$B$141) -> 0 | Z54: =Y54*Annahmen!$B$137 -> 0 | AA54: =T54-U54-V54-W54-Z54 -> 1925.4942 | AB54: =AB53+AA54 -> 6083.3297 | AC54: =IF(AA54>0,1,0) -> 1 | AD54: =IF(AB54>=0,1,0) -> 1
A55: 9 | B55: 09/2027 | C55: =IF($A55>=Annahmen!$C$82,Annahmen!$C$83,0) -> 0.7 | D55: =C55*Annahmen!$C$84 -> 0.21 | E55: =(C55-D55)*Annahmen!$B$96 -> 240.1 | F55: =IF($A55>Annahmen!$B$86,INDEX($C$47:$C$70,$A55-Annahmen!$B$86)*Annahmen!$C$85,0) -> 0.28 | G55: =F55*(Annahmen!$C$87*(Annahmen!$B$97+Annahmen!$B$98)-Annahmen!$B$96*(1-Annahmen!$C$84)) -> 658.56 | H55: =IF($A55>=Annahmen!$C$82,Annahmen!$C$88,0) -> 1 | I55: =H55*(Annahmen!$B$97+Annahmen!$C$89*Annahmen!$B$98) -> 344 | J55: =IF($A55>=Annahmen!$C$82,Annahmen!$C$90,0) -> 0.5 | K55: =J55*(Annahmen!$B$99+Annahmen!$B$91*Annahmen!$B$102) -> 127.25806 | L55: =IF($A55>=Annahmen!$C$82,Annahmen!$C$92,0) -> 5 | M55: =L55*Annahmen!$B$103 -> 445 | N55: =IF($A55>=Annahmen!$C$82,Annahmen!$C$93,0) -> 50 | O55: =N55*Annahmen!$B$104 -> 300 | P55: =IF($A55>=Annahmen!$C$82,Annahmen!$C$94,0) -> 0 | Q55: =P55*Annahmen!$B$105 -> 0 | R55: =IF($A55>=Annahmen!$C$82,Annahmen!$C$95,0) -> 1 | S55: =R55*Annahmen!$B$106 -> 49 | T55: =E55+G55+I55+K55+M55+O55+Q55+S55 -> 2163.9181 | U55: =C55*Annahmen!$B$51+F55*Annahmen!$C$87*Annahmen!$B$47+H55*(Annahmen!$B$45+Annahmen!$C$89*(Annahmen!$B$47-Annahmen!$B$45))+J55*Annahmen!$B$48+L55*Annahmen!$B$49+(N55+P55)*Annahmen!$B$50 -> 37.596285 | V55: =SUMPRODUCT((((Annahmen!$C$145:$C$155="monatlich")*(Annahmen!$D$145:$D$155<=$A55))+((Annahmen!$C$145:$C$155="einmalig")*(Annahmen!$D$145:$D$155=$A55)))*Annahmen!$B$145:$B$155*Annahmen!$F$145:$F$155) -> 50.827571 | W55: =Annahmen!$C$135 -> 150 | X55: =C55+F55*Annahmen!$C$87+H55+J55+L55/Annahmen!$B$46+(N55+P55)/(Annahmen!$B$23/Annahmen!$B$24) -> 4.3375 | Y55: =MAX(0,(X55-Annahmen!$B$140)/Annahmen!$B$141) -> 0 | Z55: =Y55*Annahmen!$B$137 -> 0 | AA55: =T55-U55-V55-W55-Z55 -> 1925.4942 | AB55: =AB54+AA55 -> 8008.8239 | AC55: =IF(AA55>0,1,0) -> 1 | AD55: =IF(AB55>=0,1,0) -> 1
A56: 10 | B56: 10/2027 | C56: =IF($A56>=Annahmen!$C$82,Annahmen!$C$83,0) -> 0.7 | D56: =C56*Annahmen!$C$84 -> 0.21 | E56: =(C56-D56)*Annahmen!$B$96 -> 240.1 | F56: =IF($A56>Annahmen!$B$86,INDEX($C$47:$C$70,$A56-Annahmen!$B$86)*Annahmen!$C$85,0) -> 0.28 | G56: =F56*(Annahmen!$C$87*(Annahmen!$B$97+Annahmen!$B$98)-Annahmen!$B$96*(1-Annahmen!$C$84)) -> 658.56 | H56: =IF($A56>=Annahmen!$C$82,Annahmen!$C$88,0) -> 1 | I56: =H56*(Annahmen!$B$97+Annahmen!$C$89*Annahmen!$B$98) -> 344 | J56: =IF($A56>=Annahmen!$C$82,Annahmen!$C$90,0) -> 0.5 | K56: =J56*(Annahmen!$B$99+Annahmen!$B$91*Annahmen!$B$102) -> 127.25806 | L56: =IF($A56>=Annahmen!$C$82,Annahmen!$C$92,0) -> 5 | M56: =L56*Annahmen!$B$103 -> 445 | N56: =IF($A56>=Annahmen!$C$82,Annahmen!$C$93,0) -> 50 | O56: =N56*Annahmen!$B$104 -> 300 | P56: =IF($A56>=Annahmen!$C$82,Annahmen!$C$94,0) -> 0 | Q56: =P56*Annahmen!$B$105 -> 0 | R56: =IF($A56>=Annahmen!$C$82,Annahmen!$C$95,0) -> 1 | S56: =R56*Annahmen!$B$106 -> 49 | T56: =E56+G56+I56+K56+M56+O56+Q56+S56 -> 2163.9181 | U56: =C56*Annahmen!$B$51+F56*Annahmen!$C$87*Annahmen!$B$47+H56*(Annahmen!$B$45+Annahmen!$C$89*(Annahmen!$B$47-Annahmen!$B$45))+J56*Annahmen!$B$48+L56*Annahmen!$B$49+(N56+P56)*Annahmen!$B$50 -> 37.596285 | V56: =SUMPRODUCT((((Annahmen!$C$145:$C$155="monatlich")*(Annahmen!$D$145:$D$155<=$A56))+((Annahmen!$C$145:$C$155="einmalig")*(Annahmen!$D$145:$D$155=$A56)))*Annahmen!$B$145:$B$155*Annahmen!$F$145:$F$155) -> 50.827571 | W56: =Annahmen!$C$135 -> 150 | X56: =C56+F56*Annahmen!$C$87+H56+J56+L56/Annahmen!$B$46+(N56+P56)/(Annahmen!$B$23/Annahmen!$B$24) -> 4.3375 | Y56: =MAX(0,(X56-Annahmen!$B$140)/Annahmen!$B$141) -> 0 | Z56: =Y56*Annahmen!$B$137 -> 0 | AA56: =T56-U56-V56-W56-Z56 -> 1925.4942 | AB56: =AB55+AA56 -> 9934.3181 | AC56: =IF(AA56>0,1,0) -> 1 | AD56: =IF(AB56>=0,1,0) -> 1
A57: 11 | B57: 11/2027 | C57: =IF($A57>=Annahmen!$C$82,Annahmen!$C$83,0) -> 0.7 | D57: =C57*Annahmen!$C$84 -> 0.21 | E57: =(C57-D57)*Annahmen!$B$96 -> 240.1 | F57: =IF($A57>Annahmen!$B$86,INDEX($C$47:$C$70,$A57-Annahmen!$B$86)*Annahmen!$C$85,0) -> 0.28 | G57: =F57*(Annahmen!$C$87*(Annahmen!$B$97+Annahmen!$B$98)-Annahmen!$B$96*(1-Annahmen!$C$84)) -> 658.56 | H57: =IF($A57>=Annahmen!$C$82,Annahmen!$C$88,0) -> 1 | I57: =H57*(Annahmen!$B$97+Annahmen!$C$89*Annahmen!$B$98) -> 344 | J57: =IF($A57>=Annahmen!$C$82,Annahmen!$C$90,0) -> 0.5 | K57: =J57*(Annahmen!$B$99+Annahmen!$B$91*Annahmen!$B$102) -> 127.25806 | L57: =IF($A57>=Annahmen!$C$82,Annahmen!$C$92,0) -> 5 | M57: =L57*Annahmen!$B$103 -> 445 | N57: =IF($A57>=Annahmen!$C$82,Annahmen!$C$93,0) -> 50 | O57: =N57*Annahmen!$B$104 -> 300 | P57: =IF($A57>=Annahmen!$C$82,Annahmen!$C$94,0) -> 0 | Q57: =P57*Annahmen!$B$105 -> 0 | R57: =IF($A57>=Annahmen!$C$82,Annahmen!$C$95,0) -> 1 | S57: =R57*Annahmen!$B$106 -> 49 | T57: =E57+G57+I57+K57+M57+O57+Q57+S57 -> 2163.9181 | U57: =C57*Annahmen!$B$51+F57*Annahmen!$C$87*Annahmen!$B$47+H57*(Annahmen!$B$45+Annahmen!$C$89*(Annahmen!$B$47-Annahmen!$B$45))+J57*Annahmen!$B$48+L57*Annahmen!$B$49+(N57+P57)*Annahmen!$B$50 -> 37.596285 | V57: =SUMPRODUCT((((Annahmen!$C$145:$C$155="monatlich")*(Annahmen!$D$145:$D$155<=$A57))+((Annahmen!$C$145:$C$155="einmalig")*(Annahmen!$D$145:$D$155=$A57)))*Annahmen!$B$145:$B$155*Annahmen!$F$145:$F$155) -> 50.827571 | W57: =Annahmen!$C$135 -> 150 | X57: =C57+F57*Annahmen!$C$87+H57+J57+L57/Annahmen!$B$46+(N57+P57)/(Annahmen!$B$23/Annahmen!$B$24) -> 4.3375 | Y57: =MAX(0,(X57-Annahmen!$B$140)/Annahmen!$B$141) -> 0 | Z57: =Y57*Annahmen!$B$137 -> 0 | AA57: =T57-U57-V57-W57-Z57 -> 1925.4942 | AB57: =AB56+AA57 -> 11859.812 | AC57: =IF(AA57>0,1,0) -> 1 | AD57: =IF(AB57>=0,1,0) -> 1
A58: 12 | B58: 12/2027 | C58: =IF($A58>=Annahmen!$C$82,Annahmen!$C$83,0) -> 0.7 | D58: =C58*Annahmen!$C$84 -> 0.21 | E58: =(C58-D58)*Annahmen!$B$96 -> 240.1 | F58: =IF($A58>Annahmen!$B$86,INDEX($C$47:$C$70,$A58-Annahmen!$B$86)*Annahmen!$C$85,0) -> 0.28 | G58: =F58*(Annahmen!$C$87*(Annahmen!$B$97+Annahmen!$B$98)-Annahmen!$B$96*(1-Annahmen!$C$84)) -> 658.56 | H58: =IF($A58>=Annahmen!$C$82,Annahmen!$C$88,0) -> 1 | I58: =H58*(Annahmen!$B$97+Annahmen!$C$89*Annahmen!$B$98) -> 344 | J58: =IF($A58>=Annahmen!$C$82,Annahmen!$C$90,0) -> 0.5 | K58: =J58*(Annahmen!$B$99+Annahmen!$B$91*Annahmen!$B$102) -> 127.25806 | L58: =IF($A58>=Annahmen!$C$82,Annahmen!$C$92,0) -> 5 | M58: =L58*Annahmen!$B$103 -> 445 | N58: =IF($A58>=Annahmen!$C$82,Annahmen!$C$93,0) -> 50 | O58: =N58*Annahmen!$B$104 -> 300 | P58: =IF($A58>=Annahmen!$C$82,Annahmen!$C$94,0) -> 0 | Q58: =P58*Annahmen!$B$105 -> 0 | R58: =IF($A58>=Annahmen!$C$82,Annahmen!$C$95,0) -> 1 | S58: =R58*Annahmen!$B$106 -> 49 | T58: =E58+G58+I58+K58+M58+O58+Q58+S58 -> 2163.9181 | U58: =C58*Annahmen!$B$51+F58*Annahmen!$C$87*Annahmen!$B$47+H58*(Annahmen!$B$45+Annahmen!$C$89*(Annahmen!$B$47-Annahmen!$B$45))+J58*Annahmen!$B$48+L58*Annahmen!$B$49+(N58+P58)*Annahmen!$B$50 -> 37.596285 | V58: =SUMPRODUCT((((Annahmen!$C$145:$C$155="monatlich")*(Annahmen!$D$145:$D$155<=$A58))+((Annahmen!$C$145:$C$155="einmalig")*(Annahmen!$D$145:$D$155=$A58)))*Annahmen!$B$145:$B$155*Annahmen!$F$145:$F$155) -> 50.827571 | W58: =Annahmen!$C$135 -> 150 | X58: =C58+F58*Annahmen!$C$87+H58+J58+L58/Annahmen!$B$46+(N58+P58)/(Annahmen!$B$23/Annahmen!$B$24) -> 4.3375 | Y58: =MAX(0,(X58-Annahmen!$B$140)/Annahmen!$B$141) -> 0 | Z58: =Y58*Annahmen!$B$137 -> 0 | AA58: =T58-U58-V58-W58-Z58 -> 1925.4942 | AB58: =AB57+AA58 -> 13785.306 | AC58: =IF(AA58>0,1,0) -> 1 | AD58: =IF(AB58>=0,1,0) -> 1
A59: 13 | B59: 01/2028 | C59: =IF($A59>=Annahmen!$C$82,Annahmen!$C$83,0) -> 0.7 | D59: =C59*Annahmen!$C$84 -> 0.21 | E59: =(C59-D59)*Annahmen!$B$96 -> 240.1 | F59: =IF($A59>Annahmen!$B$86,INDEX($C$47:$C$70,$A59-Annahmen!$B$86)*Annahmen!$C$85,0) -> 0.28 | G59: =F59*(Annahmen!$C$87*(Annahmen!$B$97+Annahmen!$B$98)-Annahmen!$B$96*(1-Annahmen!$C$84)) -> 658.56 | H59: =IF($A59>=Annahmen!$C$82,Annahmen!$C$88,0) -> 1 | I59: =H59*(Annahmen!$B$97+Annahmen!$C$89*Annahmen!$B$98) -> 344 | J59: =IF($A59>=Annahmen!$C$82,Annahmen!$C$90,0) -> 0.5 | K59: =J59*(Annahmen!$B$99+Annahmen!$B$91*Annahmen!$B$102) -> 127.25806 | L59: =IF($A59>=Annahmen!$C$82,Annahmen!$C$92,0) -> 5 | M59: =L59*Annahmen!$B$103 -> 445 | N59: =IF($A59>=Annahmen!$C$82,Annahmen!$C$93,0) -> 50 | O59: =N59*Annahmen!$B$104 -> 300 | P59: =IF($A59>=Annahmen!$C$82,Annahmen!$C$94,0) -> 0 | Q59: =P59*Annahmen!$B$105 -> 0 | R59: =IF($A59>=Annahmen!$C$82,Annahmen!$C$95,0) -> 1 | S59: =R59*Annahmen!$B$106 -> 49 | T59: =E59+G59+I59+K59+M59+O59+Q59+S59 -> 2163.9181 | U59: =C59*Annahmen!$B$51+F59*Annahmen!$C$87*Annahmen!$B$47+H59*(Annahmen!$B$45+Annahmen!$C$89*(Annahmen!$B$47-Annahmen!$B$45))+J59*Annahmen!$B$48+L59*Annahmen!$B$49+(N59+P59)*Annahmen!$B$50 -> 37.596285 | V59: =SUMPRODUCT((((Annahmen!$C$145:$C$155="monatlich")*(Annahmen!$D$145:$D$155<=$A59))+((Annahmen!$C$145:$C$155="einmalig")*(Annahmen!$D$145:$D$155=$A59)))*Annahmen!$B$145:$B$155*Annahmen!$F$145:$F$155) -> 50.827571 | W59: =Annahmen!$C$135 -> 150 | X59: =C59+F59*Annahmen!$C$87+H59+J59+L59/Annahmen!$B$46+(N59+P59)/(Annahmen!$B$23/Annahmen!$B$24) -> 4.3375 | Y59: =MAX(0,(X59-Annahmen!$B$140)/Annahmen!$B$141) -> 0 | Z59: =Y59*Annahmen!$B$137 -> 0 | AA59: =T59-U59-V59-W59-Z59 -> 1925.4942 | AB59: =AB58+AA59 -> 15710.801 | AC59: =IF(AA59>0,1,0) -> 1 | AD59: =IF(AB59>=0,1,0) -> 1
... A70: 24 | B70: 12/2028 | C70: =IF($A70>=Annahmen!$C$82,Annahmen!$C$83,0) -> 0.7 | D70: =C70*Annahmen!$C$84 -> 0.21 | E70: =(C70-D70)*Annahmen!$B$96 -> 240.1 | F70: =IF($A70>Annahmen!$B$86,INDEX($C$47:$C$70,$A70-Annahmen!$B$86)*Annahmen!$C$85,0) -> 0.28 | G70: =F70*(Annahmen!$C$87*(Annahmen!$B$97+Annahmen!$B$98)-Annahmen!$B$96*(1-Annahmen!$C$84)) -> 658.56 | H70: =IF($A70>=Annahmen!$C$82,Annahmen!$C$88,0) -> 1 | I70: =H70*(Annahmen!$B$97+Annahmen!$C$89*Annahmen!$B$98) -> 344 | J70: =IF($A70>=Annahmen!$C$82,Annahmen!$C$90,0) -> 0.5 | K70: =J70*(Annahmen!$B$99+Annahmen!$B$91*Annahmen!$B$102) -> 127.25806 | L70: =IF($A70>=Annahmen!$C$82,Annahmen!$C$92,0) -> 5 | M70: =L70*Annahmen!$B$103 -> 445 | N70: =IF($A70>=Annahmen!$C$82,Annahmen!$C$93,0) -> 50 | O70: =N70*Annahmen!$B$104 -> 300 | P70: =IF($A70>=Annahmen!$C$82,Annahmen!$C$94,0) -> 0 | Q70: =P70*Annahmen!$B$105 -> 0 | R70: =IF($A70>=Annahmen!$C$82,Annahmen!$C$95,0) -> 1 | S70: =R70*Annahmen!$B$106 -> 49 | T70: =E70+G70+I70+K70+M70+O70+Q70+S70 -> 2163.9181 | U70: =C70*Annahmen!$B$51+F70*Annahmen!$C$87*Annahmen!$B$47+H70*(Annahmen!$B$45+Annahmen!$C$89*(Annahmen!$B$47-Annahmen!$B$45))+J70*Annahmen!$B$48+L70*Annahmen!$B$49+(N70+P70)*Annahmen!$B$50 -> 37.596285 | V70: =SUMPRODUCT((((Annahmen!$C$145:$C$155="monatlich")*(Annahmen!$D$145:$D$155<=$A70))+((Annahmen!$C$145:$C$155="einmalig")*(Annahmen!$D$145:$D$155=$A70)))*Annahmen!$B$145:$B$155*Annahmen!$F$145:$F$155) -> 50.827571 | W70: =Annahmen!$C$135 -> 150 | X70: =C70+F70*Annahmen!$C$87+H70+J70+L70/Annahmen!$B$46+(N70+P70)/(Annahmen!$B$23/Annahmen!$B$24) -> 4.3375 | Y70: =MAX(0,(X70-Annahmen!$B$140)/Annahmen!$B$141) -> 0 | Z70: =Y70*Annahmen!$B$137 -> 0 | AA70: =T70-U70-V70-W70-Z70 -> 1925.4942 | AB70: =AB69+AA70 -> 36891.237 | AC70: =IF(AA70>0,1,0) -> 1 | AD70: =IF(AB70>=0,1,0) -> 1
A74: ="Szenario stark – "&Annahmen!$D$133 -> Szenario stark – skalierbares Business
A75: Monat | B75: Datum | C75: Piloten | D75: davon Barter | E75: Pilot-Umsatz | F75: Folge-aufträge | G75: Folge-Umsatz (nach Anrechnung) | H75: BFSG-EPUB Titel | I75: Umsatz BFSG/MO | J75: Alignment Titel | K75: Umsatz Alignment | L75: Vertonung Audio-h | M75: Umsatz Vertonung | N75: Übersetzung NS | O75: Umsatz Übersetzung | P75: Modernisierung NS | Q75: Umsatz Moderni-sierung | R75: Zusatz-formate | S75: Umsatz Formate | T75: Umsatz gesamt | U75: Rechen-kosten | V75: Fixkosten anteilig | W75: Marketing | X75: Titel-Äquiv. | Y75: Personal-bedarf FTE | Z75: Personal-kosten | AA75: Ergebnis | AB75: Ergebnis kumuliert | AC75: BE monatl. | AD75: BE kum.
A76: 1 | B76: 01/2027 | C76: =IF($A76>=Annahmen!$D$82,Annahmen!$D$83,0) -> 0 | D76: =C76*Annahmen!$D$84 -> 0 | E76: =(C76-D76)*Annahmen!$B$96 -> 0 | F76: =IF($A76>Annahmen!$B$86,INDEX($C$76:$C$99,$A76-Annahmen!$B$86)*Annahmen!$D$85,0) -> 0 | G76: =F76*(Annahmen!$D$87*(Annahmen!$B$97+Annahmen!$B$98)-Annahmen!$B$96*(1-Annahmen!$D$84)) -> 0 | H76: =IF($A76>=Annahmen!$D$82,Annahmen!$D$88,0) -> 0 | I76: =H76*(Annahmen!$B$97+Annahmen!$D$89*Annahmen!$B$98) -> 0 | J76: =IF($A76>=Annahmen!$D$82,Annahmen!$D$90,0) -> 0 | K76: =J76*(Annahmen!$B$99+Annahmen!$B$91*Annahmen!$B$102) -> 0 | L76: =IF($A76>=Annahmen!$D$82,Annahmen!$D$92,0) -> 0 | M76: =L76*Annahmen!$B$103 -> 0 | N76: =IF($A76>=Annahmen!$D$82,Annahmen!$D$93,0) -> 0 | O76: =N76*Annahmen!$B$104 -> 0 | P76: =IF($A76>=Annahmen!$D$82,Annahmen!$D$94,0) -> 0 | Q76: =P76*Annahmen!$B$105 -> 0 | R76: =IF($A76>=Annahmen!$D$82,Annahmen!$D$95,0) -> 0 | S76: =R76*Annahmen!$B$106 -> 0 | T76: =E76+G76+I76+K76+M76+O76+Q76+S76 -> 0 | U76: =C76*Annahmen!$B$51+F76*Annahmen!$D$87*Annahmen!$B$47+H76*(Annahmen!$B$45+Annahmen!$D$89*(Annahmen!$B$47-Annahmen!$B$45))+J76*Annahmen!$B$48+L76*Annahmen!$B$49+(N76+P76)*Annahmen!$B$50 -> 0 | V76: =SUMPRODUCT((((Annahmen!$C$145:$C$155="monatlich")*(Annahmen!$D$145:$D$155<=$A76))+((Annahmen!$C$145:$C$155="einmalig")*(Annahmen!$D$145:$D$155=$A76)))*Annahmen!$B$145:$B$155*Annahmen!$F$145:$F$155) -> 213.22757 | W76: =Annahmen!$D$135 -> 400 | X76: =C76+F76*Annahmen!$D$87+H76+J76+L76/Annahmen!$B$46+(N76+P76)/(Annahmen!$B$23/Annahmen!$B$24) -> 0 | Y76: =MAX(0,(X76-Annahmen!$B$140)/Annahmen!$B$141) -> 0 | Z76: =Y76*Annahmen!$B$137 -> 0 | AA76: =T76-U76-V76-W76-Z76 -> -613.22757 | AB76: =AA76 -> -613.22757 | AC76: =IF(AA76>0,1,0) -> 0 | AD76: =IF(AB76>=0,1,0) -> 0
A77: 2 | B77: 02/2027 | C77: =IF($A77>=Annahmen!$D$82,Annahmen!$D$83,0) -> 0 | D77: =C77*Annahmen!$D$84 -> 0 | E77: =(C77-D77)*Annahmen!$B$96 -> 0 | F77: =IF($A77>Annahmen!$B$86,INDEX($C$76:$C$99,$A77-Annahmen!$B$86)*Annahmen!$D$85,0) -> 0 | G77: =F77*(Annahmen!$D$87*(Annahmen!$B$97+Annahmen!$B$98)-Annahmen!$B$96*(1-Annahmen!$D$84)) -> 0 | H77: =IF($A77>=Annahmen!$D$82,Annahmen!$D$88,0) -> 0 | I77: =H77*(Annahmen!$B$97+Annahmen!$D$89*Annahmen!$B$98) -> 0 | J77: =IF($A77>=Annahmen!$D$82,Annahmen!$D$90,0) -> 0 | K77: =J77*(Annahmen!$B$99+Annahmen!$B$91*Annahmen!$B$102) -> 0 | L77: =IF($A77>=Annahmen!$D$82,Annahmen!$D$92,0) -> 0 | M77: =L77*Annahmen!$B$103 -> 0 | N77: =IF($A77>=Annahmen!$D$82,Annahmen!$D$93,0) -> 0 | O77: =N77*Annahmen!$B$104 -> 0 | P77: =IF($A77>=Annahmen!$D$82,Annahmen!$D$94,0) -> 0 | Q77: =P77*Annahmen!$B$105 -> 0 | R77: =IF($A77>=Annahmen!$D$82,Annahmen!$D$95,0) -> 0 | S77: =R77*Annahmen!$B$106 -> 0 | T77: =E77+G77+I77+K77+M77+O77+Q77+S77 -> 0 | U77: =C77*Annahmen!$B$51+F77*Annahmen!$D$87*Annahmen!$B$47+H77*(Annahmen!$B$45+Annahmen!$D$89*(Annahmen!$B$47-Annahmen!$B$45))+J77*Annahmen!$B$48+L77*Annahmen!$B$49+(N77+P77)*Annahmen!$B$50 -> 0 | V77: =SUMPRODUCT((((Annahmen!$C$145:$C$155="monatlich")*(Annahmen!$D$145:$D$155<=$A77))+((Annahmen!$C$145:$C$155="einmalig")*(Annahmen!$D$145:$D$155=$A77)))*Annahmen!$B$145:$B$155*Annahmen!$F$145:$F$155) -> 50.827571 | W77: =Annahmen!$D$135 -> 400 | X77: =C77+F77*Annahmen!$D$87+H77+J77+L77/Annahmen!$B$46+(N77+P77)/(Annahmen!$B$23/Annahmen!$B$24) -> 0 | Y77: =MAX(0,(X77-Annahmen!$B$140)/Annahmen!$B$141) -> 0 | Z77: =Y77*Annahmen!$B$137 -> 0 | AA77: =T77-U77-V77-W77-Z77 -> -450.82757 | AB77: =AB76+AA77 -> -1064.0551 | AC77: =IF(AA77>0,1,0) -> 0 | AD77: =IF(AB77>=0,1,0) -> 0
A78: 3 | B78: 03/2027 | C78: =IF($A78>=Annahmen!$D$82,Annahmen!$D$83,0) -> 1.5 | D78: =C78*Annahmen!$D$84 -> 0.3 | E78: =(C78-D78)*Annahmen!$B$96 -> 588 | F78: =IF($A78>Annahmen!$B$86,INDEX($C$76:$C$99,$A78-Annahmen!$B$86)*Annahmen!$D$85,0) -> 0 | G78: =F78*(Annahmen!$D$87*(Annahmen!$B$97+Annahmen!$B$98)-Annahmen!$B$96*(1-Annahmen!$D$84)) -> 0 | H78: =IF($A78>=Annahmen!$D$82,Annahmen!$D$88,0) -> 3 | I78: =H78*(Annahmen!$B$97+Annahmen!$D$89*Annahmen!$B$98) -> 1149 | J78: =IF($A78>=Annahmen!$D$82,Annahmen!$D$90,0) -> 2 | K78: =J78*(Annahmen!$B$99+Annahmen!$B$91*Annahmen!$B$102) -> 509.03226 | L78: =IF($A78>=Annahmen!$D$82,Annahmen!$D$92,0) -> 20 | M78: =L78*Annahmen!$B$103 -> 1780 | N78: =IF($A78>=Annahmen!$D$82,Annahmen!$D$93,0) -> 300 | O78: =N78*Annahmen!$B$104 -> 1800 | P78: =IF($A78>=Annahmen!$D$82,Annahmen!$D$94,0) -> 100 | Q78: =P78*Annahmen!$B$105 -> 400 | R78: =IF($A78>=Annahmen!$D$82,Annahmen!$D$95,0) -> 4 | S78: =R78*Annahmen!$B$106 -> 196 | T78: =E78+G78+I78+K78+M78+O78+Q78+S78 -> 6422.0323 | U78: =C78*Annahmen!$B$51+F78*Annahmen!$D$87*Annahmen!$B$47+H78*(Annahmen!$B$45+Annahmen!$D$89*(Annahmen!$B$47-Annahmen!$B$45))+J78*Annahmen!$B$48+L78*Annahmen!$B$49+(N78+P78)*Annahmen!$B$50 -> 82.835545 | V78: =SUMPRODUCT((((Annahmen!$C$145:$C$155="monatlich")*(Annahmen!$D$145:$D$155<=$A78))+((Annahmen!$C$145:$C$155="einmalig")*(Annahmen!$D$145:$D$155=$A78)))*Annahmen!$B$145:$B$155*Annahmen!$F$145:$F$155) -> 330.82757 | W78: =Annahmen!$D$135 -> 400 | X78: =C78+F78*Annahmen!$D$87+H78+J78+L78/Annahmen!$B$46+(N78+P78)/(Annahmen!$B$23/Annahmen!$B$24) -> 10.075 | Y78: =MAX(0,(X78-Annahmen!$B$140)/Annahmen!$B$141) -> 0.13833333 | Z78: =Y78*Annahmen!$B$137 -> 622.5 | AA78: =T78-U78-V78-W78-Z78 -> 4985.8691 | AB78: =AB77+AA78 -> 3921.814 | AC78: =IF(AA78>0,1,0) -> 1 | AD78: =IF(AB78>=0,1,0) -> 1
A79: 4 | B79: 04/2027 | C79: =IF($A79>=Annahmen!$D$82,Annahmen!$D$83,0) -> 1.5 | D79: =C79*Annahmen!$D$84 -> 0.3 | E79: =(C79-D79)*Annahmen!$B$96 -> 588 | F79: =IF($A79>Annahmen!$B$86,INDEX($C$76:$C$99,$A79-Annahmen!$B$86)*Annahmen!$D$85,0) -> 0 | G79: =F79*(Annahmen!$D$87*(Annahmen!$B$97+Annahmen!$B$98)-Annahmen!$B$96*(1-Annahmen!$D$84)) -> 0 | H79: =IF($A79>=Annahmen!$D$82,Annahmen!$D$88,0) -> 3 | I79: =H79*(Annahmen!$B$97+Annahmen!$D$89*Annahmen!$B$98) -> 1149 | J79: =IF($A79>=Annahmen!$D$82,Annahmen!$D$90,0) -> 2 | K79: =J79*(Annahmen!$B$99+Annahmen!$B$91*Annahmen!$B$102) -> 509.03226 | L79: =IF($A79>=Annahmen!$D$82,Annahmen!$D$92,0) -> 20 | M79: =L79*Annahmen!$B$103 -> 1780 | N79: =IF($A79>=Annahmen!$D$82,Annahmen!$D$93,0) -> 300 | O79: =N79*Annahmen!$B$104 -> 1800 | P79: =IF($A79>=Annahmen!$D$82,Annahmen!$D$94,0) -> 100 | Q79: =P79*Annahmen!$B$105 -> 400 | R79: =IF($A79>=Annahmen!$D$82,Annahmen!$D$95,0) -> 4 | S79: =R79*Annahmen!$B$106 -> 196 | T79: =E79+G79+I79+K79+M79+O79+Q79+S79 -> 6422.0323 | U79: =C79*Annahmen!$B$51+F79*Annahmen!$D$87*Annahmen!$B$47+H79*(Annahmen!$B$45+Annahmen!$D$89*(Annahmen!$B$47-Annahmen!$B$45))+J79*Annahmen!$B$48+L79*Annahmen!$B$49+(N79+P79)*Annahmen!$B$50 -> 82.835545 | V79: =SUMPRODUCT((((Annahmen!$C$145:$C$155="monatlich")*(Annahmen!$D$145:$D$155<=$A79))+((Annahmen!$C$145:$C$155="einmalig")*(Annahmen!$D$145:$D$155=$A79)))*Annahmen!$B$145:$B$155*Annahmen!$F$145:$F$155) -> 50.827571 | W79: =Annahmen!$D$135 -> 400 | X79: =C79+F79*Annahmen!$D$87+H79+J79+L79/Annahmen!$B$46+(N79+P79)/(Annahmen!$B$23/Annahmen!$B$24) -> 10.075 | Y79: =MAX(0,(X79-Annahmen!$B$140)/Annahmen!$B$141) -> 0.13833333 | Z79: =Y79*Annahmen!$B$137 -> 622.5 | AA79: =T79-U79-V79-W79-Z79 -> 5265.8691 | AB79: =AB78+AA79 -> 9187.6831 | AC79: =IF(AA79>0,1,0) -> 1 | AD79: =IF(AB79>=0,1,0) -> 1
A80: 5 | B80: 05/2027 | C80: =IF($A80>=Annahmen!$D$82,Annahmen!$D$83,0) -> 1.5 | D80: =C80*Annahmen!$D$84 -> 0.3 | E80: =(C80-D80)*Annahmen!$B$96 -> 588 | F80: =IF($A80>Annahmen!$B$86,INDEX($C$76:$C$99,$A80-Annahmen!$B$86)*Annahmen!$D$85,0) -> 0 | G80: =F80*(Annahmen!$D$87*(Annahmen!$B$97+Annahmen!$B$98)-Annahmen!$B$96*(1-Annahmen!$D$84)) -> 0 | H80: =IF($A80>=Annahmen!$D$82,Annahmen!$D$88,0) -> 3 | I80: =H80*(Annahmen!$B$97+Annahmen!$D$89*Annahmen!$B$98) -> 1149 | J80: =IF($A80>=Annahmen!$D$82,Annahmen!$D$90,0) -> 2 | K80: =J80*(Annahmen!$B$99+Annahmen!$B$91*Annahmen!$B$102) -> 509.03226 | L80: =IF($A80>=Annahmen!$D$82,Annahmen!$D$92,0) -> 20 | M80: =L80*Annahmen!$B$103 -> 1780 | N80: =IF($A80>=Annahmen!$D$82,Annahmen!$D$93,0) -> 300 | O80: =N80*Annahmen!$B$104 -> 1800 | P80: =IF($A80>=Annahmen!$D$82,Annahmen!$D$94,0) -> 100 | Q80: =P80*Annahmen!$B$105 -> 400 | R80: =IF($A80>=Annahmen!$D$82,Annahmen!$D$95,0) -> 4 | S80: =R80*Annahmen!$B$106 -> 196 | T80: =E80+G80+I80+K80+M80+O80+Q80+S80 -> 6422.0323 | U80: =C80*Annahmen!$B$51+F80*Annahmen!$D$87*Annahmen!$B$47+H80*(Annahmen!$B$45+Annahmen!$D$89*(Annahmen!$B$47-Annahmen!$B$45))+J80*Annahmen!$B$48+L80*Annahmen!$B$49+(N80+P80)*Annahmen!$B$50 -> 82.835545 | V80: =SUMPRODUCT((((Annahmen!$C$145:$C$155="monatlich")*(Annahmen!$D$145:$D$155<=$A80))+((Annahmen!$C$145:$C$155="einmalig")*(Annahmen!$D$145:$D$155=$A80)))*Annahmen!$B$145:$B$155*Annahmen!$F$145:$F$155) -> 610.82757 | W80: =Annahmen!$D$135 -> 400 | X80: =C80+F80*Annahmen!$D$87+H80+J80+L80/Annahmen!$B$46+(N80+P80)/(Annahmen!$B$23/Annahmen!$B$24) -> 10.075 | Y80: =MAX(0,(X80-Annahmen!$B$140)/Annahmen!$B$141) -> 0.13833333 | Z80: =Y80*Annahmen!$B$137 -> 622.5 | AA80: =T80-U80-V80-W80-Z80 -> 4705.8691 | AB80: =AB79+AA80 -> 13893.552 | AC80: =IF(AA80>0,1,0) -> 1 | AD80: =IF(AB80>=0,1,0) -> 1
A81: 6 | B81: 06/2027 | C81: =IF($A81>=Annahmen!$D$82,Annahmen!$D$83,0) -> 1.5 | D81: =C81*Annahmen!$D$84 -> 0.3 | E81: =(C81-D81)*Annahmen!$B$96 -> 588 | F81: =IF($A81>Annahmen!$B$86,INDEX($C$76:$C$99,$A81-Annahmen!$B$86)*Annahmen!$D$85,0) -> 0.75 | G81: =F81*(Annahmen!$D$87*(Annahmen!$B$97+Annahmen!$B$98)-Annahmen!$B$96*(1-Annahmen!$D$84)) -> 2940 | H81: =IF($A81>=Annahmen!$D$82,Annahmen!$D$88,0) -> 3 | I81: =H81*(Annahmen!$B$97+Annahmen!$D$89*Annahmen!$B$98) -> 1149 | J81: =IF($A81>=Annahmen!$D$82,Annahmen!$D$90,0) -> 2 | K81: =J81*(Annahmen!$B$99+Annahmen!$B$91*Annahmen!$B$102) -> 509.03226 | L81: =IF($A81>=Annahmen!$D$82,Annahmen!$D$92,0) -> 20 | M81: =L81*Annahmen!$B$103 -> 1780 | N81: =IF($A81>=Annahmen!$D$82,Annahmen!$D$93,0) -> 300 | O81: =N81*Annahmen!$B$104 -> 1800 | P81: =IF($A81>=Annahmen!$D$82,Annahmen!$D$94,0) -> 100 | Q81: =P81*Annahmen!$B$105 -> 400 | R81: =IF($A81>=Annahmen!$D$82,Annahmen!$D$95,0) -> 4 | S81: =R81*Annahmen!$B$106 -> 196 | T81: =E81+G81+I81+K81+M81+O81+Q81+S81 -> 9362.0323 | U81: =C81*Annahmen!$B$51+F81*Annahmen!$D$87*Annahmen!$B$47+H81*(Annahmen!$B$45+Annahmen!$D$89*(Annahmen!$B$47-Annahmen!$B$45))+J81*Annahmen!$B$48+L81*Annahmen!$B$49+(N81+P81)*Annahmen!$B$50 -> 134.866 | V81: =SUMPRODUCT((((Annahmen!$C$145:$C$155="monatlich")*(Annahmen!$D$145:$D$155<=$A81))+((Annahmen!$C$145:$C$155="einmalig")*(Annahmen!$D$145:$D$155=$A81)))*Annahmen!$B$145:$B$155*Annahmen!$F$145:$F$155) -> 50.827571 | W81: =Annahmen!$D$135 -> 400 | X81: =C81+F81*Annahmen!$D$87+H81+J81+L81/Annahmen!$B$46+(N81+P81)/(Annahmen!$B$23/Annahmen!$B$24) -> 16.075 | Y81: =MAX(0,(X81-Annahmen!$B$140)/Annahmen!$B$141) -> 0.53833333 | Z81: =Y81*Annahmen!$B$137 -> 2422.5 | AA81: =T81-U81-V81-W81-Z81 -> 6353.8387 | AB81: =AB80+AA81 -> 20247.391 | AC81: =IF(AA81>0,1,0) -> 1 | AD81: =IF(AB81>=0,1,0) -> 1
A82: 7 | B82: 07/2027 | C82: =IF($A82>=Annahmen!$D$82,Annahmen!$D$83,0) -> 1.5 | D82: =C82*Annahmen!$D$84 -> 0.3 | E82: =(C82-D82)*Annahmen!$B$96 -> 588 | F82: =IF($A82>Annahmen!$B$86,INDEX($C$76:$C$99,$A82-Annahmen!$B$86)*Annahmen!$D$85,0) -> 0.75 | G82: =F82*(Annahmen!$D$87*(Annahmen!$B$97+Annahmen!$B$98)-Annahmen!$B$96*(1-Annahmen!$D$84)) -> 2940 | H82: =IF($A82>=Annahmen!$D$82,Annahmen!$D$88,0) -> 3 | I82: =H82*(Annahmen!$B$97+Annahmen!$D$89*Annahmen!$B$98) -> 1149 | J82: =IF($A82>=Annahmen!$D$82,Annahmen!$D$90,0) -> 2 | K82: =J82*(Annahmen!$B$99+Annahmen!$B$91*Annahmen!$B$102) -> 509.03226 | L82: =IF($A82>=Annahmen!$D$82,Annahmen!$D$92,0) -> 20 | M82: =L82*Annahmen!$B$103 -> 1780 | N82: =IF($A82>=Annahmen!$D$82,Annahmen!$D$93,0) -> 300 | O82: =N82*Annahmen!$B$104 -> 1800 | P82: =IF($A82>=Annahmen!$D$82,Annahmen!$D$94,0) -> 100 | Q82: =P82*Annahmen!$B$105 -> 400 | R82: =IF($A82>=Annahmen!$D$82,Annahmen!$D$95,0) -> 4 | S82: =R82*Annahmen!$B$106 -> 196 | T82: =E82+G82+I82+K82+M82+O82+Q82+S82 -> 9362.0323 | U82: =C82*Annahmen!$B$51+F82*Annahmen!$D$87*Annahmen!$B$47+H82*(Annahmen!$B$45+Annahmen!$D$89*(Annahmen!$B$47-Annahmen!$B$45))+J82*Annahmen!$B$48+L82*Annahmen!$B$49+(N82+P82)*Annahmen!$B$50 -> 134.866 | V82: =SUMPRODUCT((((Annahmen!$C$145:$C$155="monatlich")*(Annahmen!$D$145:$D$155<=$A82))+((Annahmen!$C$145:$C$155="einmalig")*(Annahmen!$D$145:$D$155=$A82)))*Annahmen!$B$145:$B$155*Annahmen!$F$145:$F$155) -> 50.827571 | W82: =Annahmen!$D$135 -> 400 | X82: =C82+F82*Annahmen!$D$87+H82+J82+L82/Annahmen!$B$46+(N82+P82)/(Annahmen!$B$23/Annahmen!$B$24) -> 16.075 | Y82: =MAX(0,(X82-Annahmen!$B$140)/Annahmen!$B$141) -> 0.53833333 | Z82: =Y82*Annahmen!$B$137 -> 2422.5 | AA82: =T82-U82-V82-W82-Z82 -> 6353.8387 | AB82: =AB81+AA82 -> 26601.23 | AC82: =IF(AA82>0,1,0) -> 1 | AD82: =IF(AB82>=0,1,0) -> 1
A83: 8 | B83: 08/2027 | C83: =IF($A83>=Annahmen!$D$82,Annahmen!$D$83,0) -> 1.5 | D83: =C83*Annahmen!$D$84 -> 0.3 | E83: =(C83-D83)*Annahmen!$B$96 -> 588 | F83: =IF($A83>Annahmen!$B$86,INDEX($C$76:$C$99,$A83-Annahmen!$B$86)*Annahmen!$D$85,0) -> 0.75 | G83: =F83*(Annahmen!$D$87*(Annahmen!$B$97+Annahmen!$B$98)-Annahmen!$B$96*(1-Annahmen!$D$84)) -> 2940 | H83: =IF($A83>=Annahmen!$D$82,Annahmen!$D$88,0) -> 3 | I83: =H83*(Annahmen!$B$97+Annahmen!$D$89*Annahmen!$B$98) -> 1149 | J83: =IF($A83>=Annahmen!$D$82,Annahmen!$D$90,0) -> 2 | K83: =J83*(Annahmen!$B$99+Annahmen!$B$91*Annahmen!$B$102) -> 509.03226 | L83: =IF($A83>=Annahmen!$D$82,Annahmen!$D$92,0) -> 20 | M83: =L83*Annahmen!$B$103 -> 1780 | N83: =IF($A83>=Annahmen!$D$82,Annahmen!$D$93,0) -> 300 | O83: =N83*Annahmen!$B$104 -> 1800 | P83: =IF($A83>=Annahmen!$D$82,Annahmen!$D$94,0) -> 100 | Q83: =P83*Annahmen!$B$105 -> 400 | R83: =IF($A83>=Annahmen!$D$82,Annahmen!$D$95,0) -> 4 | S83: =R83*Annahmen!$B$106 -> 196 | T83: =E83+G83+I83+K83+M83+O83+Q83+S83 -> 9362.0323 | U83: =C83*Annahmen!$B$51+F83*Annahmen!$D$87*Annahmen!$B$47+H83*(Annahmen!$B$45+Annahmen!$D$89*(Annahmen!$B$47-Annahmen!$B$45))+J83*Annahmen!$B$48+L83*Annahmen!$B$49+(N83+P83)*Annahmen!$B$50 -> 134.866 | V83: =SUMPRODUCT((((Annahmen!$C$145:$C$155="monatlich")*(Annahmen!$D$145:$D$155<=$A83))+((Annahmen!$C$145:$C$155="einmalig")*(Annahmen!$D$145:$D$155=$A83)))*Annahmen!$B$145:$B$155*Annahmen!$F$145:$F$155) -> 50.827571 | W83: =Annahmen!$D$135 -> 400 | X83: =C83+F83*Annahmen!$D$87+H83+J83+L83/Annahmen!$B$46+(N83+P83)/(Annahmen!$B$23/Annahmen!$B$24) -> 16.075 | Y83: =MAX(0,(X83-Annahmen!$B$140)/Annahmen!$B$141) -> 0.53833333 | Z83: =Y83*Annahmen!$B$137 -> 2422.5 | AA83: =T83-U83-V83-W83-Z83 -> 6353.8387 | AB83: =AB82+AA83 -> 32955.068 | AC83: =IF(AA83>0,1,0) -> 1 | AD83: =IF(AB83>=0,1,0) -> 1
A84: 9 | B84: 09/2027 | C84: =IF($A84>=Annahmen!$D$82,Annahmen!$D$83,0) -> 1.5 | D84: =C84*Annahmen!$D$84 -> 0.3 | E84: =(C84-D84)*Annahmen!$B$96 -> 588 | F84: =IF($A84>Annahmen!$B$86,INDEX($C$76:$C$99,$A84-Annahmen!$B$86)*Annahmen!$D$85,0) -> 0.75 | G84: =F84*(Annahmen!$D$87*(Annahmen!$B$97+Annahmen!$B$98)-Annahmen!$B$96*(1-Annahmen!$D$84)) -> 2940 | H84: =IF($A84>=Annahmen!$D$82,Annahmen!$D$88,0) -> 3 | I84: =H84*(Annahmen!$B$97+Annahmen!$D$89*Annahmen!$B$98) -> 1149 | J84: =IF($A84>=Annahmen!$D$82,Annahmen!$D$90,0) -> 2 | K84: =J84*(Annahmen!$B$99+Annahmen!$B$91*Annahmen!$B$102) -> 509.03226 | L84: =IF($A84>=Annahmen!$D$82,Annahmen!$D$92,0) -> 20 | M84: =L84*Annahmen!$B$103 -> 1780 | N84: =IF($A84>=Annahmen!$D$82,Annahmen!$D$93,0) -> 300 | O84: =N84*Annahmen!$B$104 -> 1800 | P84: =IF($A84>=Annahmen!$D$82,Annahmen!$D$94,0) -> 100 | Q84: =P84*Annahmen!$B$105 -> 400 | R84: =IF($A84>=Annahmen!$D$82,Annahmen!$D$95,0) -> 4 | S84: =R84*Annahmen!$B$106 -> 196 | T84: =E84+G84+I84+K84+M84+O84+Q84+S84 -> 9362.0323 | U84: =C84*Annahmen!$B$51+F84*Annahmen!$D$87*Annahmen!$B$47+H84*(Annahmen!$B$45+Annahmen!$D$89*(Annahmen!$B$47-Annahmen!$B$45))+J84*Annahmen!$B$48+L84*Annahmen!$B$49+(N84+P84)*Annahmen!$B$50 -> 134.866 | V84: =SUMPRODUCT((((Annahmen!$C$145:$C$155="monatlich")*(Annahmen!$D$145:$D$155<=$A84))+((Annahmen!$C$145:$C$155="einmalig")*(Annahmen!$D$145:$D$155=$A84)))*Annahmen!$B$145:$B$155*Annahmen!$F$145:$F$155) -> 50.827571 | W84: =Annahmen!$D$135 -> 400 | X84: =C84+F84*Annahmen!$D$87+H84+J84+L84/Annahmen!$B$46+(N84+P84)/(Annahmen!$B$23/Annahmen!$B$24) -> 16.075 | Y84: =MAX(0,(X84-Annahmen!$B$140)/Annahmen!$B$141) -> 0.53833333 | Z84: =Y84*Annahmen!$B$137 -> 2422.5 | AA84: =T84-U84-V84-W84-Z84 -> 6353.8387 | AB84: =AB83+AA84 -> 39308.907 | AC84: =IF(AA84>0,1,0) -> 1 | AD84: =IF(AB84>=0,1,0) -> 1
A85: 10 | B85: 10/2027 | C85: =IF($A85>=Annahmen!$D$82,Annahmen!$D$83,0) -> 1.5 | D85: =C85*Annahmen!$D$84 -> 0.3 | E85: =(C85-D85)*Annahmen!$B$96 -> 588 | F85: =IF($A85>Annahmen!$B$86,INDEX($C$76:$C$99,$A85-Annahmen!$B$86)*Annahmen!$D$85,0) -> 0.75 | G85: =F85*(Annahmen!$D$87*(Annahmen!$B$97+Annahmen!$B$98)-Annahmen!$B$96*(1-Annahmen!$D$84)) -> 2940 | H85: =IF($A85>=Annahmen!$D$82,Annahmen!$D$88,0) -> 3 | I85: =H85*(Annahmen!$B$97+Annahmen!$D$89*Annahmen!$B$98) -> 1149 | J85: =IF($A85>=Annahmen!$D$82,Annahmen!$D$90,0) -> 2 | K85: =J85*(Annahmen!$B$99+Annahmen!$B$91*Annahmen!$B$102) -> 509.03226 | L85: =IF($A85>=Annahmen!$D$82,Annahmen!$D$92,0) -> 20 | M85: =L85*Annahmen!$B$103 -> 1780 | N85: =IF($A85>=Annahmen!$D$82,Annahmen!$D$93,0) -> 300 | O85: =N85*Annahmen!$B$104 -> 1800 | P85: =IF($A85>=Annahmen!$D$82,Annahmen!$D$94,0) -> 100 | Q85: =P85*Annahmen!$B$105 -> 400 | R85: =IF($A85>=Annahmen!$D$82,Annahmen!$D$95,0) -> 4 | S85: =R85*Annahmen!$B$106 -> 196 | T85: =E85+G85+I85+K85+M85+O85+Q85+S85 -> 9362.0323 | U85: =C85*Annahmen!$B$51+F85*Annahmen!$D$87*Annahmen!$B$47+H85*(Annahmen!$B$45+Annahmen!$D$89*(Annahmen!$B$47-Annahmen!$B$45))+J85*Annahmen!$B$48+L85*Annahmen!$B$49+(N85+P85)*Annahmen!$B$50 -> 134.866 | V85: =SUMPRODUCT((((Annahmen!$C$145:$C$155="monatlich")*(Annahmen!$D$145:$D$155<=$A85))+((Annahmen!$C$145:$C$155="einmalig")*(Annahmen!$D$145:$D$155=$A85)))*Annahmen!$B$145:$B$155*Annahmen!$F$145:$F$155) -> 50.827571 | W85: =Annahmen!$D$135 -> 400 | X85: =C85+F85*Annahmen!$D$87+H85+J85+L85/Annahmen!$B$46+(N85+P85)/(Annahmen!$B$23/Annahmen!$B$24) -> 16.075 | Y85: =MAX(0,(X85-Annahmen!$B$140)/Annahmen!$B$141) -> 0.53833333 | Z85: =Y85*Annahmen!$B$137 -> 2422.5 | AA85: =T85-U85-V85-W85-Z85 -> 6353.8387 | AB85: =AB84+AA85 -> 45662.746 | AC85: =IF(AA85>0,1,0) -> 1 | AD85: =IF(AB85>=0,1,0) -> 1
A86: 11 | B86: 11/2027 | C86: =IF($A86>=Annahmen!$D$82,Annahmen!$D$83,0) -> 1.5 | D86: =C86*Annahmen!$D$84 -> 0.3 | E86: =(C86-D86)*Annahmen!$B$96 -> 588 | F86: =IF($A86>Annahmen!$B$86,INDEX($C$76:$C$99,$A86-Annahmen!$B$86)*Annahmen!$D$85,0) -> 0.75 | G86: =F86*(Annahmen!$D$87*(Annahmen!$B$97+Annahmen!$B$98)-Annahmen!$B$96*(1-Annahmen!$D$84)) -> 2940 | H86: =IF($A86>=Annahmen!$D$82,Annahmen!$D$88,0) -> 3 | I86: =H86*(Annahmen!$B$97+Annahmen!$D$89*Annahmen!$B$98) -> 1149 | J86: =IF($A86>=Annahmen!$D$82,Annahmen!$D$90,0) -> 2 | K86: =J86*(Annahmen!$B$99+Annahmen!$B$91*Annahmen!$B$102) -> 509.03226 | L86: =IF($A86>=Annahmen!$D$82,Annahmen!$D$92,0) -> 20 | M86: =L86*Annahmen!$B$103 -> 1780 | N86: =IF($A86>=Annahmen!$D$82,Annahmen!$D$93,0) -> 300 | O86: =N86*Annahmen!$B$104 -> 1800 | P86: =IF($A86>=Annahmen!$D$82,Annahmen!$D$94,0) -> 100 | Q86: =P86*Annahmen!$B$105 -> 400 | R86: =IF($A86>=Annahmen!$D$82,Annahmen!$D$95,0) -> 4 | S86: =R86*Annahmen!$B$106 -> 196 | T86: =E86+G86+I86+K86+M86+O86+Q86+S86 -> 9362.0323 | U86: =C86*Annahmen!$B$51+F86*Annahmen!$D$87*Annahmen!$B$47+H86*(Annahmen!$B$45+Annahmen!$D$89*(Annahmen!$B$47-Annahmen!$B$45))+J86*Annahmen!$B$48+L86*Annahmen!$B$49+(N86+P86)*Annahmen!$B$50 -> 134.866 | V86: =SUMPRODUCT((((Annahmen!$C$145:$C$155="monatlich")*(Annahmen!$D$145:$D$155<=$A86))+((Annahmen!$C$145:$C$155="einmalig")*(Annahmen!$D$145:$D$155=$A86)))*Annahmen!$B$145:$B$155*Annahmen!$F$145:$F$155) -> 50.827571 | W86: =Annahmen!$D$135 -> 400 | X86: =C86+F86*Annahmen!$D$87+H86+J86+L86/Annahmen!$B$46+(N86+P86)/(Annahmen!$B$23/Annahmen!$B$24) -> 16.075 | Y86: =MAX(0,(X86-Annahmen!$B$140)/Annahmen!$B$141) -> 0.53833333 | Z86: =Y86*Annahmen!$B$137 -> 2422.5 | AA86: =T86-U86-V86-W86-Z86 -> 6353.8387 | AB86: =AB85+AA86 -> 52016.584 | AC86: =IF(AA86>0,1,0) -> 1 | AD86: =IF(AB86>=0,1,0) -> 1
A87: 12 | B87: 12/2027 | C87: =IF($A87>=Annahmen!$D$82,Annahmen!$D$83,0) -> 1.5 | D87: =C87*Annahmen!$D$84 -> 0.3 | E87: =(C87-D87)*Annahmen!$B$96 -> 588 | F87: =IF($A87>Annahmen!$B$86,INDEX($C$76:$C$99,$A87-Annahmen!$B$86)*Annahmen!$D$85,0) -> 0.75 | G87: =F87*(Annahmen!$D$87*(Annahmen!$B$97+Annahmen!$B$98)-Annahmen!$B$96*(1-Annahmen!$D$84)) -> 2940 | H87: =IF($A87>=Annahmen!$D$82,Annahmen!$D$88,0) -> 3 | I87: =H87*(Annahmen!$B$97+Annahmen!$D$89*Annahmen!$B$98) -> 1149 | J87: =IF($A87>=Annahmen!$D$82,Annahmen!$D$90,0) -> 2 | K87: =J87*(Annahmen!$B$99+Annahmen!$B$91*Annahmen!$B$102) -> 509.03226 | L87: =IF($A87>=Annahmen!$D$82,Annahmen!$D$92,0) -> 20 | M87: =L87*Annahmen!$B$103 -> 1780 | N87: =IF($A87>=Annahmen!$D$82,Annahmen!$D$93,0) -> 300 | O87: =N87*Annahmen!$B$104 -> 1800 | P87: =IF($A87>=Annahmen!$D$82,Annahmen!$D$94,0) -> 100 | Q87: =P87*Annahmen!$B$105 -> 400 | R87: =IF($A87>=Annahmen!$D$82,Annahmen!$D$95,0) -> 4 | S87: =R87*Annahmen!$B$106 -> 196 | T87: =E87+G87+I87+K87+M87+O87+Q87+S87 -> 9362.0323 | U87: =C87*Annahmen!$B$51+F87*Annahmen!$D$87*Annahmen!$B$47+H87*(Annahmen!$B$45+Annahmen!$D$89*(Annahmen!$B$47-Annahmen!$B$45))+J87*Annahmen!$B$48+L87*Annahmen!$B$49+(N87+P87)*Annahmen!$B$50 -> 134.866 | V87: =SUMPRODUCT((((Annahmen!$C$145:$C$155="monatlich")*(Annahmen!$D$145:$D$155<=$A87))+((Annahmen!$C$145:$C$155="einmalig")*(Annahmen!$D$145:$D$155=$A87)))*Annahmen!$B$145:$B$155*Annahmen!$F$145:$F$155) -> 50.827571 | W87: =Annahmen!$D$135 -> 400 | X87: =C87+F87*Annahmen!$D$87+H87+J87+L87/Annahmen!$B$46+(N87+P87)/(Annahmen!$B$23/Annahmen!$B$24) -> 16.075 | Y87: =MAX(0,(X87-Annahmen!$B$140)/Annahmen!$B$141) -> 0.53833333 | Z87: =Y87*Annahmen!$B$137 -> 2422.5 | AA87: =T87-U87-V87-W87-Z87 -> 6353.8387 | AB87: =AB86+AA87 -> 58370.423 | AC87: =IF(AA87>0,1,0) -> 1 | AD87: =IF(AB87>=0,1,0) -> 1
A88: 13 | B88: 01/2028 | C88: =IF($A88>=Annahmen!$D$82,Annahmen!$D$83,0) -> 1.5 | D88: =C88*Annahmen!$D$84 -> 0.3 | E88: =(C88-D88)*Annahmen!$B$96 -> 588 | F88: =IF($A88>Annahmen!$B$86,INDEX($C$76:$C$99,$A88-Annahmen!$B$86)*Annahmen!$D$85,0) -> 0.75 | G88: =F88*(Annahmen!$D$87*(Annahmen!$B$97+Annahmen!$B$98)-Annahmen!$B$96*(1-Annahmen!$D$84)) -> 2940 | H88: =IF($A88>=Annahmen!$D$82,Annahmen!$D$88,0) -> 3 | I88: =H88*(Annahmen!$B$97+Annahmen!$D$89*Annahmen!$B$98) -> 1149 | J88: =IF($A88>=Annahmen!$D$82,Annahmen!$D$90,0) -> 2 | K88: =J88*(Annahmen!$B$99+Annahmen!$B$91*Annahmen!$B$102) -> 509.03226 | L88: =IF($A88>=Annahmen!$D$82,Annahmen!$D$92,0) -> 20 | M88: =L88*Annahmen!$B$103 -> 1780 | N88: =IF($A88>=Annahmen!$D$82,Annahmen!$D$93,0) -> 300 | O88: =N88*Annahmen!$B$104 -> 1800 | P88: =IF($A88>=Annahmen!$D$82,Annahmen!$D$94,0) -> 100 | Q88: =P88*Annahmen!$B$105 -> 400 | R88: =IF($A88>=Annahmen!$D$82,Annahmen!$D$95,0) -> 4 | S88: =R88*Annahmen!$B$106 -> 196 | T88: =E88+G88+I88+K88+M88+O88+Q88+S88 -> 9362.0323 | U88: =C88*Annahmen!$B$51+F88*Annahmen!$D$87*Annahmen!$B$47+H88*(Annahmen!$B$45+Annahmen!$D$89*(Annahmen!$B$47-Annahmen!$B$45))+J88*Annahmen!$B$48+L88*Annahmen!$B$49+(N88+P88)*Annahmen!$B$50 -> 134.866 | V88: =SUMPRODUCT((((Annahmen!$C$145:$C$155="monatlich")*(Annahmen!$D$145:$D$155<=$A88))+((Annahmen!$C$145:$C$155="einmalig")*(Annahmen!$D$145:$D$155=$A88)))*Annahmen!$B$145:$B$155*Annahmen!$F$145:$F$155) -> 50.827571 | W88: =Annahmen!$D$135 -> 400 | X88: =C88+F88*Annahmen!$D$87+H88+J88+L88/Annahmen!$B$46+(N88+P88)/(Annahmen!$B$23/Annahmen!$B$24) -> 16.075 | Y88: =MAX(0,(X88-Annahmen!$B$140)/Annahmen!$B$141) -> 0.53833333 | Z88: =Y88*Annahmen!$B$137 -> 2422.5 | AA88: =T88-U88-V88-W88-Z88 -> 6353.8387 | AB88: =AB87+AA88 -> 64724.262 | AC88: =IF(AA88>0,1,0) -> 1 | AD88: =IF(AB88>=0,1,0) -> 1
... A99: 24 | B99: 12/2028 | C99: =IF($A99>=Annahmen!$D$82,Annahmen!$D$83,0) -> 1.5 | D99: =C99*Annahmen!$D$84 -> 0.3 | E99: =(C99-D99)*Annahmen!$B$96 -> 588 | F99: =IF($A99>Annahmen!$B$86,INDEX($C$76:$C$99,$A99-Annahmen!$B$86)*Annahmen!$D$85,0) -> 0.75 | G99: =F99*(Annahmen!$D$87*(Annahmen!$B$97+Annahmen!$B$98)-Annahmen!$B$96*(1-Annahmen!$D$84)) -> 2940 | H99: =IF($A99>=Annahmen!$D$82,Annahmen!$D$88,0) -> 3 | I99: =H99*(Annahmen!$B$97+Annahmen!$D$89*Annahmen!$B$98) -> 1149 | J99: =IF($A99>=Annahmen!$D$82,Annahmen!$D$90,0) -> 2 | K99: =J99*(Annahmen!$B$99+Annahmen!$B$91*Annahmen!$B$102) -> 509.03226 | L99: =IF($A99>=Annahmen!$D$82,Annahmen!$D$92,0) -> 20 | M99: =L99*Annahmen!$B$103 -> 1780 | N99: =IF($A99>=Annahmen!$D$82,Annahmen!$D$93,0) -> 300 | O99: =N99*Annahmen!$B$104 -> 1800 | P99: =IF($A99>=Annahmen!$D$82,Annahmen!$D$94,0) -> 100 | Q99: =P99*Annahmen!$B$105 -> 400 | R99: =IF($A99>=Annahmen!$D$82,Annahmen!$D$95,0) -> 4 | S99: =R99*Annahmen!$B$106 -> 196 | T99: =E99+G99+I99+K99+M99+O99+Q99+S99 -> 9362.0323 | U99: =C99*Annahmen!$B$51+F99*Annahmen!$D$87*Annahmen!$B$47+H99*(Annahmen!$B$45+Annahmen!$D$89*(Annahmen!$B$47-Annahmen!$B$45))+J99*Annahmen!$B$48+L99*Annahmen!$B$49+(N99+P99)*Annahmen!$B$50 -> 134.866 | V99: =SUMPRODUCT((((Annahmen!$C$145:$C$155="monatlich")*(Annahmen!$D$145:$D$155<=$A99))+((Annahmen!$C$145:$C$155="einmalig")*(Annahmen!$D$145:$D$155=$A99)))*Annahmen!$B$145:$B$155*Annahmen!$F$145:$F$155) -> 50.827571 | W99: =Annahmen!$D$135 -> 400 | X99: =C99+F99*Annahmen!$D$87+H99+J99+L99/Annahmen!$B$46+(N99+P99)/(Annahmen!$B$23/Annahmen!$B$24) -> 16.075 | Y99: =MAX(0,(X99-Annahmen!$B$140)/Annahmen!$B$141) -> 0.53833333 | Z99: =Y99*Annahmen!$B$137 -> 2422.5 | AA99: =T99-U99-V99-W99-Z99 -> 6353.8387 | AB99: =AB98+AA99 -> 134616.49 | AC99: =IF(AA99>0,1,0) -> 1 | AD99: =IF(AB99>=0,1,0) -> 1

Sheet SOMNIO
A1: SOMNIO Publishing — 24 Monate ab 01/2027
A3: Kennzahl | B3: ="vorsichtig – "&Annahmen!$B$133 -> vorsichtig – teures Hobby | C3: ="mittel – "&Annahmen!$C$133 -> mittel – profitabler Nebenerwerb | D3: ="stark – "&Annahmen!$D$133 -> stark – skalierbares Business
A4: Break-even monatlich (erster Monat Ergebnis > 0) | B4: =IFERROR("Monat "&MATCH(1,W18:W41,0)&" ("&INDEX($B$18:$B$41,MATCH(1,W18:W41,0))&")","nicht in 24 M") -> nicht in 24 M | C4: =IFERROR("Monat "&MATCH(1,W47:W70,0)&" ("&INDEX($B$47:$B$70,MATCH(1,W47:W70,0))&")","nicht in 24 M") -> Monat 10 (10/2027) | D4: =IFERROR("Monat "&MATCH(1,W76:W99,0)&" ("&INDEX($B$76:$B$99,MATCH(1,W76:W99,0))&")","nicht in 24 M") -> Monat 7 (07/2027)
A5: Break-even kumuliert (erster Monat kum. ≥ 0) | B5: =IFERROR("Monat "&MATCH(1,X18:X41,0)&" ("&INDEX($B$18:$B$41,MATCH(1,X18:X41,0))&")","nicht in 24 M") -> nicht in 24 M | C5: =IFERROR("Monat "&MATCH(1,X47:X70,0)&" ("&INDEX($B$47:$B$70,MATCH(1,X47:X70,0))&")","nicht in 24 M") -> Monat 15 (03/2028) | D5: =IFERROR("Monat "&MATCH(1,X76:X99,0)&" ("&INDEX($B$76:$B$99,MATCH(1,X76:X99,0))&")","nicht in 24 M") -> Monat 8 (08/2027)
A6: Deckungsbeitrag je Verkauf / Titel
A7: Ertrag je E-Book-Verkauf | B7: =Annahmen!$B$116/(1+Annahmen!$B$9)*Annahmen!$B$129 -> 1.4670561
A8: Ertrag je Hörbuch-Verkauf | B8: =Annahmen!$B$117/(1+Annahmen!$B$9)*Annahmen!$B$130 -> 4.1070093
A9: Ertrag je zweisprachigem Verkauf | B9: =Annahmen!$B$118/(1+Annahmen!$B$9)*Annahmen!$B$129 -> 2.4483645
A10: DB je Autor·innen-Titel (Self-Publishing) | B10: =Annahmen!$B$127-Annahmen!$B$47 -> 381.32826
A12: Katalogproduktion (Text, Basis-Audio) trägt TÆLLA; SOMNIO verwertet dieselben Werke ohne Zusatzkosten. KI-Stimme kennzeichnen (TECHNIK §9, AI Act Art. 50).
A16: ="Szenario vorsichtig – "&Annahmen!$B$133 -> Szenario vorsichtig – teures Hobby
A17: Monat | B17: Datum | C17: Neue E-Books | D17: E-Books kum. | E17: Verkäufe E-Book | F17: Ertrag E-Book | G17: Neue Hörbücher | H17: Hörbücher kum. | I17: Verkäufe Hörbuch | J17: Ertrag Hörbuch | K17: Neue zweispr. | L17: Zweispr. kum. | M17: Verkäufe zweispr. | N17: Ertrag zweispr. | O17: Self-Pub Aufträge | P17: Self-Pub Umsatz | Q17: Umsatz gesamt | R17: Variable Kosten | S17: Fixkosten anteilig | T17: Marketing | U17: Ergebnis | V17: Ergebnis kumuliert | W17: BE monatl. | X17: BE kum.
A18: 1 | B18: 01/2027 | C18: =IF($A18>=Annahmen!$B$109,Annahmen!$B$110,0) -> 0 | D18: =C18 -> 0 | E18: =D18*Annahmen!$B$113 -> 0 | F18: =E18*Annahmen!$B$116/(1+Annahmen!$B$9)*Annahmen!$B$129 -> 0 | G18: =IF($A18>=Annahmen!$B$109,Annahmen!$B$111,0) -> 0 | H18: =G18 -> 0 | I18: =H18*Annahmen!$B$114 -> 0 | J18: =I18*Annahmen!$B$117/(1+Annahmen!$B$9)*Annahmen!$B$130 -> 0 | K18: =IF($A18>=Annahmen!$B$109,Annahmen!$B$112,0) -> 0 | L18: =K18 -> 0 | M18: =L18*Annahmen!$B$115 -> 0 | N18: =M18*Annahmen!$B$118/(1+Annahmen!$B$9)*Annahmen!$B$129 -> 0 | O18: =IF($A18>=Annahmen!$B$125,Annahmen!$B$126,0) -> 0 | P18: =O18*Annahmen!$B$127 -> 0 | Q18: =F18+J18+N18+P18 -> 0 | R18: =O18*Annahmen!$B$47+(C18+G18+K18)*Annahmen!$B$128 -> 0 | S18: =SUMPRODUCT((((Annahmen!$C$145:$C$155="monatlich")*(Annahmen!$D$145:$D$155<=$A18))+((Annahmen!$C$145:$C$155="einmalig")*(Annahmen!$D$145:$D$155=$A18)))*Annahmen!$B$145:$B$155*Annahmen!$G$145:$G$155) -> 109.56049 | T18: =IF($A18>=Annahmen!$B$109,Annahmen!$B$136,0) -> 0 | U18: =Q18-R18-S18-T18 -> -109.56049 | V18: =U18 -> -109.56049 | W18: =IF(U18>0,1,0) -> 0 | X18: =IF(V18>=0,1,0) -> 0
A19: 2 | B19: 02/2027 | C19: =IF($A19>=Annahmen!$B$109,Annahmen!$B$110,0) -> 0 | D19: =D18+C19 -> 0 | E19: =D19*Annahmen!$B$113 -> 0 | F19: =E19*Annahmen!$B$116/(1+Annahmen!$B$9)*Annahmen!$B$129 -> 0 | G19: =IF($A19>=Annahmen!$B$109,Annahmen!$B$111,0) -> 0 | H19: =H18+G19 -> 0 | I19: =H19*Annahmen!$B$114 -> 0 | J19: =I19*Annahmen!$B$117/(1+Annahmen!$B$9)*Annahmen!$B$130 -> 0 | K19: =IF($A19>=Annahmen!$B$109,Annahmen!$B$112,0) -> 0 | L19: =L18+K19 -> 0 | M19: =L19*Annahmen!$B$115 -> 0 | N19: =M19*Annahmen!$B$118/(1+Annahmen!$B$9)*Annahmen!$B$129 -> 0 | O19: =IF($A19>=Annahmen!$B$125,Annahmen!$B$126,0) -> 0 | P19: =O19*Annahmen!$B$127 -> 0 | Q19: =F19+J19+N19+P19 -> 0 | R19: =O19*Annahmen!$B$47+(C19+G19+K19)*Annahmen!$B$128 -> 0 | S19: =SUMPRODUCT((((Annahmen!$C$145:$C$155="monatlich")*(Annahmen!$D$145:$D$155<=$A19))+((Annahmen!$C$145:$C$155="einmalig")*(Annahmen!$D$145:$D$155=$A19)))*Annahmen!$B$145:$B$155*Annahmen!$G$145:$G$155) -> 28.360493 | T19: =IF($A19>=Annahmen!$B$109,Annahmen!$B$136,0) -> 0 | U19: =Q19-R19-S19-T19 -> -28.360493 | V19: =V18+U19 -> -137.92099 | W19: =IF(U19>0,1,0) -> 0 | X19: =IF(V19>=0,1,0) -> 0
A20: 3 | B20: 03/2027 | C20: =IF($A20>=Annahmen!$B$109,Annahmen!$B$110,0) -> 0 | D20: =D19+C20 -> 0 | E20: =D20*Annahmen!$B$113 -> 0 | F20: =E20*Annahmen!$B$116/(1+Annahmen!$B$9)*Annahmen!$B$129 -> 0 | G20: =IF($A20>=Annahmen!$B$109,Annahmen!$B$111,0) -> 0 | H20: =H19+G20 -> 0 | I20: =H20*Annahmen!$B$114 -> 0 | J20: =I20*Annahmen!$B$117/(1+Annahmen!$B$9)*Annahmen!$B$130 -> 0 | K20: =IF($A20>=Annahmen!$B$109,Annahmen!$B$112,0) -> 0 | L20: =L19+K20 -> 0 | M20: =L20*Annahmen!$B$115 -> 0 | N20: =M20*Annahmen!$B$118/(1+Annahmen!$B$9)*Annahmen!$B$129 -> 0 | O20: =IF($A20>=Annahmen!$B$125,Annahmen!$B$126,0) -> 0 | P20: =O20*Annahmen!$B$127 -> 0 | Q20: =F20+J20+N20+P20 -> 0 | R20: =O20*Annahmen!$B$47+(C20+G20+K20)*Annahmen!$B$128 -> 0 | S20: =SUMPRODUCT((((Annahmen!$C$145:$C$155="monatlich")*(Annahmen!$D$145:$D$155<=$A20))+((Annahmen!$C$145:$C$155="einmalig")*(Annahmen!$D$145:$D$155=$A20)))*Annahmen!$B$145:$B$155*Annahmen!$G$145:$G$155) -> 98.360493 | T20: =IF($A20>=Annahmen!$B$109,Annahmen!$B$136,0) -> 0 | U20: =Q20-R20-S20-T20 -> -98.360493 | V20: =V19+U20 -> -236.28148 | W20: =IF(U20>0,1,0) -> 0 | X20: =IF(V20>=0,1,0) -> 0
A21: 4 | B21: 04/2027 | C21: =IF($A21>=Annahmen!$B$109,Annahmen!$B$110,0) -> 0 | D21: =D20+C21 -> 0 | E21: =D21*Annahmen!$B$113 -> 0 | F21: =E21*Annahmen!$B$116/(1+Annahmen!$B$9)*Annahmen!$B$129 -> 0 | G21: =IF($A21>=Annahmen!$B$109,Annahmen!$B$111,0) -> 0 | H21: =H20+G21 -> 0 | I21: =H21*Annahmen!$B$114 -> 0 | J21: =I21*Annahmen!$B$117/(1+Annahmen!$B$9)*Annahmen!$B$130 -> 0 | K21: =IF($A21>=Annahmen!$B$109,Annahmen!$B$112,0) -> 0 | L21: =L20+K21 -> 0 | M21: =L21*Annahmen!$B$115 -> 0 | N21: =M21*Annahmen!$B$118/(1+Annahmen!$B$9)*Annahmen!$B$129 -> 0 | O21: =IF($A21>=Annahmen!$B$125,Annahmen!$B$126,0) -> 0 | P21: =O21*Annahmen!$B$127 -> 0 | Q21: =F21+J21+N21+P21 -> 0 | R21: =O21*Annahmen!$B$47+(C21+G21+K21)*Annahmen!$B$128 -> 0 | S21: =SUMPRODUCT((((Annahmen!$C$145:$C$155="monatlich")*(Annahmen!$D$145:$D$155<=$A21))+((Annahmen!$C$145:$C$155="einmalig")*(Annahmen!$D$145:$D$155=$A21)))*Annahmen!$B$145:$B$155*Annahmen!$G$145:$G$155) -> 28.360493 | T21: =IF($A21>=Annahmen!$B$109,Annahmen!$B$136,0) -> 0 | U21: =Q21-R21-S21-T21 -> -28.360493 | V21: =V20+U21 -> -264.64197 | W21: =IF(U21>0,1,0) -> 0 | X21: =IF(V21>=0,1,0) -> 0
A22: 5 | B22: 05/2027 | C22: =IF($A22>=Annahmen!$B$109,Annahmen!$B$110,0) -> 0 | D22: =D21+C22 -> 0 | E22: =D22*Annahmen!$B$113 -> 0 | F22: =E22*Annahmen!$B$116/(1+Annahmen!$B$9)*Annahmen!$B$129 -> 0 | G22: =IF($A22>=Annahmen!$B$109,Annahmen!$B$111,0) -> 0 | H22: =H21+G22 -> 0 | I22: =H22*Annahmen!$B$114 -> 0 | J22: =I22*Annahmen!$B$117/(1+Annahmen!$B$9)*Annahmen!$B$130 -> 0 | K22: =IF($A22>=Annahmen!$B$109,Annahmen!$B$112,0) -> 0 | L22: =L21+K22 -> 0 | M22: =L22*Annahmen!$B$115 -> 0 | N22: =M22*Annahmen!$B$118/(1+Annahmen!$B$9)*Annahmen!$B$129 -> 0 | O22: =IF($A22>=Annahmen!$B$125,Annahmen!$B$126,0) -> 0 | P22: =O22*Annahmen!$B$127 -> 0 | Q22: =F22+J22+N22+P22 -> 0 | R22: =O22*Annahmen!$B$47+(C22+G22+K22)*Annahmen!$B$128 -> 0 | S22: =SUMPRODUCT((((Annahmen!$C$145:$C$155="monatlich")*(Annahmen!$D$145:$D$155<=$A22))+((Annahmen!$C$145:$C$155="einmalig")*(Annahmen!$D$145:$D$155=$A22)))*Annahmen!$B$145:$B$155*Annahmen!$G$145:$G$155) -> 28.360493 | T22: =IF($A22>=Annahmen!$B$109,Annahmen!$B$136,0) -> 0 | U22: =Q22-R22-S22-T22 -> -28.360493 | V22: =V21+U22 -> -293.00247 | W22: =IF(U22>0,1,0) -> 0 | X22: =IF(V22>=0,1,0) -> 0
A23: 6 | B23: 06/2027 | C23: =IF($A23>=Annahmen!$B$109,Annahmen!$B$110,0) -> 2 | D23: =D22+C23 -> 2 | E23: =D23*Annahmen!$B$113 -> 0.4 | F23: =E23*Annahmen!$B$116/(1+Annahmen!$B$9)*Annahmen!$B$129 -> 0.58682243 | G23: =IF($A23>=Annahmen!$B$109,Annahmen!$B$111,0) -> 1 | H23: =H22+G23 -> 1 | I23: =H23*Annahmen!$B$114 -> 0.1 | J23: =I23*Annahmen!$B$117/(1+Annahmen!$B$9)*Annahmen!$B$130 -> 0.41070093 | K23: =IF($A23>=Annahmen!$B$109,Annahmen!$B$112,0) -> 1 | L23: =L22+K23 -> 1 | M23: =L23*Annahmen!$B$115 -> 0.2 | N23: =M23*Annahmen!$B$118/(1+Annahmen!$B$9)*Annahmen!$B$129 -> 0.4896729 | O23: =IF($A23>=Annahmen!$B$125,Annahmen!$B$126,0) -> 0 | P23: =O23*Annahmen!$B$127 -> 0 | Q23: =F23+J23+N23+P23 -> 1.4871963 | R23: =O23*Annahmen!$B$47+(C23+G23+K23)*Annahmen!$B$128 -> 0 | S23: =SUMPRODUCT((((Annahmen!$C$145:$C$155="monatlich")*(Annahmen!$D$145:$D$155<=$A23))+((Annahmen!$C$145:$C$155="einmalig")*(Annahmen!$D$145:$D$155=$A23)))*Annahmen!$B$145:$B$155*Annahmen!$G$145:$G$155) -> 28.360493 | T23: =IF($A23>=Annahmen!$B$109,Annahmen!$B$136,0) -> 0 | U23: =Q23-R23-S23-T23 -> -26.873297 | V23: =V22+U23 -> -319.87576 | W23: =IF(U23>0,1,0) -> 0 | X23: =IF(V23>=0,1,0) -> 0
A24: 7 | B24: 07/2027 | C24: =IF($A24>=Annahmen!$B$109,Annahmen!$B$110,0) -> 2 | D24: =D23+C24 -> 4 | E24: =D24*Annahmen!$B$113 -> 0.8 | F24: =E24*Annahmen!$B$116/(1+Annahmen!$B$9)*Annahmen!$B$129 -> 1.1736449 | G24: =IF($A24>=Annahmen!$B$109,Annahmen!$B$111,0) -> 1 | H24: =H23+G24 -> 2 | I24: =H24*Annahmen!$B$114 -> 0.2 | J24: =I24*Annahmen!$B$117/(1+Annahmen!$B$9)*Annahmen!$B$130 -> 0.82140187 | K24: =IF($A24>=Annahmen!$B$109,Annahmen!$B$112,0) -> 1 | L24: =L23+K24 -> 2 | M24: =L24*Annahmen!$B$115 -> 0.4 | N24: =M24*Annahmen!$B$118/(1+Annahmen!$B$9)*Annahmen!$B$129 -> 0.97934579 | O24: =IF($A24>=Annahmen!$B$125,Annahmen!$B$126,0) -> 0 | P24: =O24*Annahmen!$B$127 -> 0 | Q24: =F24+J24+N24+P24 -> 2.9743925 | R24: =O24*Annahmen!$B$47+(C24+G24+K24)*Annahmen!$B$128 -> 0 | S24: =SUMPRODUCT((((Annahmen!$C$145:$C$155="monatlich")*(Annahmen!$D$145:$D$155<=$A24))+((Annahmen!$C$145:$C$155="einmalig")*(Annahmen!$D$145:$D$155=$A24)))*Annahmen!$B$145:$B$155*Annahmen!$G$145:$G$155) -> 28.360493 | T24: =IF($A24>=Annahmen!$B$109,Annahmen!$B$136,0) -> 0 | U24: =Q24-R24-S24-T24 -> -25.386101 | V24: =V23+U24 -> -345.26186 | W24: =IF(U24>0,1,0) -> 0 | X24: =IF(V24>=0,1,0) -> 0
A25: 8 | B25: 08/2027 | C25: =IF($A25>=Annahmen!$B$109,Annahmen!$B$110,0) -> 2 | D25: =D24+C25 -> 6 | E25: =D25*Annahmen!$B$113 -> 1.2 | F25: =E25*Annahmen!$B$116/(1+Annahmen!$B$9)*Annahmen!$B$129 -> 1.7604673 | G25: =IF($A25>=Annahmen!$B$109,Annahmen!$B$111,0) -> 1 | H25: =H24+G25 -> 3 | I25: =H25*Annahmen!$B$114 -> 0.3 | J25: =I25*Annahmen!$B$117/(1+Annahmen!$B$9)*Annahmen!$B$130 -> 1.2321028 | K25: =IF($A25>=Annahmen!$B$109,Annahmen!$B$112,0) -> 1 | L25: =L24+K25 -> 3 | M25: =L25*Annahmen!$B$115 -> 0.6 | N25: =M25*Annahmen!$B$118/(1+Annahmen!$B$9)*Annahmen!$B$129 -> 1.4690187 | O25: =IF($A25>=Annahmen!$B$125,Annahmen!$B$126,0) -> 0 | P25: =O25*Annahmen!$B$127 -> 0 | Q25: =F25+J25+N25+P25 -> 4.4615888 | R25: =O25*Annahmen!$B$47+(C25+G25+K25)*Annahmen!$B$128 -> 0 | S25: =SUMPRODUCT((((Annahmen!$C$145:$C$155="monatlich")*(Annahmen!$D$145:$D$155<=$A25))+((Annahmen!$C$145:$C$155="einmalig")*(Annahmen!$D$145:$D$155=$A25)))*Annahmen!$B$145:$B$155*Annahmen!$G$145:$G$155) -> 28.360493 | T25: =IF($A25>=Annahmen!$B$109,Annahmen!$B$136,0) -> 0 | U25: =Q25-R25-S25-T25 -> -23.898904 | V25: =V24+U25 -> -369.16077 | W25: =IF(U25>0,1,0) -> 0 | X25: =IF(V25>=0,1,0) -> 0
A26: 9 | B26: 09/2027 | C26: =IF($A26>=Annahmen!$B$109,Annahmen!$B$110,0) -> 2 | D26: =D25+C26 -> 8 | E26: =D26*Annahmen!$B$113 -> 1.6 | F26: =E26*Annahmen!$B$116/(1+Annahmen!$B$9)*Annahmen!$B$129 -> 2.3472897 | G26: =IF($A26>=Annahmen!$B$109,Annahmen!$B$111,0) -> 1 | H26: =H25+G26 -> 4 | I26: =H26*Annahmen!$B$114 -> 0.4 | J26: =I26*Annahmen!$B$117/(1+Annahmen!$B$9)*Annahmen!$B$130 -> 1.6428037 | K26: =IF($A26>=Annahmen!$B$109,Annahmen!$B$112,0) -> 1 | L26: =L25+K26 -> 4 | M26: =L26*Annahmen!$B$115 -> 0.8 | N26: =M26*Annahmen!$B$118/(1+Annahmen!$B$9)*Annahmen!$B$129 -> 1.9586916 | O26: =IF($A26>=Annahmen!$B$125,Annahmen!$B$126,0) -> 0 | P26: =O26*Annahmen!$B$127 -> 0 | Q26: =F26+J26+N26+P26 -> 5.948785 | R26: =O26*Annahmen!$B$47+(C26+G26+K26)*Annahmen!$B$128 -> 0 | S26: =SUMPRODUCT((((Annahmen!$C$145:$C$155="monatlich")*(Annahmen!$D$145:$D$155<=$A26))+((Annahmen!$C$145:$C$155="einmalig")*(Annahmen!$D$145:$D$155=$A26)))*Annahmen!$B$145:$B$155*Annahmen!$G$145:$G$155) -> 28.360493 | T26: =IF($A26>=Annahmen!$B$109,Annahmen!$B$136,0) -> 0 | U26: =Q26-R26-S26-T26 -> -22.411708 | V26: =V25+U26 -> -391.57248 | W26: =IF(U26>0,1,0) -> 0 | X26: =IF(V26>=0,1,0) -> 0
A27: 10 | B27: 10/2027 | C27: =IF($A27>=Annahmen!$B$109,Annahmen!$B$110,0) -> 2 | D27: =D26+C27 -> 10 | E27: =D27*Annahmen!$B$113 -> 2 | F27: =E27*Annahmen!$B$116/(1+Annahmen!$B$9)*Annahmen!$B$129 -> 2.9341121 | G27: =IF($A27>=Annahmen!$B$109,Annahmen!$B$111,0) -> 1 | H27: =H26+G27 -> 5 | I27: =H27*Annahmen!$B$114 -> 0.5 | J27: =I27*Annahmen!$B$117/(1+Annahmen!$B$9)*Annahmen!$B$130 -> 2.0535047 | K27: =IF($A27>=Annahmen!$B$109,Annahmen!$B$112,0) -> 1 | L27: =L26+K27 -> 5 | M27: =L27*Annahmen!$B$115 -> 1 | N27: =M27*Annahmen!$B$118/(1+Annahmen!$B$9)*Annahmen!$B$129 -> 2.4483645 | O27: =IF($A27>=Annahmen!$B$125,Annahmen!$B$126,0) -> 0 | P27: =O27*Annahmen!$B$127 -> 0 | Q27: =F27+J27+N27+P27 -> 7.4359813 | R27: =O27*Annahmen!$B$47+(C27+G27+K27)*Annahmen!$B$128 -> 0 | S27: =SUMPRODUCT((((Annahmen!$C$145:$C$155="monatlich")*(Annahmen!$D$145:$D$155<=$A27))+((Annahmen!$C$145:$C$155="einmalig")*(Annahmen!$D$145:$D$155=$A27)))*Annahmen!$B$145:$B$155*Annahmen!$G$145:$G$155) -> 28.360493 | T27: =IF($A27>=Annahmen!$B$109,Annahmen!$B$136,0) -> 0 | U27: =Q27-R27-S27-T27 -> -20.924512 | V27: =V26+U27 -> -412.49699 | W27: =IF(U27>0,1,0) -> 0 | X27: =IF(V27>=0,1,0) -> 0
A28: 11 | B28: 11/2027 | C28: =IF($A28>=Annahmen!$B$109,Annahmen!$B$110,0) -> 2 | D28: =D27+C28 -> 12 | E28: =D28*Annahmen!$B$113 -> 2.4 | F28: =E28*Annahmen!$B$116/(1+Annahmen!$B$9)*Annahmen!$B$129 -> 3.5209346 | G28: =IF($A28>=Annahmen!$B$109,Annahmen!$B$111,0) -> 1 | H28: =H27+G28 -> 6 | I28: =H28*Annahmen!$B$114 -> 0.6 | J28: =I28*Annahmen!$B$117/(1+Annahmen!$B$9)*Annahmen!$B$130 -> 2.4642056 | K28: =IF($A28>=Annahmen!$B$109,Annahmen!$B$112,0) -> 1 | L28: =L27+K28 -> 6 | M28: =L28*Annahmen!$B$115 -> 1.2 | N28: =M28*Annahmen!$B$118/(1+Annahmen!$B$9)*Annahmen!$B$129 -> 2.9380374 | O28: =IF($A28>=Annahmen!$B$125,Annahmen!$B$126,0) -> 0 | P28: =O28*Annahmen!$B$127 -> 0 | Q28: =F28+J28+N28+P28 -> 8.9231776 | R28: =O28*Annahmen!$B$47+(C28+G28+K28)*Annahmen!$B$128 -> 0 | S28: =SUMPRODUCT((((Annahmen!$C$145:$C$155="monatlich")*(Annahmen!$D$145:$D$155<=$A28))+((Annahmen!$C$145:$C$155="einmalig")*(Annahmen!$D$145:$D$155=$A28)))*Annahmen!$B$145:$B$155*Annahmen!$G$145:$G$155) -> 28.360493 | T28: =IF($A28>=Annahmen!$B$109,Annahmen!$B$136,0) -> 0 | U28: =Q28-R28-S28-T28 -> -19.437316 | V28: =V27+U28 -> -431.9343 | W28: =IF(U28>0,1,0) -> 0 | X28: =IF(V28>=0,1,0) -> 0
A29: 12 | B29: 12/2027 | C29: =IF($A29>=Annahmen!$B$109,Annahmen!$B$110,0) -> 2 | D29: =D28+C29 -> 14 | E29: =D29*Annahmen!$B$113 -> 2.8 | F29: =E29*Annahmen!$B$116/(1+Annahmen!$B$9)*Annahmen!$B$129 -> 4.107757 | G29: =IF($A29>=Annahmen!$B$109,Annahmen!$B$111,0) -> 1 | H29: =H28+G29 -> 7 | I29: =H29*Annahmen!$B$114 -> 0.7 | J29: =I29*Annahmen!$B$117/(1+Annahmen!$B$9)*Annahmen!$B$130 -> 2.8749065 | K29: =IF($A29>=Annahmen!$B$109,Annahmen!$B$112,0) -> 1 | L29: =L28+K29 -> 7 | M29: =L29*Annahmen!$B$115 -> 1.4 | N29: =M29*Annahmen!$B$118/(1+Annahmen!$B$9)*Annahmen!$B$129 -> 3.4277103 | O29: =IF($A29>=Annahmen!$B$125,Annahmen!$B$126,0) -> 0 | P29: =O29*Annahmen!$B$127 -> 0 | Q29: =F29+J29+N29+P29 -> 10.410374 | R29: =O29*Annahmen!$B$47+(C29+G29+K29)*Annahmen!$B$128 -> 0 | S29: =SUMPRODUCT((((Annahmen!$C$145:$C$155="monatlich")*(Annahmen!$D$145:$D$155<=$A29))+((Annahmen!$C$145:$C$155="einmalig")*(Annahmen!$D$145:$D$155=$A29)))*Annahmen!$B$145:$B$155*Annahmen!$G$145:$G$155) -> 28.360493 | T29: =IF($A29>=Annahmen!$B$109,Annahmen!$B$136,0) -> 0 | U29: =Q29-R29-S29-T29 -> -17.950119 | V29: =V28+U29 -> -449.88442 | W29: =IF(U29>0,1,0) -> 0 | X29: =IF(V29>=0,1,0) -> 0
A30: 13 | B30: 01/2028 | C30: =IF($A30>=Annahmen!$B$109,Annahmen!$B$110,0) -> 2 | D30: =D29+C30 -> 16 | E30: =D30*Annahmen!$B$113 -> 3.2 | F30: =E30*Annahmen!$B$116/(1+Annahmen!$B$9)*Annahmen!$B$129 -> 4.6945794 | G30: =IF($A30>=Annahmen!$B$109,Annahmen!$B$111,0) -> 1 | H30: =H29+G30 -> 8 | I30: =H30*Annahmen!$B$114 -> 0.8 | J30: =I30*Annahmen!$B$117/(1+Annahmen!$B$9)*Annahmen!$B$130 -> 3.2856075 | K30: =IF($A30>=Annahmen!$B$109,Annahmen!$B$112,0) -> 1 | L30: =L29+K30 -> 8 | M30: =L30*Annahmen!$B$115 -> 1.6 | N30: =M30*Annahmen!$B$118/(1+Annahmen!$B$9)*Annahmen!$B$129 -> 3.9173832 | O30: =IF($A30>=Annahmen!$B$125,Annahmen!$B$126,0) -> 0 | P30: =O30*Annahmen!$B$127 -> 0 | Q30: =F30+J30+N30+P30 -> 11.89757 | R30: =O30*Annahmen!$B$47+(C30+G30+K30)*Annahmen!$B$128 -> 0 | S30: =SUMPRODUCT((((Annahmen!$C$145:$C$155="monatlich")*(Annahmen!$D$145:$D$155<=$A30))+((Annahmen!$C$145:$C$155="einmalig")*(Annahmen!$D$145:$D$155=$A30)))*Annahmen!$B$145:$B$155*Annahmen!$G$145:$G$155) -> 28.360493 | T30: =IF($A30>=Annahmen!$B$109,Annahmen!$B$136,0) -> 0 | U30: =Q30-R30-S30-T30 -> -16.462923 | V30: =V29+U30 -> -466.34735 | W30: =IF(U30>0,1,0) -> 0 | X30: =IF(V30>=0,1,0) -> 0
... A41: 24 | B41: 12/2028 | C41: =IF($A41>=Annahmen!$B$109,Annahmen!$B$110,0) -> 2 | D41: =D40+C41 -> 38 | E41: =D41*Annahmen!$B$113 -> 7.6 | F41: =E41*Annahmen!$B$116/(1+Annahmen!$B$9)*Annahmen!$B$129 -> 11.149626 | G41: =IF($A41>=Annahmen!$B$109,Annahmen!$B$111,0) -> 1 | H41: =H40+G41 -> 19 | I41: =H41*Annahmen!$B$114 -> 1.9 | J41: =I41*Annahmen!$B$117/(1+Annahmen!$B$9)*Annahmen!$B$130 -> 7.8033178 | K41: =IF($A41>=Annahmen!$B$109,Annahmen!$B$112,0) -> 1 | L41: =L40+K41 -> 19 | M41: =L41*Annahmen!$B$115 -> 3.8 | N41: =M41*Annahmen!$B$118/(1+Annahmen!$B$9)*Annahmen!$B$129 -> 9.303785 | O41: =IF($A41>=Annahmen!$B$125,Annahmen!$B$126,0) -> 0 | P41: =O41*Annahmen!$B$127 -> 0 | Q41: =F41+J41+N41+P41 -> 28.256729 | R41: =O41*Annahmen!$B$47+(C41+G41+K41)*Annahmen!$B$128 -> 0 | S41: =SUMPRODUCT((((Annahmen!$C$145:$C$155="monatlich")*(Annahmen!$D$145:$D$155<=$A41))+((Annahmen!$C$145:$C$155="einmalig")*(Annahmen!$D$145:$D$155=$A41)))*Annahmen!$B$145:$B$155*Annahmen!$G$145:$G$155) -> 28.360493 | T41: =IF($A41>=Annahmen!$B$109,Annahmen!$B$136,0) -> 0 | U41: =Q41-R41-S41-T41 -> -0.10376419 | V41: =V40+U41 -> -549.28455 | W41: =IF(U41>0,1,0) -> 0 | X41: =IF(V41>=0,1,0) -> 0
A45: ="Szenario mittel – "&Annahmen!$C$133 -> Szenario mittel – profitabler Nebenerwerb
A46: Monat | B46: Datum | C46: Neue E-Books | D46: E-Books kum. | E46: Verkäufe E-Book | F46: Ertrag E-Book | G46: Neue Hörbücher | H46: Hörbücher kum. | I46: Verkäufe Hörbuch | J46: Ertrag Hörbuch | K46: Neue zweispr. | L46: Zweispr. kum. | M46: Verkäufe zweispr. | N46: Ertrag zweispr. | O46: Self-Pub Aufträge | P46: Self-Pub Umsatz | Q46: Umsatz gesamt | R46: Variable Kosten | S46: Fixkosten anteilig | T46: Marketing | U46: Ergebnis | V46: Ergebnis kumuliert | W46: BE monatl. | X46: BE kum.
A47: 1 | B47: 01/2027 | C47: =IF($A47>=Annahmen!$C$109,Annahmen!$C$110,0) -> 0 | D47: =C47 -> 0 | E47: =D47*Annahmen!$C$113 -> 0 | F47: =E47*Annahmen!$B$116/(1+Annahmen!$B$9)*Annahmen!$B$129 -> 0 | G47: =IF($A47>=Annahmen!$C$109,Annahmen!$C$111,0) -> 0 | H47: =G47 -> 0 | I47: =H47*Annahmen!$C$114 -> 0 | J47: =I47*Annahmen!$B$117/(1+Annahmen!$B$9)*Annahmen!$B$130 -> 0 | K47: =IF($A47>=Annahmen!$C$109,Annahmen!$C$112,0) -> 0 | L47: =K47 -> 0 | M47: =L47*Annahmen!$C$115 -> 0 | N47: =M47*Annahmen!$B$118/(1+Annahmen!$B$9)*Annahmen!$B$129 -> 0 | O47: =IF($A47>=Annahmen!$C$125,Annahmen!$C$126,0) -> 0 | P47: =O47*Annahmen!$B$127 -> 0 | Q47: =F47+J47+N47+P47 -> 0 | R47: =O47*Annahmen!$B$47+(C47+G47+K47)*Annahmen!$B$128 -> 0 | S47: =SUMPRODUCT((((Annahmen!$C$145:$C$155="monatlich")*(Annahmen!$D$145:$D$155<=$A47))+((Annahmen!$C$145:$C$155="einmalig")*(Annahmen!$D$145:$D$155=$A47)))*Annahmen!$B$145:$B$155*Annahmen!$G$145:$G$155) -> 109.56049 | T47: =IF($A47>=Annahmen!$C$109,Annahmen!$C$136,0) -> 0 | U47: =Q47-R47-S47-T47 -> -109.56049 | V47: =U47 -> -109.56049 | W47: =IF(U47>0,1,0) -> 0 | X47: =IF(V47>=0,1,0) -> 0
A48: 2 | B48: 02/2027 | C48: =IF($A48>=Annahmen!$C$109,Annahmen!$C$110,0) -> 0 | D48: =D47+C48 -> 0 | E48: =D48*Annahmen!$C$113 -> 0 | F48: =E48*Annahmen!$B$116/(1+Annahmen!$B$9)*Annahmen!$B$129 -> 0 | G48: =IF($A48>=Annahmen!$C$109,Annahmen!$C$111,0) -> 0 | H48: =H47+G48 -> 0 | I48: =H48*Annahmen!$C$114 -> 0 | J48: =I48*Annahmen!$B$117/(1+Annahmen!$B$9)*Annahmen!$B$130 -> 0 | K48: =IF($A48>=Annahmen!$C$109,Annahmen!$C$112,0) -> 0 | L48: =L47+K48 -> 0 | M48: =L48*Annahmen!$C$115 -> 0 | N48: =M48*Annahmen!$B$118/(1+Annahmen!$B$9)*Annahmen!$B$129 -> 0 | O48: =IF($A48>=Annahmen!$C$125,Annahmen!$C$126,0) -> 0 | P48: =O48*Annahmen!$B$127 -> 0 | Q48: =F48+J48+N48+P48 -> 0 | R48: =O48*Annahmen!$B$47+(C48+G48+K48)*Annahmen!$B$128 -> 0 | S48: =SUMPRODUCT((((Annahmen!$C$145:$C$155="monatlich")*(Annahmen!$D$145:$D$155<=$A48))+((Annahmen!$C$145:$C$155="einmalig")*(Annahmen!$D$145:$D$155=$A48)))*Annahmen!$B$145:$B$155*Annahmen!$G$145:$G$155) -> 28.360493 | T48: =IF($A48>=Annahmen!$C$109,Annahmen!$C$136,0) -> 0 | U48: =Q48-R48-S48-T48 -> -28.360493 | V48: =V47+U48 -> -137.92099 | W48: =IF(U48>0,1,0) -> 0 | X48: =IF(V48>=0,1,0) -> 0
A49: 3 | B49: 03/2027 | C49: =IF($A49>=Annahmen!$C$109,Annahmen!$C$110,0) -> 0 | D49: =D48+C49 -> 0 | E49: =D49*Annahmen!$C$113 -> 0 | F49: =E49*Annahmen!$B$116/(1+Annahmen!$B$9)*Annahmen!$B$129 -> 0 | G49: =IF($A49>=Annahmen!$C$109,Annahmen!$C$111,0) -> 0 | H49: =H48+G49 -> 0 | I49: =H49*Annahmen!$C$114 -> 0 | J49: =I49*Annahmen!$B$117/(1+Annahmen!$B$9)*Annahmen!$B$130 -> 0 | K49: =IF($A49>=Annahmen!$C$109,Annahmen!$C$112,0) -> 0 | L49: =L48+K49 -> 0 | M49: =L49*Annahmen!$C$115 -> 0 | N49: =M49*Annahmen!$B$118/(1+Annahmen!$B$9)*Annahmen!$B$129 -> 0 | O49: =IF($A49>=Annahmen!$C$125,Annahmen!$C$126,0) -> 0 | P49: =O49*Annahmen!$B$127 -> 0 | Q49: =F49+J49+N49+P49 -> 0 | R49: =O49*Annahmen!$B$47+(C49+G49+K49)*Annahmen!$B$128 -> 0 | S49: =SUMPRODUCT((((Annahmen!$C$145:$C$155="monatlich")*(Annahmen!$D$145:$D$155<=$A49))+((Annahmen!$C$145:$C$155="einmalig")*(Annahmen!$D$145:$D$155=$A49)))*Annahmen!$B$145:$B$155*Annahmen!$G$145:$G$155) -> 98.360493 | T49: =IF($A49>=Annahmen!$C$109,Annahmen!$C$136,0) -> 0 | U49: =Q49-R49-S49-T49 -> -98.360493 | V49: =V48+U49 -> -236.28148 | W49: =IF(U49>0,1,0) -> 0 | X49: =IF(V49>=0,1,0) -> 0
A50: 4 | B50: 04/2027 | C50: =IF($A50>=Annahmen!$C$109,Annahmen!$C$110,0) -> 5 | D50: =D49+C50 -> 5 | E50: =D50*Annahmen!$C$113 -> 2 | F50: =E50*Annahmen!$B$116/(1+Annahmen!$B$9)*Annahmen!$B$129 -> 2.9341121 | G50: =IF($A50>=Annahmen!$C$109,Annahmen!$C$111,0) -> 3 | H50: =H49+G50 -> 3 | I50: =H50*Annahmen!$C$114 -> 0.9 | J50: =I50*Annahmen!$B$117/(1+Annahmen!$B$9)*Annahmen!$B$130 -> 3.6963084 | K50: =IF($A50>=Annahmen!$C$109,Annahmen!$C$112,0) -> 3 | L50: =L49+K50 -> 3 | M50: =L50*Annahmen!$C$115 -> 1.2 | N50: =M50*Annahmen!$B$118/(1+Annahmen!$B$9)*Annahmen!$B$129 -> 2.9380374 | O50: =IF($A50>=Annahmen!$C$125,Annahmen!$C$126,0) -> 0 | P50: =O50*Annahmen!$B$127 -> 0 | Q50: =F50+J50+N50+P50 -> 9.5684579 | R50: =O50*Annahmen!$B$47+(C50+G50+K50)*Annahmen!$B$128 -> 0 | S50: =SUMPRODUCT((((Annahmen!$C$145:$C$155="monatlich")*(Annahmen!$D$145:$D$155<=$A50))+((Annahmen!$C$145:$C$155="einmalig")*(Annahmen!$D$145:$D$155=$A50)))*Annahmen!$B$145:$B$155*Annahmen!$G$145:$G$155) -> 28.360493 | T50: =IF($A50>=Annahmen!$C$109,Annahmen!$C$136,0) -> 100 | U50: =Q50-R50-S50-T50 -> -118.79204 | V50: =V49+U50 -> -355.07351 | W50: =IF(U50>0,1,0) -> 0 | X50: =IF(V50>=0,1,0) -> 0
A51: 5 | B51: 05/2027 | C51: =IF($A51>=Annahmen!$C$109,Annahmen!$C$110,0) -> 5 | D51: =D50+C51 -> 10 | E51: =D51*Annahmen!$C$113 -> 4 | F51: =E51*Annahmen!$B$116/(1+Annahmen!$B$9)*Annahmen!$B$129 -> 5.8682243 | G51: =IF($A51>=Annahmen!$C$109,Annahmen!$C$111,0) -> 3 | H51: =H50+G51 -> 6 | I51: =H51*Annahmen!$C$114 -> 1.8 | J51: =I51*Annahmen!$B$117/(1+Annahmen!$B$9)*Annahmen!$B$130 -> 7.3926168 | K51: =IF($A51>=Annahmen!$C$109,Annahmen!$C$112,0) -> 3 | L51: =L50+K51 -> 6 | M51: =L51*Annahmen!$C$115 -> 2.4 | N51: =M51*Annahmen!$B$118/(1+Annahmen!$B$9)*Annahmen!$B$129 -> 5.8760748 | O51: =IF($A51>=Annahmen!$C$125,Annahmen!$C$126,0) -> 0 | P51: =O51*Annahmen!$B$127 -> 0 | Q51: =F51+J51+N51+P51 -> 19.136916 | R51: =O51*Annahmen!$B$47+(C51+G51+K51)*Annahmen!$B$128 -> 0 | S51: =SUMPRODUCT((((Annahmen!$C$145:$C$155="monatlich")*(Annahmen!$D$145:$D$155<=$A51))+((Annahmen!$C$145:$C$155="einmalig")*(Annahmen!$D$145:$D$155=$A51)))*Annahmen!$B$145:$B$155*Annahmen!$G$145:$G$155) -> 28.360493 | T51: =IF($A51>=Annahmen!$C$109,Annahmen!$C$136,0) -> 100 | U51: =Q51-R51-S51-T51 -> -109.22358 | V51: =V50+U51 -> -464.29709 | W51: =IF(U51>0,1,0) -> 0 | X51: =IF(V51>=0,1,0) -> 0
A52: 6 | B52: 06/2027 | C52: =IF($A52>=Annahmen!$C$109,Annahmen!$C$110,0) -> 5 | D52: =D51+C52 -> 15 | E52: =D52*Annahmen!$C$113 -> 6 | F52: =E52*Annahmen!$B$116/(1+Annahmen!$B$9)*Annahmen!$B$129 -> 8.8023364 | G52: =IF($A52>=Annahmen!$C$109,Annahmen!$C$111,0) -> 3 | H52: =H51+G52 -> 9 | I52: =H52*Annahmen!$C$114 -> 2.7 | J52: =I52*Annahmen!$B$117/(1+Annahmen!$B$9)*Annahmen!$B$130 -> 11.088925 | K52: =IF($A52>=Annahmen!$C$109,Annahmen!$C$112,0) -> 3 | L52: =L51+K52 -> 9 | M52: =L52*Annahmen!$C$115 -> 3.6 | N52: =M52*Annahmen!$B$118/(1+Annahmen!$B$9)*Annahmen!$B$129 -> 8.8141121 | O52: =IF($A52>=Annahmen!$C$125,Annahmen!$C$126,0) -> 0 | P52: =O52*Annahmen!$B$127 -> 0 | Q52: =F52+J52+N52+P52 -> 28.705374 | R52: =O52*Annahmen!$B$47+(C52+G52+K52)*Annahmen!$B$128 -> 0 | S52: =SUMPRODUCT((((Annahmen!$C$145:$C$155="monatlich")*(Annahmen!$D$145:$D$155<=$A52))+((Annahmen!$C$145:$C$155="einmalig")*(Annahmen!$D$145:$D$155=$A52)))*Annahmen!$B$145:$B$155*Annahmen!$G$145:$G$155) -> 28.360493 | T52: =IF($A52>=Annahmen!$C$109,Annahmen!$C$136,0) -> 100 | U52: =Q52-R52-S52-T52 -> -99.655119 | V52: =V51+U52 -> -563.95221 | W52: =IF(U52>0,1,0) -> 0 | X52: =IF(V52>=0,1,0) -> 0
A53: 7 | B53: 07/2027 | C53: =IF($A53>=Annahmen!$C$109,Annahmen!$C$110,0) -> 5 | D53: =D52+C53 -> 20 | E53: =D53*Annahmen!$C$113 -> 8 | F53: =E53*Annahmen!$B$116/(1+Annahmen!$B$9)*Annahmen!$B$129 -> 11.736449 | G53: =IF($A53>=Annahmen!$C$109,Annahmen!$C$111,0) -> 3 | H53: =H52+G53 -> 12 | I53: =H53*Annahmen!$C$114 -> 3.6 | J53: =I53*Annahmen!$B$117/(1+Annahmen!$B$9)*Annahmen!$B$130 -> 14.785234 | K53: =IF($A53>=Annahmen!$C$109,Annahmen!$C$112,0) -> 3 | L53: =L52+K53 -> 12 | M53: =L53*Annahmen!$C$115 -> 4.8 | N53: =M53*Annahmen!$B$118/(1+Annahmen!$B$9)*Annahmen!$B$129 -> 11.75215 | O53: =IF($A53>=Annahmen!$C$125,Annahmen!$C$126,0) -> 0 | P53: =O53*Annahmen!$B$127 -> 0 | Q53: =F53+J53+N53+P53 -> 38.273832 | R53: =O53*Annahmen!$B$47+(C53+G53+K53)*Annahmen!$B$128 -> 0 | S53: =SUMPRODUCT((((Annahmen!$C$145:$C$155="monatlich")*(Annahmen!$D$145:$D$155<=$A53))+((Annahmen!$C$145:$C$155="einmalig")*(Annahmen!$D$145:$D$155=$A53)))*Annahmen!$B$145:$B$155*Annahmen!$G$145:$G$155) -> 28.360493 | T53: =IF($A53>=Annahmen!$C$109,Annahmen!$C$136,0) -> 100 | U53: =Q53-R53-S53-T53 -> -90.086661 | V53: =V52+U53 -> -654.03887 | W53: =IF(U53>0,1,0) -> 0 | X53: =IF(V53>=0,1,0) -> 0
A54: 8 | B54: 08/2027 | C54: =IF($A54>=Annahmen!$C$109,Annahmen!$C$110,0) -> 5 | D54: =D53+C54 -> 25 | E54: =D54*Annahmen!$C$113 -> 10 | F54: =E54*Annahmen!$B$116/(1+Annahmen!$B$9)*Annahmen!$B$129 -> 14.670561 | G54: =IF($A54>=Annahmen!$C$109,Annahmen!$C$111,0) -> 3 | H54: =H53+G54 -> 15 | I54: =H54*Annahmen!$C$114 -> 4.5 | J54: =I54*Annahmen!$B$117/(1+Annahmen!$B$9)*Annahmen!$B$130 -> 18.481542 | K54: =IF($A54>=Annahmen!$C$109,Annahmen!$C$112,0) -> 3 | L54: =L53+K54 -> 15 | M54: =L54*Annahmen!$C$115 -> 6 | N54: =M54*Annahmen!$B$118/(1+Annahmen!$B$9)*Annahmen!$B$129 -> 14.690187 | O54: =IF($A54>=Annahmen!$C$125,Annahmen!$C$126,0) -> 0 | P54: =O54*Annahmen!$B$127 -> 0 | Q54: =F54+J54+N54+P54 -> 47.84229 | R54: =O54*Annahmen!$B$47+(C54+G54+K54)*Annahmen!$B$128 -> 0 | S54: =SUMPRODUCT((((Annahmen!$C$145:$C$155="monatlich")*(Annahmen!$D$145:$D$155<=$A54))+((Annahmen!$C$145:$C$155="einmalig")*(Annahmen!$D$145:$D$155=$A54)))*Annahmen!$B$145:$B$155*Annahmen!$G$145:$G$155) -> 28.360493 | T54: =IF($A54>=Annahmen!$C$109,Annahmen!$C$136,0) -> 100 | U54: =Q54-R54-S54-T54 -> -80.518203 | V54: =V53+U54 -> -734.55708 | W54: =IF(U54>0,1,0) -> 0 | X54: =IF(V54>=0,1,0) -> 0
A55: 9 | B55: 09/2027 | C55: =IF($A55>=Annahmen!$C$109,Annahmen!$C$110,0) -> 5 | D55: =D54+C55 -> 30 | E55: =D55*Annahmen!$C$113 -> 12 | F55: =E55*Annahmen!$B$116/(1+Annahmen!$B$9)*Annahmen!$B$129 -> 17.604673 | G55: =IF($A55>=Annahmen!$C$109,Annahmen!$C$111,0) -> 3 | H55: =H54+G55 -> 18 | I55: =H55*Annahmen!$C$114 -> 5.4 | J55: =I55*Annahmen!$B$117/(1+Annahmen!$B$9)*Annahmen!$B$130 -> 22.17785 | K55: =IF($A55>=Annahmen!$C$109,Annahmen!$C$112,0) -> 3 | L55: =L54+K55 -> 18 | M55: =L55*Annahmen!$C$115 -> 7.2 | N55: =M55*Annahmen!$B$118/(1+Annahmen!$B$9)*Annahmen!$B$129 -> 17.628224 | O55: =IF($A55>=Annahmen!$C$125,Annahmen!$C$126,0) -> 0 | P55: =O55*Annahmen!$B$127 -> 0 | Q55: =F55+J55+N55+P55 -> 57.410748 | R55: =O55*Annahmen!$B$47+(C55+G55+K55)*Annahmen!$B$128 -> 0 | S55: =SUMPRODUCT((((Annahmen!$C$145:$C$155="monatlich")*(Annahmen!$D$145:$D$155<=$A55))+((Annahmen!$C$145:$C$155="einmalig")*(Annahmen!$D$145:$D$155=$A55)))*Annahmen!$B$145:$B$155*Annahmen!$G$145:$G$155) -> 28.360493 | T55: =IF($A55>=Annahmen!$C$109,Annahmen!$C$136,0) -> 100 | U55: =Q55-R55-S55-T55 -> -70.949746 | V55: =V54+U55 -> -805.50682 | W55: =IF(U55>0,1,0) -> 0 | X55: =IF(V55>=0,1,0) -> 0
A56: 10 | B56: 10/2027 | C56: =IF($A56>=Annahmen!$C$109,Annahmen!$C$110,0) -> 5 | D56: =D55+C56 -> 35 | E56: =D56*Annahmen!$C$113 -> 14 | F56: =E56*Annahmen!$B$116/(1+Annahmen!$B$9)*Annahmen!$B$129 -> 20.538785 | G56: =IF($A56>=Annahmen!$C$109,Annahmen!$C$111,0) -> 3 | H56: =H55+G56 -> 21 | I56: =H56*Annahmen!$C$114 -> 6.3 | J56: =I56*Annahmen!$B$117/(1+Annahmen!$B$9)*Annahmen!$B$130 -> 25.874159 | K56: =IF($A56>=Annahmen!$C$109,Annahmen!$C$112,0) -> 3 | L56: =L55+K56 -> 21 | M56: =L56*Annahmen!$C$115 -> 8.4 | N56: =M56*Annahmen!$B$118/(1+Annahmen!$B$9)*Annahmen!$B$129 -> 20.566262 | O56: =IF($A56>=Annahmen!$C$125,Annahmen!$C$126,0) -> 0.5 | P56: =O56*Annahmen!$B$127 -> 195 | Q56: =F56+J56+N56+P56 -> 261.97921 | R56: =O56*Annahmen!$B$47+(C56+G56+K56)*Annahmen!$B$128 -> 4.3358716 | S56: =SUMPRODUCT((((Annahmen!$C$145:$C$155="monatlich")*(Annahmen!$D$145:$D$155<=$A56))+((Annahmen!$C$145:$C$155="einmalig")*(Annahmen!$D$145:$D$155=$A56)))*Annahmen!$B$145:$B$155*Annahmen!$G$145:$G$155) -> 28.360493 | T56: =IF($A56>=Annahmen!$C$109,Annahmen!$C$136,0) -> 100 | U56: =Q56-R56-S56-T56 -> 129.28284 | V56: =V55+U56 -> -676.22398 | W56: =IF(U56>0,1,0) -> 1 | X56: =IF(V56>=0,1,0) -> 0
A57: 11 | B57: 11/2027 | C57: =IF($A57>=Annahmen!$C$109,Annahmen!$C$110,0) -> 5 | D57: =D56+C57 -> 40 | E57: =D57*Annahmen!$C$113 -> 16 | F57: =E57*Annahmen!$B$116/(1+Annahmen!$B$9)*Annahmen!$B$129 -> 23.472897 | G57: =IF($A57>=Annahmen!$C$109,Annahmen!$C$111,0) -> 3 | H57: =H56+G57 -> 24 | I57: =H57*Annahmen!$C$114 -> 7.2 | J57: =I57*Annahmen!$B$117/(1+Annahmen!$B$9)*Annahmen!$B$130 -> 29.570467 | K57: =IF($A57>=Annahmen!$C$109,Annahmen!$C$112,0) -> 3 | L57: =L56+K57 -> 24 | M57: =L57*Annahmen!$C$115 -> 9.6 | N57: =M57*Annahmen!$B$118/(1+Annahmen!$B$9)*Annahmen!$B$129 -> 23.504299 | O57: =IF($A57>=Annahmen!$C$125,Annahmen!$C$126,0) -> 0.5 | P57: =O57*Annahmen!$B$127 -> 195 | Q57: =F57+J57+N57+P57 -> 271.54766 | R57: =O57*Annahmen!$B$47+(C57+G57+K57)*Annahmen!$B$128 -> 4.3358716 | S57: =SUMPRODUCT((((Annahmen!$C$145:$C$155="monatlich")*(Annahmen!$D$145:$D$155<=$A57))+((Annahmen!$C$145:$C$155="einmalig")*(Annahmen!$D$145:$D$155=$A57)))*Annahmen!$B$145:$B$155*Annahmen!$G$145:$G$155) -> 28.360493 | T57: =IF($A57>=Annahmen!$C$109,Annahmen!$C$136,0) -> 100 | U57: =Q57-R57-S57-T57 -> 138.8513 | V57: =V56+U57 -> -537.37268 | W57: =IF(U57>0,1,0) -> 1 | X57: =IF(V57>=0,1,0) -> 0
A58: 12 | B58: 12/2027 | C58: =IF($A58>=Annahmen!$C$109,Annahmen!$C$110,0) -> 5 | D58: =D57+C58 -> 45 | E58: =D58*Annahmen!$C$113 -> 18 | F58: =E58*Annahmen!$B$116/(1+Annahmen!$B$9)*Annahmen!$B$129 -> 26.407009 | G58: =IF($A58>=Annahmen!$C$109,Annahmen!$C$111,0) -> 3 | H58: =H57+G58 -> 27 | I58: =H58*Annahmen!$C$114 -> 8.1 | J58: =I58*Annahmen!$B$117/(1+Annahmen!$B$9)*Annahmen!$B$130 -> 33.266776 | K58: =IF($A58>=Annahmen!$C$109,Annahmen!$C$112,0) -> 3 | L58: =L57+K58 -> 27 | M58: =L58*Annahmen!$C$115 -> 10.8 | N58: =M58*Annahmen!$B$118/(1+Annahmen!$B$9)*Annahmen!$B$129 -> 26.442336 | O58: =IF($A58>=Annahmen!$C$125,Annahmen!$C$126,0) -> 0.5 | P58: =O58*Annahmen!$B$127 -> 195 | Q58: =F58+J58+N58+P58 -> 281.11612 | R58: =O58*Annahmen!$B$47+(C58+G58+K58)*Annahmen!$B$128 -> 4.3358716 | S58: =SUMPRODUCT((((Annahmen!$C$145:$C$155="monatlich")*(Annahmen!$D$145:$D$155<=$A58))+((Annahmen!$C$145:$C$155="einmalig")*(Annahmen!$D$145:$D$155=$A58)))*Annahmen!$B$145:$B$155*Annahmen!$G$145:$G$155) -> 28.360493 | T58: =IF($A58>=Annahmen!$C$109,Annahmen!$C$136,0) -> 100 | U58: =Q58-R58-S58-T58 -> 148.41976 | V58: =V57+U58 -> -388.95293 | W58: =IF(U58>0,1,0) -> 1 | X58: =IF(V58>=0,1,0) -> 0
A59: 13 | B59: 01/2028 | C59: =IF($A59>=Annahmen!$C$109,Annahmen!$C$110,0) -> 5 | D59: =D58+C59 -> 50 | E59: =D59*Annahmen!$C$113 -> 20 | F59: =E59*Annahmen!$B$116/(1+Annahmen!$B$9)*Annahmen!$B$129 -> 29.341121 | G59: =IF($A59>=Annahmen!$C$109,Annahmen!$C$111,0) -> 3 | H59: =H58+G59 -> 30 | I59: =H59*Annahmen!$C$114 -> 9 | J59: =I59*Annahmen!$B$117/(1+Annahmen!$B$9)*Annahmen!$B$130 -> 36.963084 | K59: =IF($A59>=Annahmen!$C$109,Annahmen!$C$112,0) -> 3 | L59: =L58+K59 -> 30 | M59: =L59*Annahmen!$C$115 -> 12 | N59: =M59*Annahmen!$B$118/(1+Annahmen!$B$9)*Annahmen!$B$129 -> 29.380374 | O59: =IF($A59>=Annahmen!$C$125,Annahmen!$C$126,0) -> 0.5 | P59: =O59*Annahmen!$B$127 -> 195 | Q59: =F59+J59+N59+P59 -> 290.68458 | R59: =O59*Annahmen!$B$47+(C59+G59+K59)*Annahmen!$B$128 -> 4.3358716 | S59: =SUMPRODUCT((((Annahmen!$C$145:$C$155="monatlich")*(Annahmen!$D$145:$D$155<=$A59))+((Annahmen!$C$145:$C$155="einmalig")*(Annahmen!$D$145:$D$155=$A59)))*Annahmen!$B$145:$B$155*Annahmen!$G$145:$G$155) -> 28.360493 | T59: =IF($A59>=Annahmen!$C$109,Annahmen!$C$136,0) -> 100 | U59: =Q59-R59-S59-T59 -> 157.98821 | V59: =V58+U59 -> -230.96471 | W59: =IF(U59>0,1,0) -> 1 | X59: =IF(V59>=0,1,0) -> 0
... A70: 24 | B70: 12/2028 | C70: =IF($A70>=Annahmen!$C$109,Annahmen!$C$110,0) -> 5 | D70: =D69+C70 -> 105 | E70: =D70*Annahmen!$C$113 -> 42 | F70: =E70*Annahmen!$B$116/(1+Annahmen!$B$9)*Annahmen!$B$129 -> 61.616355 | G70: =IF($A70>=Annahmen!$C$109,Annahmen!$C$111,0) -> 3 | H70: =H69+G70 -> 63 | I70: =H70*Annahmen!$C$114 -> 18.9 | J70: =I70*Annahmen!$B$117/(1+Annahmen!$B$9)*Annahmen!$B$130 -> 77.622477 | K70: =IF($A70>=Annahmen!$C$109,Annahmen!$C$112,0) -> 3 | L70: =L69+K70 -> 63 | M70: =L70*Annahmen!$C$115 -> 25.2 | N70: =M70*Annahmen!$B$118/(1+Annahmen!$B$9)*Annahmen!$B$129 -> 61.698785 | O70: =IF($A70>=Annahmen!$C$125,Annahmen!$C$126,0) -> 0.5 | P70: =O70*Annahmen!$B$127 -> 195 | Q70: =F70+J70+N70+P70 -> 395.93762 | R70: =O70*Annahmen!$B$47+(C70+G70+K70)*Annahmen!$B$128 -> 4.3358716 | S70: =SUMPRODUCT((((Annahmen!$C$145:$C$155="monatlich")*(Annahmen!$D$145:$D$155<=$A70))+((Annahmen!$C$145:$C$155="einmalig")*(Annahmen!$D$145:$D$155=$A70)))*Annahmen!$B$145:$B$155*Annahmen!$G$145:$G$155) -> 28.360493 | T70: =IF($A70>=Annahmen!$C$109,Annahmen!$C$136,0) -> 100 | U70: =Q70-R70-S70-T70 -> 263.24125 | V70: =V69+U70 -> 2138.4239 | W70: =IF(U70>0,1,0) -> 1 | X70: =IF(V70>=0,1,0) -> 1
A74: ="Szenario stark – "&Annahmen!$D$133 -> Szenario stark – skalierbares Business
A75: Monat | B75: Datum | C75: Neue E-Books | D75: E-Books kum. | E75: Verkäufe E-Book | F75: Ertrag E-Book | G75: Neue Hörbücher | H75: Hörbücher kum. | I75: Verkäufe Hörbuch | J75: Ertrag Hörbuch | K75: Neue zweispr. | L75: Zweispr. kum. | M75: Verkäufe zweispr. | N75: Ertrag zweispr. | O75: Self-Pub Aufträge | P75: Self-Pub Umsatz | Q75: Umsatz gesamt | R75: Variable Kosten | S75: Fixkosten anteilig | T75: Marketing | U75: Ergebnis | V75: Ergebnis kumuliert | W75: BE monatl. | X75: BE kum.
